Workbook
Name Requirement: #REF!
Name Requirement: #REF!
Name Requirement: #REF!
Name Requirement: #REF!
Name Requirement: #REF!
Name Requirement: #REF!
Name Requirement: #REF!
Name Requirement: #REF!
Name Requirement: #REF!
Name Requirement: #REF!
Name Requirement: #REF!
Name Requirement: #REF!
Name Requirement: #REF!
Name Requirement: #REF!
Name Requirement: #REF!
Name Requirement: #REF!
Name Requirement: #REF!
Name Requirement: #REF!
Name Requirement: #REF!
Name Requirement: #REF!
Name StartTime: #REF!
Name StartTime: CALENDAR!#REF!
Name StartTime: #REF!
Name StartTime: #REF!
Name TimeInterval: #REF!
Name TimeInterval: CALENDAR!#REF!
Name TimeInterval: #REF!
Name TimeInterval: #REF!

Sheet CALENDAR
A2: CHECK IN | I2: NIGHTS | J2: =C3-C2 -> 0 | K2: NOME CLIENTE | PROGRAMA
A3: CHECK OUT | D3: 46305 | E3: 46306 | F3: 46307 | G3: 46308 | H3: 46309 | I3: =TEXT(C2,"dd/mm") -> 00/01 | J3: =IF(C2+1<=C3,TEXT(C2+1,"DD/MM"),"") | K3: =IF(C2+2<=C3,TEXT(C2+2,"DD/MM"),"") | L3: =IF(C2+3<=C3,TEXT(C2+3,"DD/MM"),"")
A4: TIME | D4: Sat | E4: Sun | F4: Mon | G4: Tue | H4: Wed | I4: =IF(I3<>"",TEXT(C2,"DDD"),"") -> Sat | J4: =IF(J3<>"",TEXT(C2+1,"DDD"),"") | K4: =IF(K3<>"",TEXT(C2+2,"DDD"),"") | L4: =IF(L3<>"",TEXT(C2+3,"DDD"),"")
A7: 0.29166667 | C7: MORNING
A8: 0.33333333
A9: 0.375
A10: 0.41666667
A11: 0.45833333
A12: 0.5
A13: 0.52083333 | C13: LUNCH TIME
A14: 0.58333333 | C14: AFTERNOON
A15: 0.625
A16: 0.66666667
A17: 0.70833333
A18: 0.75
A19: 0.8125 | C19: DINNER TIME
A20: 0.83333333 | C20: NIGHT
A21: 0.875
A22: 0.91666667
A23: 0.95833333

Sheet BASE PAX
C3: COIGUE
A4: PER PAX
A5: 2. FOOD | B5: QUANT. | C5: $ CUSTO | D5: $ VENDA | E5: SUBTOTAL
A6: BREAKFAST | B6: 0 | C6: 22000 | D6: =(C6*0.2)+C6 -> 26400 | E6: =D6*B6 -> 0 | F6: PADRAO BREAKFAST | G6: ='[1]⚙️ INPUTS'!$B$16 -> 24000 | H6: ='[1]⚙️ INPUTS'!$B$17 -> 18000
A7: LUNCH 1 | B7: 0 | C7: 40000 | D7: =(C7*0.2)+C7 -> 48000 | E7: =B7*D7 -> 0 | G7: ADULTO | H7: KIDS
A8: LUNCH 2 | B8: 0 | C8: 40000 | D8: =(C8*0.2)+C8 -> 48000 | E8: =B8*D8 -> 0
A9: LUNCH 3 | B9: 0 | C9: 40000 | D9: =(C9*0.2)+C9 -> 48000 | E9: =B9*D9 -> 0
A10: LUNCH 4 | B10: 0 | C10: 45000 | D10: =(C10*0.2)+C10 -> 54000 | E10: =B10*D10 -> 0
A11: LUNCH 5 | B11: 0 | C11: 50000 | D11: =(C11*0.2)+C11 -> 60000 | E11: =B11*D11 -> 0
A12: LUNCH 6 | B12: 0 | C12: 0 | D12: =(C12*0.2)+C12 -> 0 | E12: =B12*D12 -> 0
A13: LUNCH 7 | B13: 0 | C13: 5000 | D13: =(C13*0.2)+C13 -> 6000 | E13: =B13*D13 -> 0
A14: SNACKS | B14: 0 | C14: 8000 | D14: =(C14*0.2)+C14 -> 9600 | E14: =B14*D14 -> 0
A15: DINNER 1 | B15: 0 | C15: 70000 | D15: =(C15*0.2)+C15 -> 84000 | E15: =B15*D15 -> 0
A16: DINNER 2 | B16: 0 | C16: 25000 | D16: =(C16*0.2)+C16 -> 30000 | E16: =B16*D16 -> 0
A17: DINNER 3 | B17: 0 | C17: 50000 | D17: =(C17*0.2)+C17 -> 60000 | E17: =B17*D17 -> 0
A18: DINNER 4 | B18: 0 | C18: 65000 | D18: =(C18*0.2)+C18 -> 78000 | E18: =B18*D18 -> 0
A19: DINNER 5 | B19: 0 | C19: 75000 | D19: =(C19*0.2)+C19 -> 90000 | E19: =B19*D19 -> 0
A20: DINNER 6 | B20: 0 | C20: 0 | D20: =(C20*0.2)+C20 -> 0 | E20: =B20*D20 -> 0
A21: DINNER 7 | B21: 0 | C21: 75000 | D21: =(C21*0.2)+C21 -> 90000 | E21: =B21*D21 -> 0 | G21: ADULTO | H21: KIDS
A22: QUANT. TOTAL | PADRAO ALMOÇO | B22: 0 | C22: 40000 | D22: =(C22*0.2)+C22 -> 48000 | F22: PADRAO ALMOÇO | G22: 0 | H22: 0
A23: QUANT. TOTAL | PADRAO JANTAR | B23: 0 | C23: 50000 | D23: =(C23*0.2)+C23 -> 60000 | F23: PADRAO JANTAR | G23: ='[1]⚙️ INPUTS'!$B$21 -> 60000 | H23: ='[1]⚙️ INPUTS'!$B$22 -> 36000
A24: SUBTOTAL FOOD | E24: =SUM(E6:E21) -> 0
A26: 3. DRINKS / per cabin | B26: QUANT. | C26: $ CUSTO | D26: $ VENDA | E26: SUBTOTAL
A27: SUCOS | B27: 0 | C27: 0 | D27: =(C27*0.2)+C27 -> 0 | E27: =D27*B27 -> 0
A28: SUCOS | B28: 0 | C28: 0 | D28: =(C28*0.2)+C28 -> 0 | E28: =D28*B28 -> 0
A29: CERVEJAS | B29: 0 | C29: 2000 | D29: =(C29*0.2)+C29 -> 2400 | E29: =D29*B29 -> 0
A30: VINHOS | B30: 0 | C30: 8000 | D30: =(C30*0.2)+C30 -> 9600 | E30: =D30*B30 -> 0
A31: DRINKS | B31: 0 | C31: 15000 | D31: =(C31*0.2)+C31 -> 18000 | E31: =D31*B31 -> 0
A32: COOLER | B32: 0 | C32: 5000 | D32: =(C32*0.2)+C32 -> 6000 | E32: =D32*B32 -> 0
B33: 0 | C33: 0 | D33: =(C33*0.2)+C33 -> 0 | E33: =D33*B33 -> 0
A34: SUBTOTAL DRINKS | E34: =SUM(E27:E33) -> 0
A36: 4. ACTIVITIES / per pax | B36: QUANT. | C36: $ CUSTO | D36: $ VENDA | E36: SUBTOTAL
A37: HOTTUBE | B37: 0 | C37: 12000 | D37: =C37*0.2+C37 -> 14400 | E37: =D37*B37 -> 0
A38: TREKKING 1/2 DAY | B38: 0 | C38: 60000 | D38: =C38*0.2+C38 -> 72000 | E38: =D38*B38 -> 0
A39: TREKKING FUK DAY | B39: 0 | C39: 90000 | D39: =C39*0.2+C39 -> 108000 | E39: =D39*B39 -> 0
A40: FLOTADA FAMILIAR | B40: 0 | C40: 60000 | D40: =C40*0.2+C40 -> 72000 | E40: =D40*B40 -> 0
A41: RAFTING 1/2 DAY | B41: 0 | C41: 75000 | D41: =C41*0.2+C41 -> 90000 | E41: =D41*B41 -> 0
A42: RAFTING FULL DAY | B42: 0 | C42: 110000 | D42: =C42*0.2+C42 -> 132000 | E42: =D42*B42 -> 0
A43: CABALGADA 1/2 DAy | B43: 0 | C43: 90000 | D43: =C43*0.2+C43 -> 108000 | E43: =D43*B43 -> 0
A44: CABALGADA FULL DAY | B44: 0 | C44: 140000 | D44: =C44*0.2+C44 -> 168000 | E44: =D44*B44 -> 0
A45: LANCHA YELCHO | B45: 0 | C45: 120000 | D45: =C45*0.2+C45 -> 144000 | E45: =D45*B45 -> 0
A46: RECREACAO INFANTIL 3HS | B46: 0 | C46: 30000 | D46: =C46*0.2+C46 -> 36000 | E46: =D46*B46 -> 0
A47: SUBTOTAL ACTIVITIES | E47: =SUM(E37:E46) -> 0
A49: 5. TRANSPORT / per pax | B49: QUANT. | C49: $ CUSTO | D49: $ VENDA | E49: SUBTOTAL
A50: TRANSFER AEROPORTO CHEGADA | B50: 0 | C50: 80000 | D50: =C50*0.2+C50 -> 96000 | E50: =D50*B50 -> 0
A51: TRANSFER AEROPORTO PARTIDA | B51: 0 | C51: 80000 | D51: =C51*0.2+C51 -> 96000 | E51: =D51*B51 -> 0
A52: TRANSFERS INTERNO | B52: 0 | C52: 18000 | D52: =C52*0.2+C52 -> 21600 | E52: =D52*B52 -> 0
A53: EXTRAS 1 | B53: 0 | C53: 150000 | D53: =C53*0.2+C53 -> 180000 | E53: =D53*B53 -> 0
A54: EXTRAS 2 | B54: 0 | C54: 0 | D54: =C54*0.2+C54 -> 0 | E54: =D54*B54 -> 0
A55: SUBTOTAL TRANSPORT | E55: =SUM(E50:E54) -> 0
A57: 6. EXPERIENCES / per pax | B57: QUANT. | C57: $ CUSTO | D57: $ VENDA | E57: SUBTOTAL
A58: WS INSTRUCTOR | B58: 0 | C58: 3415000 | D58: =(C58*0.15)+C58 -> 3927250 | E58: =D58*B58 -> 0
A59: PRODUCER FEE | B59: 0 | C59: 180000 | D59: =(C59*0.2)+C59 -> 216000 | E59: =D59*B59 -> 0
B60: 0 | C60: 20000 | D60: =(C60*0.2)+C60 -> 24000 | E60: =D60*B60 -> 0
A61: 4. ACTIVITIES | E61: =SUM(E58:E60) -> 0
A63: 7. EXTRAS / per cabin | B63: USOS | C63: $ CUSTO/ DIA | D63: $ VENDA / total dias | E63: SUBTOTAL
A64: COORDENAÇÃO PRODUÇÃO | B64: 0 | C64: 50000 | D64: =((C64*0.2)+C64)*CALENDAR!$J$2 -> 0 | E64: =D64*B64 -> 0
A65: EXTRA MÃO DE OBRA | B65: 0 | C65: 50000 | D65: =((C65*0.2)+C65)*CALENDAR!$J$2 -> 0 | E65: =D65*B65 -> 0
A66: TAXA LIMPEZA CHECK IN / CHECKOUT | B66: 0 | C66: 40000 | D66: =((C66*0.2)+C66)*CALENDAR!$J$2 -> 0 | E66: =D66*B66 -> 0
A67: TAXA LIMPEZA DIARIA | B67: 0 | C67: 30000 | D67: =((C67*0.2)+C67)*CALENDAR!$J$2 -> 0 | E67: =D67*B67 -> 0
A68: SOUVENIR | B68: 0 | C68: 15000 | D68: =((C68*0.2)+C68)*CALENDAR!$J$2 -> 0 | E68: =D68*B68 -> 0
A69: ASSISTENTE COORDENAÇÃO | B69: 0 | C69: 30000 | D69: =((C69*0.2)+C69)*CALENDAR!$J$2 -> 0 | E69: =D69*B69 -> 0
A70: SUBTOTAL EXTRAS | E70: =SUM(E64:E69) -> 0
A72: 8. QUINCHO / per cabin | B72: USOS | C72: $ CUSTO | D72: $ VENDA | E72: SUBTOTAL
A73: QUINCHO DAY USE / CABIN | B73: 0 | C73: 15000 | D73: =C73+(C73*0.2) -> 18000 | E73: =D73*B73 -> 0
A74: SUBTOTAL QUINCHO | E74: =E73 -> 0

Sheet BUDGET RESUMO
C3: =CALENDAR!A2 -> CHECK IN | D3: =CALENDAR!C2 -> 0 | F3: CHECK OUT | G3: =CALENDAR!C3+1 -> 1 | K3: =CALENDAR!I2 -> NIGHTS | L3: =CALENDAR!J2 -> 0 | M3: =CALENDAR!J2 -> 0 | N3: =CALENDAR!K2 -> NOME CLIENTE | PROGRAMA
C4: PAX | D4: PAX | E4: PAX | F4: PAX | G4: PAX | H4: PAX | I4: PAX | J4: PAX | K4: PAX | L4: PAX | M4: PAX | N4: PAX | O4: PAX | P4: PAX | Q4: PAX | R4: PAX | S4: PAX | T4: PAX | U4: PAX | V4: PAX | W4: PAX | X4: PAX | Y4: PAX
C5: 1 | D5: 2 | E5: 2+1 | F5: 1 | G5: 2 | H5: 2+1 | I5: 2+2 | J5: 1 | K5: 2 | L5: 3 | M5: 2+1 | N5: 2+2 | O5: 1 | P5: 2 | Q5: 2+1 | R5: 2+2 | S5: 2+3 | T5: 3 | U5: 3+1 | V5: 3+2 | W5: 4 | X5: 4+1 | Y5: 5
C6: 1 | D6: 2 | E6: 3 | F6: 1 | G6: 2 | H6: 3 | I6: 4 | J6: 1 | K6: 2 | L6: 3 | M6: 3 | N6: 4 | O6: 1 | P6: 2 | Q6: 3 | R6: 4 | S6: 5 | T6: 3 | U6: 4 | V6: 5 | W6: 4 | X6: 5 | Y6: 5
C7: SIM = 1 NÃO = 0
C8: 0 | D8: 0 | E8: 0 | F8: 0 | G8: 0 | H8: 0 | I8: 0 | J8: 0 | K8: 0 | L8: 0 | M8: 0 | N8: 0 | O8: 0 | P8: 0 | Q8: 0 | R8: 0 | S8: 0 | T8: 0 | U8: 0 | V8: 0 | W8: 0 | X8: 0 | Y8: 0
B9: CABIN | C9: COIGUE | D9: COIGUE | E9: COIGUE | F9: NIRE | G9: NIRE | H9: NIRE | I9: NIRE | J9: CHAITEN | K9: CHAITEN | L9: CHAITEN | M9: CHAITEN | N9: CHAITEN | O9: CORCOVADO | P9: CORCOVADO | Q9: CORCOVADO | R9: CORCOVADO | S9: CORCOVADO | T9: CORCOVADO | U9: CORCOVADO | V9: CORCOVADO | W9: CORCOVADO | X9: CORCOVADO | Y9: CORCOVADO
B10: 1.LODGING | C10: ='BUDGET COIGUE 1'!D13*C8 -> 0 | D10: ='BUDGET COIGUE 2'!$D$13*D8 -> 0 | E10: ='BUDGET COIGUE 2+1'!$D$13*E8 -> 0 | F10: ='BUDGET NIRE 1'!$D$13*F8 -> 0 | G10: ='BUDGET NIRE 2'!$D$13*G8 -> 0 | H10: ='BUDGET NIRE 2+1'!$D$13*H8 -> 0 | I10: ='BUDGET NIRE 2+2'!$D$13*I8 -> 0 | J10: ='BUDGET CHAITEN 1'!$D$13*J8 -> 0 | K10: ='BUDGET CHAITEN 2'!$D$13*K8 -> 0 | L10: ='BUDGET CHAITEN 3'!$D$13*L8 -> 0 | M10: ='BUDGET CHAITEN 2+1'!$D$13*M8 -> 0 | N10: ='BUDGET CHAITEN 2+2'!$D$13*N8 -> 0 | O10: ='BUDGET CORCOVADO 1'!$D$13*O8 -> 0 | P10: ='BUDGET CORCOVADO 2'!$D$13*P8 -> 0 | Q10: ='BUDGET CORCOVADO 2+1'!$D$13*Q8 -> 0 | R10: ='BUDGET CORCOVADO 2+2'!$D$13*R8 -> 0 | S10: ='BUDGET CORCOVADO 2+3'!$D$13*S8 -> 0 | T10: ='BUDGET CORCOVADO 3'!$D$13*T8 -> 0 | U10: ='BUDGET CORCOVADO 3+1'!$D$13*U8 -> 0 | V10: ='BUDGET CORCOVADO 3+2'!$D$13*V8 -> 0 | W10: ='BUDGET CORCOVADO 4'!$D$13*W8 -> 0 | X10: ='BUDGET CORCOVADO 4+1'!$D$13*X8 -> 0 | Y10: ='BUDGET CORCOVADO 5'!$D$13*Y8 -> 0
B11: 2.FOOD | C11: ='BUDGET COIGUE 1'!$D$14*C8 -> 0 | D11: ='BUDGET COIGUE 2'!$D$14*D8 -> 0 | E11: ='BUDGET COIGUE 2+1'!$D$14*E8 -> 0 | F11: ='BUDGET NIRE 1'!$D$14*F8 -> 0 | G11: ='BUDGET NIRE 2'!$D$14*G8 -> 0 | H11: ='BUDGET NIRE 2+1'!$D$14*H8 -> 0 | I11: ='BUDGET NIRE 2+2'!$D$14*I8 -> 0 | J11: ='BUDGET CHAITEN 1'!$D$14*J8 -> 0 | K11: ='BUDGET CHAITEN 2'!$D$14*K8 -> 0 | L11: ='BUDGET CHAITEN 3'!$D$14*L8 -> 0 | M11: ='BUDGET CHAITEN 2+1'!$D$14*M8 -> 0 | N11: ='BUDGET CHAITEN 2+2'!$D$14*N8 -> 0 | O11: ='BUDGET CORCOVADO 1'!$D$14*O8 -> 0 | P11: ='BUDGET CORCOVADO 2'!$D$14*P8 -> 0 | Q11: ='BUDGET CORCOVADO 2+1'!$D$14*Q8 -> 0 | R11: ='BUDGET CORCOVADO 2+2'!$D$14*R8 -> 0 | S11: ='BUDGET CORCOVADO 2+3'!$D$14*S8 -> 0 | T11: ='BUDGET CORCOVADO 3'!$D$14*T8 -> 0 | U11: ='BUDGET CORCOVADO 3+1'!$D$14*U8 -> 0 | V11: ='BUDGET CORCOVADO 3+2'!$D$14*V8 -> 0 | W11: ='BUDGET CORCOVADO 4'!$D$14*W8 -> 0 | X11: ='BUDGET CORCOVADO 4+1'!$D$14*X8 -> 0 | Y11: ='BUDGET CORCOVADO 5'!$D$14*Y8 -> 0
B12: 3.DRINKS | C12: ='BUDGET COIGUE 1'!$D$15*C8 -> 0 | D12: ='BUDGET COIGUE 2'!$D$15*D8 -> 0 | E12: ='BUDGET COIGUE 2+1'!$D$15*E8 -> 0 | F12: ='BUDGET NIRE 1'!$D$15*F8 -> 0 | G12: ='BUDGET NIRE 2'!$D$15*G8 -> 0 | H12: ='BUDGET NIRE 2+1'!$D$15*H8 -> 0 | I12: ='BUDGET NIRE 2+2'!$D$15*I8 -> 0 | J12: ='BUDGET CHAITEN 1'!$D$15*J8 -> 0 | K12: ='BUDGET CHAITEN 2'!$D$15*K8 -> 0 | L12: ='BUDGET CHAITEN 3'!$D$15*L8 -> 0 | M12: ='BUDGET CHAITEN 2+1'!$D$15*M8 -> 0 | N12: ='BUDGET CHAITEN 2+2'!$D$15*N8 -> 0 | O12: ='BUDGET CORCOVADO 1'!$D$15*O8 -> 0 | P12: ='BUDGET CORCOVADO 2'!$D$15*P8 -> 0 | Q12: ='BUDGET CORCOVADO 2+1'!$D$15*Q8 -> 0 | R12: ='BUDGET CORCOVADO 2+2'!$D$15*R8 -> 0 | S12: ='BUDGET CORCOVADO 2+3'!$D$15*S8 -> 0 | T12: ='BUDGET CORCOVADO 3'!$D$15*T8 -> 0 | U12: ='BUDGET CORCOVADO 3+1'!$D$15*U8 -> 0 | V12: ='BUDGET CORCOVADO 3+2'!$D$15*V8 -> 0 | W12: ='BUDGET CORCOVADO 4'!$D$15*W8 -> 0 | X12: ='BUDGET CORCOVADO 4+1'!$D$15*X8 -> 0 | Y12: ='BUDGET CORCOVADO 5'!$D$15*Y8 -> 0
B13: 4. ACTIVITIES | C13: ='BUDGET COIGUE 1'!$D$16*C8 -> 0 | D13: ='BUDGET COIGUE 2'!$D$16*D8 -> 0 | E13: ='BUDGET COIGUE 2+1'!$D$16*E8 -> 0 | F13: ='BUDGET NIRE 1'!$D$16*F8 -> 0 | G13: ='BUDGET NIRE 2'!$D$16*G8 -> 0 | H13: ='BUDGET NIRE 2+1'!$D$16*H8 -> 0 | I13: ='BUDGET NIRE 2+2'!$D$16*I8 -> 0 | J13: ='BUDGET CHAITEN 1'!$D$16*J8 -> 0 | K13: ='BUDGET CHAITEN 2'!$D$16*K8 -> 0 | L13: ='BUDGET CHAITEN 3'!$D$16*L8 -> 0 | M13: ='BUDGET CHAITEN 2+1'!$D$16*M8 -> 0 | N13: ='BUDGET CHAITEN 2+2'!$D$16*N8 -> 0 | O13: ='BUDGET CORCOVADO 1'!$D$16*O8 -> 0 | P13: ='BUDGET CORCOVADO 2'!$D$16*P8 -> 0 | Q13: ='BUDGET CORCOVADO 2+1'!$D$16*Q8 -> 0 | R13: ='BUDGET CORCOVADO 2+2'!$D$16*R8 -> 0 | S13: ='BUDGET CORCOVADO 2+3'!$D$16*S8 -> 0 | T13: ='BUDGET CORCOVADO 3'!$D$16*T8 -> 0 | U13: ='BUDGET CORCOVADO 3+1'!$D$16*U8 -> 0 | V13: ='BUDGET CORCOVADO 3+2'!$D$16*V8 -> 0 | W13: ='BUDGET CORCOVADO 4'!$D$16*W8 -> 0 | X13: ='BUDGET CORCOVADO 4+1'!$D$16*X8 -> 0 | Y13: ='BUDGET CORCOVADO 5'!$D$16*Y8 -> 0
B14: 5.TRANSPORT | C14: ='BUDGET COIGUE 1'!$D$17*C8 -> 0 | D14: ='BUDGET COIGUE 2'!$D$17*D8 -> 0 | E14: ='BUDGET COIGUE 2+1'!$D$17*E8 -> 0 | F14: ='BUDGET NIRE 1'!$D$17*F8 -> 0 | G14: ='BUDGET NIRE 2'!$D$17*G8 -> 0 | H14: ='BUDGET NIRE 2+1'!$D$17*H8 -> 0 | I14: ='BUDGET NIRE 2+2'!$D$17*I8 -> 0 | J14: ='BUDGET CHAITEN 1'!$D$17*J8 -> 0 | K14: ='BUDGET CHAITEN 2'!$D$17*K8 -> 0 | L14: ='BUDGET CHAITEN 3'!$D$17*L8 -> 0 | M14: ='BUDGET CHAITEN 2+1'!$D$17*M8 -> 0 | N14: ='BUDGET CHAITEN 2+2'!$D$17*N8 -> 0 | O14: ='BUDGET CORCOVADO 1'!$D$17*O8 -> 0 | P14: ='BUDGET CORCOVADO 2'!$D$17*P8 -> 0 | Q14: ='BUDGET CORCOVADO 2+1'!$D$17*Q8 -> 0 | R14: ='BUDGET CORCOVADO 2+2'!$D$17*R8 -> 0 | S14: ='BUDGET CORCOVADO 2+3'!$D$17*S8 -> 0 | T14: ='BUDGET CORCOVADO 3'!$D$17*T8 -> 0 | U14: ='BUDGET CORCOVADO 3+1'!$D$17*U8 -> 0 | V14: ='BUDGET CORCOVADO 3+2'!$D$17*V8 -> 0 | W14: ='BUDGET CORCOVADO 4'!$D$17*W8 -> 0 | X14: ='BUDGET CORCOVADO 4+1'!$D$17*X8 -> 0 | Y14: ='BUDGET CORCOVADO 5'!$D$17*Y8 -> 0
B15: 6.EXPERIENCES | C15: ='BUDGET COIGUE 1'!$D$18*C8 -> 0 | D15: ='BUDGET COIGUE 2'!$D$18*D8 -> 0 | E15: ='BUDGET COIGUE 2+1'!$D$18*E8 -> 0 | F15: ='BUDGET NIRE 1'!$D$18*F8 -> 0 | G15: ='BUDGET NIRE 2'!$D$18*G8 -> 0 | H15: ='BUDGET NIRE 2+1'!$D$18*H8 -> 0 | I15: ='BUDGET NIRE 2+2'!$D$18*I8 -> 0 | J15: ='BUDGET CHAITEN 1'!$D$18*J8 -> 0 | K15: ='BUDGET CHAITEN 2'!$D$18*K8 -> 0 | L15: ='BUDGET CHAITEN 3'!$D$18*L8 -> 0 | M15: ='BUDGET CHAITEN 2+1'!$D$18*M8 -> 0 | N15: ='BUDGET CHAITEN 2+2'!$D$18*N8 -> 0 | O15: ='BUDGET CORCOVADO 1'!$D$18*O8 -> 0 | P15: ='BUDGET CORCOVADO 2'!$D$18*P8 -> 0 | Q15: ='BUDGET CORCOVADO 2+1'!$D$18*Q8 -> 0 | R15: ='BUDGET CORCOVADO 2+2'!$D$18*R8 -> 0 | S15: ='BUDGET CORCOVADO 2+3'!$D$18*S8 -> 0 | T15: ='BUDGET CORCOVADO 3'!$D$18*T8 -> 0 | U15: ='BUDGET CORCOVADO 3+1'!$D$18*U8 -> 0 | V15: ='BUDGET CORCOVADO 3+2'!$D$18*V8 -> 0 | W15: ='BUDGET CORCOVADO 4'!$D$18*W8 -> 0 | X15: ='BUDGET CORCOVADO 4+1'!$D$18*X8 -> 0 | Y15: ='BUDGET CORCOVADO 5'!$D$18*Y8 -> 0
B16: 7.EXTRAS | C16: ='BUDGET COIGUE 1'!$D$19*C8 -> 0 | D16: ='BUDGET COIGUE 2'!$D$19*D8 -> 0 | E16: ='BUDGET COIGUE 2+1'!$D$19*E8 -> 0 | F16: ='BUDGET NIRE 1'!$D$19*F8 -> 0 | G16: ='BUDGET NIRE 2'!$D$19*G8 -> 0 | H16: ='BUDGET NIRE 2+1'!$D$19*H8 -> 0 | I16: ='BUDGET NIRE 2+2'!$D$19*I8 -> 0 | J16: ='BUDGET CHAITEN 1'!$D$19*J8 -> 0 | K16: ='BUDGET CHAITEN 2'!$D$19*K8 -> 0 | L16: ='BUDGET CHAITEN 3'!$D$19*L8 -> 0 | M16: ='BUDGET CHAITEN 2+1'!$D$19*M8 -> 0 | N16: ='BUDGET CHAITEN 2+2'!$D$19*N8 -> 0 | O16: ='BUDGET CORCOVADO 1'!$D$19*O8 -> 0 | P16: ='BUDGET CORCOVADO 2'!$D$19*P8 -> 0 | Q16: ='BUDGET CORCOVADO 2+1'!$D$19*Q8 -> 0 | R16: ='BUDGET CORCOVADO 2+2'!$D$19*R8 -> 0 | S16: ='BUDGET CORCOVADO 2+3'!$D$19*S8 -> 0 | T16: ='BUDGET CORCOVADO 3'!$D$19*T8 -> 0 | U16: ='BUDGET CORCOVADO 3+1'!$D$19*U8 -> 0 | V16: ='BUDGET CORCOVADO 3+2'!$D$19*V8 -> 0 | W16: ='BUDGET CORCOVADO 4'!$D$19*W8 -> 0 | X16: ='BUDGET CORCOVADO 4+1'!$D$19*X8 -> 0 | Y16: ='BUDGET CORCOVADO 5'!$D$19*Y8 -> 0
B17: 8. QUINCHO | C17: ='BUDGET COIGUE 1'!$D$20*C8 -> 0 | D17: ='BUDGET COIGUE 2'!$D$20*D8 -> 0 | E17: ='BUDGET COIGUE 2+1'!$D$20*E8 -> 0 | F17: ='BUDGET NIRE 1'!$D$20*F8 -> 0 | G17: ='BUDGET NIRE 2'!$D$20*G8 -> 0 | H17: ='BUDGET NIRE 2+1'!$D$20*H8 -> 0 | I17: ='BUDGET NIRE 2+2'!$D$20*I8 -> 0 | J17: ='BUDGET CHAITEN 1'!$D$20*J8 -> 0 | K17: ='BUDGET CHAITEN 2'!$D$20*K8 -> 0 | L17: ='BUDGET CHAITEN 3'!$D$20*L8 -> 0 | M17: ='BUDGET CHAITEN 2+1'!$D$20*M8 -> 0 | N17: ='BUDGET CHAITEN 2+2'!$D$20*N8 -> 0 | O17: ='BUDGET CORCOVADO 1'!$D$20*O8 -> 0 | P17: ='BUDGET CORCOVADO 2'!$D$20*P8 -> 0 | Q17: ='BUDGET CORCOVADO 2+1'!$D$20*Q8 -> 0 | R17: ='BUDGET CORCOVADO 2+2'!$D$20*R8 -> 0 | S17: ='BUDGET CORCOVADO 2+3'!$D$20*S8 -> 0 | T17: ='BUDGET CORCOVADO 2'!$D$20*T8 -> 0 | U17: ='BUDGET CORCOVADO 2'!$D$20*U8 -> 0 | V17: ='BUDGET CORCOVADO 3+2'!$D$20*V8 -> 0 | W17: ='BUDGET CORCOVADO 2'!$D$20*W8 -> 0 | X17: ='BUDGET CORCOVADO 4+1'!$D$20*X8 -> 0 | Y17: ='BUDGET CORCOVADO 5'!$D$20*Y8 -> 0
B19: SUBTOTAL SEM AGÊNCIA [CC] | C19: =SUM(C10:C17) -> 0 | D19: =SUM(D10:D17) -> 0 | E19: =SUM(E10:E17) -> 0 | F19: =SUM(F10:F17) -> 0 | G19: =SUM(G10:G17) -> 0 | H19: =SUM(H10:H17) -> 0 | I19: =SUM(I10:I17) -> 0 | J19: =SUM(J10:J17) -> 0 | ... Y19: =SUM(Y10:Y17) -> 0
B20: desconto 5% | C20: =C19*0.05 -> 0 | D20: =D19*0.05 -> 0 | E20: =E19*0.05 -> 0 | F20: =F19*0.05 -> 0 | G20: =G19*0.05 -> 0 | H20: =H19*0.05 -> 0 | I20: =I19*0.05 -> 0 | J20: =J19*0.05 -> 0 | ... Y20: =Y19*0.05 -> 0
B21: SUBTOTAL [no cash] | C21: =C19-C20 -> 0 | D21: =D19-D20 -> 0 | E21: =E19-E20 -> 0 | F21: =F19-F20 -> 0 | G21: =G19-G20 -> 0 | H21: =H19-H20 -> 0 | I21: =I19-I20 -> 0 | J21: =J19-J20 -> 0 | ... Y21: =Y19-Y20 -> 0
B23: taxa agência | C23: ='[1]⚙️ INPUTS'!$B$34 -> 0.15
B24: taxa SUMUP | C24: ='[1]⚙️ INPUTS'!$B$33 -> 0.04
B25: SUBTOTAL COM TAXA DE AG [pago em cash] | C25: =C21+(C21*$C$23) -> 0 | D25: =D21+(D21*$C$23) -> 0 | E25: =E21+(E21*$C$23) -> 0 | F25: =F21+(F21*$C$23) -> 0 | G25: =G21+(G21*$C$23) -> 0 | H25: =H21+(H21*$C$23) -> 0 | I25: =I21+(I21*$C$23) -> 0 | J25: =J21+(J21*$C$23) -> 0 | ... Y25: =Y21+(Y21*$C$23) -> 0
B26: SUBTOTAL COM TAXA DE AG [pago CC] | C26: =C25+(C25*$C$24) -> 0 | D26: =D25+(D25*$C$24) -> 0 | E26: =E25+(E25*$C$24) -> 0 | F26: =F25+(F25*$C$24) -> 0 | G26: =G25+(G25*$C$24) -> 0 | H26: =H25+(H25*$C$24) -> 0 | I26: =I25+(I25*$C$24) -> 0 | J26: =J25+(J25*$C$24) -> 0 | ... Y26: =Y25+(Y25*$C$24) -> 0
B27: GANHO COMISSÃO AGÊNCIA | C27: =C26-C19 -> 0 | D27: =D26-D19 -> 0 | E27: =E26-E19 -> 0 | F27: =F26-F19 -> 0 | G27: =G26-G19 -> 0 | H27: =H26-H19 -> 0 | I27: =I26-I19 -> 0 | J27: =J26-J19 -> 0 | ... Y27: =Y26-Y19 -> 0
B29: VALOR POR PESSOA PAGO [CC] | C29: =C19/C6 -> 0 | D29: =D19/D6 -> 0 | E29: =E19/E6 -> 0 | F29: =F19/F6 -> 0 | G29: =G19/G6 -> 0 | H29: =H19/H6 -> 0 | I29: =I19/I6 -> 0 | J29: =J19/J6 -> 0 | ... Y29: =Y19/Y6 -> 0
B30: VALOR POR PESSOA COM AGÊNCIA PAGO [CC] | C30: =C29+(C29*C28) -> 0 | D30: =D29+(D29*D28) -> 0 | E30: =E29+(E29*E28) -> 0 | F30: =F29+(F29*F28) -> 0 | G30: =G29+(G29*G28) -> 0 | H30: =H29+(H29*H28) -> 0 | I30: =I29+(I29*I28) -> 0 | J30: =J29+(J29*J28) -> 0 | ... Y30: =Y29+(Y29*Y28) -> 0
B31: GANHO COMISSÃO AGÊNCIA (por pessoa) | C31: =C30-C24 -> -0.04 | D31: =D30-D24 -> 0 | E31: =E30-E24 -> 0 | F31: =F30-F24 -> 0 | G31: =G30-G24 -> 0 | H31: =H30-H24 -> 0 | I31: =I30-I24 -> 0 | J31: =J30-J24 -> 0 | ... Y31: =Y30-Y24 -> 0
B34: VALORES SEM IVA 19%
B39: SUBTOTAL COMISSÕES GANHO | C39: {='BUDGET COIGUE 1'!G20:G21} -> 0 | D39: =SUM('BUDGET COIGUE 2'!G14:G19) -> 0 | E39: =SUM('BUDGET COIGUE 2+1'!G14:G19) -> 0 | F39: {='BUDGET NIRE 1'!G20:G21} -> 0 | G39: {='BUDGET NIRE 2'!G20:G21} -> 0 | H39: =SUM('BUDGET NIRE 2+1'!G14:G19) -> 0 | J39: {='BUDGET CHAITEN 1'!G20:G21} -> 0 | K39: {='BUDGET CHAITEN 2'!G20:G21} -> 0 | M39: {='BUDGET CHAITEN 2+1'!G20:G21} -> 0 | N39: =SUM('BUDGET CHAITEN 2+2'!#REF!) -> #REF! | O39: {='BUDGET CORCOVADO 1'!G20:G21} -> 0 | P39: {='BUDGET CORCOVADO 2'!G20:G21} -> 0 | Q39: {='BUDGET CORCOVADO 2+1'!G20:G21} -> 0 | R39: {='BUDGET CORCOVADO 2+2'!G20:G21} -> 0 | S39: {='BUDGET CORCOVADO 2+3'!G20:G21} -> 0 | T39: {='BUDGET CORCOVADO 3'!G20:G21} -> 0 | U39: {='BUDGET CORCOVADO 3+1'!G20:G21} -> 0 | V39: {='BUDGET CORCOVADO 3+2'!G20:G21} -> 0 | W39: {='BUDGET CORCOVADO 4'!G20:G21} -> 0 | X39: =SUM('BUDGET CORCOVADO 4+1'!G14:G19) -> 0 | Y39: =SUM('BUDGET CORCOVADO 5'!G14:G19) -> 0
C40: 0 | F40: 0 | G40: 0 | J40: 0 | K40: 0 | M40: 0 | O40: 0 | P40: 0 | Q40: 0 | R40: 0 | S40: 0 | T40: 0 | U40: 0 | V40: 0 | W40: 0
B41: 2.FOOD | C41: ='BUDGET COIGUE 1'!G14 -> 0 | D41: ='BUDGET COIGUE 2'!G14 -> 0 | E41: ='BUDGET COIGUE 2+1'!G14 -> 0 | F41: ='BUDGET NIRE 1'!G14 -> 0 | G41: ='BUDGET NIRE 2'!G14 -> 0 | H41: ='BUDGET NIRE 2+1'!G14 -> 0 | J41: ='BUDGET CHAITEN 1'!G14 -> 0 | K41: ='BUDGET CHAITEN 2'!G14 -> 0 | M41: ='BUDGET CHAITEN 2+1'!G14 -> 0 | N41: ='BUDGET CHAITEN 2+2'!#REF! -> #REF! | O41: ='BUDGET CORCOVADO 1'!G14 -> 0 | P41: ='BUDGET CORCOVADO 2'!G14 -> 0 | Q41: ='BUDGET CORCOVADO 2+1'!G14 -> 0 | R41: ='BUDGET CORCOVADO 2+2'!G14 -> 0 | S41: ='BUDGET CORCOVADO 2+3'!G14 -> 0 | T41: ='BUDGET CORCOVADO 3'!G14 -> 0 | U41: ='BUDGET CORCOVADO 3+1'!G14 -> 0 | V41: ='BUDGET CORCOVADO 3+2'!G14 -> 0 | W41: ='BUDGET CORCOVADO 4'!G14 -> 0 | X41: ='BUDGET CORCOVADO 4+1'!G14 -> 0 | Y41: ='BUDGET CORCOVADO 5'!G14 -> 0
B42: 3.DRINKS | C42: ='BUDGET COIGUE 1'!G15 -> 0 | D42: ='BUDGET COIGUE 2'!G15 -> 0 | E42: ='BUDGET COIGUE 2+1'!G15 -> 0 | F42: ='BUDGET NIRE 1'!G15 -> 0 | G42: ='BUDGET NIRE 2'!G15 -> 0 | H42: ='BUDGET NIRE 2+1'!G15 -> 0 | J42: ='BUDGET CHAITEN 1'!G15 -> 0 | K42: ='BUDGET CHAITEN 2'!G15 -> 0 | M42: ='BUDGET CHAITEN 2+1'!G15 -> 0 | N42: ='BUDGET CHAITEN 2+2'!#REF! -> #REF! | O42: ='BUDGET CORCOVADO 1'!G15 -> 0 | P42: ='BUDGET CORCOVADO 2'!G15 -> 0 | Q42: ='BUDGET CORCOVADO 2+1'!G15 -> 0 | R42: ='BUDGET CORCOVADO 2+2'!G15 -> 0 | S42: ='BUDGET CORCOVADO 2+3'!G15 -> 0 | T42: ='BUDGET CORCOVADO 3'!G15 -> 0 | U42: ='BUDGET CORCOVADO 3+1'!G15 -> 0 | V42: ='BUDGET CORCOVADO 3+2'!G15 -> 0 | W42: ='BUDGET CORCOVADO 4'!G15 -> 0 | X42: ='BUDGET CORCOVADO 4+1'!G15 -> 0 | Y42: ='BUDGET CORCOVADO 5'!G15 -> 0
B43: 4. ACTIVITIES | C43: ='BUDGET COIGUE 1'!G16 -> 0 | D43: ='BUDGET COIGUE 2'!G16 -> 0 | E43: ='BUDGET COIGUE 2+1'!G16 -> 0 | F43: ='BUDGET NIRE 1'!G16 -> 0 | G43: ='BUDGET NIRE 2'!G16 -> 0 | H43: ='BUDGET NIRE 2+1'!G16 -> 0 | J43: ='BUDGET CHAITEN 1'!G16 -> 0 | K43: ='BUDGET CHAITEN 2'!G16 -> 0 | M43: ='BUDGET CHAITEN 2+1'!G16 -> 0 | N43: ='BUDGET CHAITEN 2+2'!#REF! -> #REF! | O43: ='BUDGET CORCOVADO 1'!G16 -> 0 | P43: ='BUDGET CORCOVADO 2'!G16 -> 0 | Q43: ='BUDGET CORCOVADO 2+1'!G16 -> 0 | R43: ='BUDGET CORCOVADO 2+2'!G16 -> 0 | S43: ='BUDGET CORCOVADO 2+3'!G16 -> 0 | T43: ='BUDGET CORCOVADO 3'!G16 -> 0 | U43: ='BUDGET CORCOVADO 3+1'!G16 -> 0 | V43: ='BUDGET CORCOVADO 3+2'!G16 -> 0 | W43: ='BUDGET CORCOVADO 4'!G16 -> 0 | X43: ='BUDGET CORCOVADO 4+1'!G16 -> 0 | Y43: ='BUDGET CORCOVADO 5'!G16 -> 0
B44: 5.TRANSPORT | C44: ='BUDGET COIGUE 1'!G17 -> 0 | D44: ='BUDGET COIGUE 2'!G17 -> 0 | E44: ='BUDGET COIGUE 2+1'!G17 -> 0 | F44: ='BUDGET NIRE 1'!G17 -> 0 | G44: ='BUDGET NIRE 2'!G17 -> 0 | H44: ='BUDGET NIRE 2+1'!G17 -> 0 | J44: ='BUDGET CHAITEN 1'!G17 -> 0 | K44: ='BUDGET CHAITEN 2'!G17 -> 0 | M44: ='BUDGET CHAITEN 2+1'!G17 -> 0 | N44: ='BUDGET CHAITEN 2+2'!#REF! -> #REF! | O44: ='BUDGET CORCOVADO 1'!G17 -> 0 | P44: ='BUDGET CORCOVADO 2'!G17 -> 0 | Q44: ='BUDGET CORCOVADO 2+1'!G17 -> 0 | R44: ='BUDGET CORCOVADO 2+2'!G17 -> 0 | S44: ='BUDGET CORCOVADO 2+3'!G17 -> 0 | T44: ='BUDGET CORCOVADO 3'!G17 -> 0 | U44: ='BUDGET CORCOVADO 3+1'!G17 -> 0 | V44: ='BUDGET CORCOVADO 3+2'!G17 -> 0 | W44: ='BUDGET CORCOVADO 4'!G17 -> 0 | X44: ='BUDGET CORCOVADO 4+1'!G17 -> 0 | Y44: ='BUDGET CORCOVADO 5'!G17 -> 0
B45: 6.EXPERIENCES | C45: ='BUDGET COIGUE 1'!G18 -> 0 | D45: ='BUDGET COIGUE 2'!G18 -> 0 | E45: ='BUDGET COIGUE 2+1'!G18 -> 0 | F45: ='BUDGET NIRE 1'!G18 -> 0 | G45: ='BUDGET NIRE 2'!G18 -> 0 | H45: ='BUDGET NIRE 2+1'!G18 -> 0 | J45: ='BUDGET CHAITEN 1'!G18 -> 0 | K45: ='BUDGET CHAITEN 2'!G18 -> 0 | M45: ='BUDGET CHAITEN 2+1'!G18 -> 0 | N45: ='BUDGET CHAITEN 2+2'!#REF! -> #REF! | O45: ='BUDGET CORCOVADO 1'!G18 -> 0 | P45: ='BUDGET CORCOVADO 2'!G18 -> 0 | Q45: ='BUDGET CORCOVADO 2+1'!G18 -> 0 | R45: ='BUDGET CORCOVADO 2+2'!G18 -> 0 | S45: ='BUDGET CORCOVADO 2+3'!G18 -> 0 | T45: ='BUDGET CORCOVADO 3'!G18 -> 0 | U45: ='BUDGET CORCOVADO 3+1'!G18 -> 0 | V45: ='BUDGET CORCOVADO 3+2'!G18 -> 0 | W45: ='BUDGET CORCOVADO 4'!G18 -> 0 | X45: ='BUDGET CORCOVADO 4+1'!G18 -> 0 | Y45: ='BUDGET CORCOVADO 5'!G18 -> 0
B46: 7.EXTRAS | C46: ='BUDGET COIGUE 1'!G19 -> 0 | D46: ='BUDGET COIGUE 2'!G19 -> 0 | E46: ='BUDGET COIGUE 2+1'!G19 -> 0 | F46: ='BUDGET NIRE 1'!G19 -> 0 | G46: ='BUDGET NIRE 2'!G19 -> 0 | H46: ='BUDGET NIRE 2+1'!G19 -> 0 | J46: ='BUDGET CHAITEN 1'!G19 -> 0 | K46: ='BUDGET CHAITEN 2'!G19 -> 0 | M46: ='BUDGET CHAITEN 2+1'!G19 -> 0 | N46: ='BUDGET CHAITEN 2+2'!#REF! -> #REF! | O46: ='BUDGET CORCOVADO 1'!G19 -> 0 | P46: ='BUDGET CORCOVADO 2'!G19 -> 0 | Q46: ='BUDGET CORCOVADO 2+1'!G19 -> 0 | R46: ='BUDGET CORCOVADO 2+2'!G19 -> 0 | S46: ='BUDGET CORCOVADO 2+3'!G19 -> 0 | T46: ='BUDGET CORCOVADO 3'!G19 -> 0 | U46: ='BUDGET CORCOVADO 3+1'!G19 -> 0 | V46: ='BUDGET CORCOVADO 3+2'!G19 -> 0 | W46: ='BUDGET CORCOVADO 4'!G19 -> 0 | X46: ='BUDGET CORCOVADO 4+1'!G19 -> 0 | Y46: ='BUDGET CORCOVADO 5'!G19 -> 0

Sheet RESULTADO
B3: CLIENT | C3: =CALENDAR!K2 -> NOME CLIENTE | PROGRAMA
B4: CHECK IN | C4: =CALENDAR!C2 -> 0
B5: CHECK OUT | C5: =CALENDAR!C3 -> 0 | H5: TOTAL PESSOAS GRUPO | I5: ='BUDGET RESUMO'!C8*'BUDGET RESUMO'!C6+'BUDGET RESUMO'!D8*'BUDGET RESUMO'!D6+'BUDGET RESUMO'!F6*'BUDGET RESUMO'!F8+'BUDGET RESUMO'!G8*'BUDGET RESUMO'!G6+'BUDGET RESUMO'!I6*'BUDGET RESUMO'!I8+'BUDGET RESUMO'!J8*'BUDGET RESUMO'!J6+'BUDGET RESUMO'!L6*'BUDGET RESUMO'!L8+'BUDGET RESUMO'!N8*'BUDGET RESUMO'!N6+'BUDGET RESUMO'!O6*'BUDGET RESUMO'!O8+'BUDGET RESUMO'!P8*'BUDGET RESUMO'!P6+'BUDGET RESUMO'!Q6*'BUDGET RESUMO'!Q8+'BUDGET RESUMO'!R8*'BUDGET RESUMO'!R6+'BUDGET RESUMO'!S6*'BUDGET RESUMO'!S8+'BUDGET RESUMO'!T8*'BUDGET RESUMO'!T6+'BUDGET RESUMO'!U6*'BUDGET RESUMO'!U8+'BUDGET RESUMO'!V8*'BUDGET RESUMO'!V6+'BUDGET RESUMO'!E8*'BUDGET RESUMO'!E6+'BUDGET RESUMO'!H8*'BUDGET RESUMO'!H6+'BUDGET RESUMO'!M8*'BUDGET RESUMO'!M6+'BUDGET RESUMO'!X8*'BUDGET RESUMO'!X6+'BUDGET RESUMO'!W8*'BUDGET RESUMO'!W6+'BUDGET RESUMO'!K8*'BUDGET RESUMO'!K6 -> 0
B6: TOTAL NIGHTS | C6: =CALENDAR!J2 -> 0 | H6: LUCRO POR NOITE | I6: =I7/C6 -> #DIV/0!
H7: TOTAL COMISSÕES + CABINS | I7: =I8+E11 -> 0
B8: SUBTOTAIS | F8: VALORES SEM IVA 19% | H8: TOTAL COMISSÕES | I8: =H13+H15+H17+H19+H21+H23 -> 0
B10: 1. LODGING
E11: =('BUDGET RESUMO'!C10*'BUDGET RESUMO'!$C$8)+('BUDGET RESUMO'!D10*'BUDGET RESUMO'!$D$8)+('BUDGET RESUMO'!F10*'BUDGET RESUMO'!$F$8)+('BUDGET RESUMO'!G10*'BUDGET RESUMO'!$G$8)+('BUDGET RESUMO'!J10*'BUDGET RESUMO'!$J$8)+('BUDGET RESUMO'!K10*'BUDGET RESUMO'!$K$8)+('BUDGET RESUMO'!M10*'BUDGET RESUMO'!$M$8)+('BUDGET RESUMO'!O10*'BUDGET RESUMO'!$O$8)+('BUDGET RESUMO'!P10*'BUDGET RESUMO'!$P$8)+('BUDGET RESUMO'!Q10*'BUDGET RESUMO'!$Q$8)+('BUDGET RESUMO'!R10*'BUDGET RESUMO'!$R$8)+('BUDGET RESUMO'!S10*'BUDGET RESUMO'!$S$8)+('BUDGET RESUMO'!T10*'BUDGET RESUMO'!$T$8)+('BUDGET RESUMO'!U10*'BUDGET RESUMO'!$U$8)+('BUDGET RESUMO'!V10*'BUDGET RESUMO'!$V$8)+('BUDGET RESUMO'!W10*'BUDGET RESUMO'!$W$8)+('BUDGET RESUMO'!E10*'BUDGET RESUMO'!$E$8)+('BUDGET RESUMO'!H10*'BUDGET RESUMO'!$H$8)+('BUDGET RESUMO'!N10*'BUDGET RESUMO'!$N$8)+('BUDGET RESUMO'!Y10*'BUDGET RESUMO'!$Y$8)+('BUDGET RESUMO'!X10*'BUDGET RESUMO'!$X$8)+('BUDGET RESUMO'!L10*'BUDGET RESUMO'!$L$8)+('BUDGET RESUMO'!I10*'BUDGET RESUMO'!$I$8) -> 0
B12: 2. FOOD
E13: =('BUDGET RESUMO'!C11*'BUDGET RESUMO'!$C$8)+('BUDGET RESUMO'!D11*'BUDGET RESUMO'!$D$8)+('BUDGET RESUMO'!F11*'BUDGET RESUMO'!$F$8)+('BUDGET RESUMO'!G11*'BUDGET RESUMO'!$G$8)+('BUDGET RESUMO'!J11*'BUDGET RESUMO'!$J$8)+('BUDGET RESUMO'!K11*'BUDGET RESUMO'!$K$8)+('BUDGET RESUMO'!M11*'BUDGET RESUMO'!$M$8)+('BUDGET RESUMO'!O11*'BUDGET RESUMO'!$O$8)+('BUDGET RESUMO'!P11*'BUDGET RESUMO'!$P$8)+('BUDGET RESUMO'!Q11*'BUDGET RESUMO'!$Q$8)+('BUDGET RESUMO'!R11*'BUDGET RESUMO'!$R$8)+('BUDGET RESUMO'!S11*'BUDGET RESUMO'!$S$8)+('BUDGET RESUMO'!T11*'BUDGET RESUMO'!$T$8)+('BUDGET RESUMO'!U11*'BUDGET RESUMO'!$U$8)+('BUDGET RESUMO'!V11*'BUDGET RESUMO'!$V$8)+('BUDGET RESUMO'!W11*'BUDGET RESUMO'!$W$8)+('BUDGET RESUMO'!E11*'BUDGET RESUMO'!$E$8)+('BUDGET RESUMO'!H11*'BUDGET RESUMO'!$H$8)+('BUDGET RESUMO'!N11*'BUDGET RESUMO'!$N$8)+('BUDGET RESUMO'!Y11*'BUDGET RESUMO'!$Y$8)+('BUDGET RESUMO'!X11*'BUDGET RESUMO'!$X$8)+('BUDGET RESUMO'!L11*'BUDGET RESUMO'!$L$8)+('BUDGET RESUMO'!I11*'BUDGET RESUMO'!$I$8) -> 0 | G13: =E13*0.2 -> 0 | H13: =0.2*E13 -> 0
B14: 3. DRINKS
E15: =('BUDGET RESUMO'!C12*'BUDGET RESUMO'!$C$8)+('BUDGET RESUMO'!D12*'BUDGET RESUMO'!$D$8)+('BUDGET RESUMO'!F12*'BUDGET RESUMO'!$F$8)+('BUDGET RESUMO'!G12*'BUDGET RESUMO'!$G$8)+('BUDGET RESUMO'!J12*'BUDGET RESUMO'!$J$8)+('BUDGET RESUMO'!K12*'BUDGET RESUMO'!$K$8)+('BUDGET RESUMO'!M12*'BUDGET RESUMO'!$M$8)+('BUDGET RESUMO'!O12*'BUDGET RESUMO'!$O$8)+('BUDGET RESUMO'!P12*'BUDGET RESUMO'!$P$8)+('BUDGET RESUMO'!Q12*'BUDGET RESUMO'!$Q$8)+('BUDGET RESUMO'!R12*'BUDGET RESUMO'!$R$8)+('BUDGET RESUMO'!S12*'BUDGET RESUMO'!$S$8)+('BUDGET RESUMO'!T12*'BUDGET RESUMO'!$T$8)+('BUDGET RESUMO'!U12*'BUDGET RESUMO'!$U$8)+('BUDGET RESUMO'!V12*'BUDGET RESUMO'!$V$8)+('BUDGET RESUMO'!W12*'BUDGET RESUMO'!$W$8)+('BUDGET RESUMO'!E12*'BUDGET RESUMO'!$E$8)+('BUDGET RESUMO'!H12*'BUDGET RESUMO'!$H$8)+('BUDGET RESUMO'!N12*'BUDGET RESUMO'!$N$8)+('BUDGET RESUMO'!Y12*'BUDGET RESUMO'!$Y$8)+('BUDGET RESUMO'!X12*'BUDGET RESUMO'!$X$8)+('BUDGET RESUMO'!L12*'BUDGET RESUMO'!$L$8)+('BUDGET RESUMO'!I12*'BUDGET RESUMO'!$I$8) -> 0 | H15: =0.2*E15 -> 0
B16: 4. ACTIVITIES
E17: =('BUDGET RESUMO'!C13*'BUDGET RESUMO'!$C$8)+('BUDGET RESUMO'!D13*'BUDGET RESUMO'!$D$8)+('BUDGET RESUMO'!F13*'BUDGET RESUMO'!$F$8)+('BUDGET RESUMO'!G13*'BUDGET RESUMO'!$G$8)+('BUDGET RESUMO'!J13*'BUDGET RESUMO'!$J$8)+('BUDGET RESUMO'!K13*'BUDGET RESUMO'!$K$8)+('BUDGET RESUMO'!M13*'BUDGET RESUMO'!$M$8)+('BUDGET RESUMO'!O13*'BUDGET RESUMO'!$O$8)+('BUDGET RESUMO'!P13*'BUDGET RESUMO'!$P$8)+('BUDGET RESUMO'!Q13*'BUDGET RESUMO'!$Q$8)+('BUDGET RESUMO'!R13*'BUDGET RESUMO'!$R$8)+('BUDGET RESUMO'!S13*'BUDGET RESUMO'!$S$8)+('BUDGET RESUMO'!T13*'BUDGET RESUMO'!$T$8)+('BUDGET RESUMO'!U13*'BUDGET RESUMO'!$U$8)+('BUDGET RESUMO'!V13*'BUDGET RESUMO'!$V$8)+('BUDGET RESUMO'!W13*'BUDGET RESUMO'!$W$8)+('BUDGET RESUMO'!E13*'BUDGET RESUMO'!$E$8)+('BUDGET RESUMO'!H13*'BUDGET RESUMO'!$H$8)+('BUDGET RESUMO'!N13*'BUDGET RESUMO'!$N$8)+('BUDGET RESUMO'!Y13*'BUDGET RESUMO'!$Y$8)+('BUDGET RESUMO'!X13*'BUDGET RESUMO'!$X$8)+('BUDGET RESUMO'!L13*'BUDGET RESUMO'!$L$8)+('BUDGET RESUMO'!I13*'BUDGET RESUMO'!$I$8) -> 0 | H17: =0.2*E17 -> 0
B18: 5. TRANSPORT
E19: =('BUDGET RESUMO'!C14*'BUDGET RESUMO'!$C$8)+('BUDGET RESUMO'!D14*'BUDGET RESUMO'!$D$8)+('BUDGET RESUMO'!F14*'BUDGET RESUMO'!$F$8)+('BUDGET RESUMO'!G14*'BUDGET RESUMO'!$G$8)+('BUDGET RESUMO'!J14*'BUDGET RESUMO'!$J$8)+('BUDGET RESUMO'!K14*'BUDGET RESUMO'!$K$8)+('BUDGET RESUMO'!M14*'BUDGET RESUMO'!$M$8)+('BUDGET RESUMO'!O14*'BUDGET RESUMO'!$O$8)+('BUDGET RESUMO'!P14*'BUDGET RESUMO'!$P$8)+('BUDGET RESUMO'!Q14*'BUDGET RESUMO'!$Q$8)+('BUDGET RESUMO'!R14*'BUDGET RESUMO'!$R$8)+('BUDGET RESUMO'!S14*'BUDGET RESUMO'!$S$8)+('BUDGET RESUMO'!T14*'BUDGET RESUMO'!$T$8)+('BUDGET RESUMO'!U14*'BUDGET RESUMO'!$U$8)+('BUDGET RESUMO'!V14*'BUDGET RESUMO'!$V$8)+('BUDGET RESUMO'!W14*'BUDGET RESUMO'!$W$8)+('BUDGET RESUMO'!E14*'BUDGET RESUMO'!$E$8)+('BUDGET RESUMO'!H14*'BUDGET RESUMO'!$H$8)+('BUDGET RESUMO'!N14*'BUDGET RESUMO'!$N$8)+('BUDGET RESUMO'!Y14*'BUDGET RESUMO'!$Y$8)+('BUDGET RESUMO'!X14*'BUDGET RESUMO'!$X$8)+('BUDGET RESUMO'!L14*'BUDGET RESUMO'!$L$8)+('BUDGET RESUMO'!I14*'BUDGET RESUMO'!$I$8) -> 0 | H19: =0.2*E19 -> 0
B20: 6. EXPERIENCES
E21: =('BUDGET RESUMO'!C15*'BUDGET RESUMO'!$C$8)+('BUDGET RESUMO'!D15*'BUDGET RESUMO'!$D$8)+('BUDGET RESUMO'!F15*'BUDGET RESUMO'!$F$8)+('BUDGET RESUMO'!G15*'BUDGET RESUMO'!$G$8)+('BUDGET RESUMO'!J15*'BUDGET RESUMO'!$J$8)+('BUDGET RESUMO'!K15*'BUDGET RESUMO'!$K$8)+('BUDGET RESUMO'!M15*'BUDGET RESUMO'!$M$8)+('BUDGET RESUMO'!O15*'BUDGET RESUMO'!$O$8)+('BUDGET RESUMO'!P15*'BUDGET RESUMO'!$P$8)+('BUDGET RESUMO'!Q15*'BUDGET RESUMO'!$Q$8)+('BUDGET RESUMO'!R15*'BUDGET RESUMO'!$R$8)+('BUDGET RESUMO'!S15*'BUDGET RESUMO'!$S$8)+('BUDGET RESUMO'!T15*'BUDGET RESUMO'!$T$8)+('BUDGET RESUMO'!U15*'BUDGET RESUMO'!$U$8)+('BUDGET RESUMO'!V15*'BUDGET RESUMO'!$V$8)+('BUDGET RESUMO'!W15*'BUDGET RESUMO'!$W$8)+('BUDGET RESUMO'!E15*'BUDGET RESUMO'!$E$8)+('BUDGET RESUMO'!H15*'BUDGET RESUMO'!$H$8)+('BUDGET RESUMO'!N15*'BUDGET RESUMO'!$N$8)+('BUDGET RESUMO'!Y15*'BUDGET RESUMO'!$Y$8)+('BUDGET RESUMO'!X15*'BUDGET RESUMO'!$X$8)+('BUDGET RESUMO'!L15*'BUDGET RESUMO'!$L$8)+('BUDGET RESUMO'!I15*'BUDGET RESUMO'!$I$8) -> 0 | H21: =0.2*E21 -> 0
B22: 7. EXTRAS
E23: =('BUDGET RESUMO'!C16*'BUDGET RESUMO'!$C$8)+('BUDGET RESUMO'!D16*'BUDGET RESUMO'!$D$8)+('BUDGET RESUMO'!F16*'BUDGET RESUMO'!$F$8)+('BUDGET RESUMO'!G16*'BUDGET RESUMO'!$G$8)+('BUDGET RESUMO'!J16*'BUDGET RESUMO'!$J$8)+('BUDGET RESUMO'!K16*'BUDGET RESUMO'!$K$8)+('BUDGET RESUMO'!M16*'BUDGET RESUMO'!$M$8)+('BUDGET RESUMO'!O16*'BUDGET RESUMO'!$O$8)+('BUDGET RESUMO'!P16*'BUDGET RESUMO'!$P$8)+('BUDGET RESUMO'!Q16*'BUDGET RESUMO'!$Q$8)+('BUDGET RESUMO'!R16*'BUDGET RESUMO'!$R$8)+('BUDGET RESUMO'!S16*'BUDGET RESUMO'!$S$8)+('BUDGET RESUMO'!T16*'BUDGET RESUMO'!$T$8)+('BUDGET RESUMO'!U16*'BUDGET RESUMO'!$U$8)+('BUDGET RESUMO'!V16*'BUDGET RESUMO'!$V$8)+('BUDGET RESUMO'!W16*'BUDGET RESUMO'!$W$8)+('BUDGET RESUMO'!E16*'BUDGET RESUMO'!$E$8)+('BUDGET RESUMO'!H16*'BUDGET RESUMO'!$H$8)+('BUDGET RESUMO'!N16*'BUDGET RESUMO'!$N$8)+('BUDGET RESUMO'!Y16*'BUDGET RESUMO'!$Y$8)+('BUDGET RESUMO'!X16*'BUDGET RESUMO'!$X$8)+('BUDGET RESUMO'!L16*'BUDGET RESUMO'!$L$8)+('BUDGET RESUMO'!I16*'BUDGET RESUMO'!$I$8) -> 0 | H23: =0.2*E23 -> 0
B24: 8. QUINCHO
E25: =('BUDGET RESUMO'!C17*'BUDGET RESUMO'!$C$8)+('BUDGET RESUMO'!D17*'BUDGET RESUMO'!$D$8)+('BUDGET RESUMO'!F17*'BUDGET RESUMO'!$F$8)+('BUDGET RESUMO'!G17*'BUDGET RESUMO'!$G$8)+('BUDGET RESUMO'!J17*'BUDGET RESUMO'!$J$8)+('BUDGET RESUMO'!K17*'BUDGET RESUMO'!$K$8)+('BUDGET RESUMO'!M17*'BUDGET RESUMO'!$M$8)+('BUDGET RESUMO'!O17*'BUDGET RESUMO'!$O$8)+('BUDGET RESUMO'!P17*'BUDGET RESUMO'!$P$8)+('BUDGET RESUMO'!Q17*'BUDGET RESUMO'!$Q$8)+('BUDGET RESUMO'!R17*'BUDGET RESUMO'!$R$8)+('BUDGET RESUMO'!S17*'BUDGET RESUMO'!$S$8)+('BUDGET RESUMO'!T17*'BUDGET RESUMO'!$T$8)+('BUDGET RESUMO'!U17*'BUDGET RESUMO'!$U$8)+('BUDGET RESUMO'!V17*'BUDGET RESUMO'!$V$8)+('BUDGET RESUMO'!W17*'BUDGET RESUMO'!$W$8)+('BUDGET RESUMO'!E17*'BUDGET RESUMO'!$E$8)+('BUDGET RESUMO'!H17*'BUDGET RESUMO'!$H$8)+('BUDGET RESUMO'!N17*'BUDGET RESUMO'!$N$8)+('BUDGET RESUMO'!Y17*'BUDGET RESUMO'!$Y$8)+('BUDGET RESUMO'!X17*'BUDGET RESUMO'!$X$8)+('BUDGET RESUMO'!L17*'BUDGET RESUMO'!$L$8)+('BUDGET RESUMO'!I17*'BUDGET RESUMO'!$I$8) -> 0
E26: =SUM(E25+E23+E21+E19+E17+E15+E13+E11) -> 0
B27: TOTAL SEM AG [cash] | E27: =E26-(E26*0.05) -> 0
B28: TOTAL SEM AG [CC] | D28: TOTAL SEM CC [cash] | E28: =E27*(1+'BUDGET RESUMO'!$C$23) -> 0
B30: TOTAL COM AGÊNCIA
B31: TOTAL COM AGÊNCIA [CC] | D31: TOTAL COM AGÊNCIA (CC) | E31: =E28*(1+'BUDGET RESUMO'!$C$24) -> 0 | F31: =('BUDGET RESUMO'!D21*(1+'BUDGET RESUMO'!$C$23))*(1+'BUDGET RESUMO'!$C$24) -> 0 | G31: =('BUDGET RESUMO'!F21*(1+'BUDGET RESUMO'!$C$23))*(1+'BUDGET RESUMO'!$C$24) -> 0 | H31: =('BUDGET RESUMO'!G21*(1+'BUDGET RESUMO'!$C$23))*(1+'BUDGET RESUMO'!$C$24) -> 0 | I31: =('BUDGET RESUMO'!I21*(1+'BUDGET RESUMO'!$C$23))*(1+'BUDGET RESUMO'!$C$24) -> 0 | J31: =('BUDGET RESUMO'!J21*(1+'BUDGET RESUMO'!$C$23))*(1+'BUDGET RESUMO'!$C$24) -> 0 | K31: =('BUDGET RESUMO'!L21*(1+'BUDGET RESUMO'!$C$23))*(1+'BUDGET RESUMO'!$C$24) -> 0 | L31: =('BUDGET RESUMO'!N21*(1+'BUDGET RESUMO'!$C$23))*(1+'BUDGET RESUMO'!$C$24) -> 0 | M31: =('BUDGET RESUMO'!O21*(1+'BUDGET RESUMO'!$C$23))*(1+'BUDGET RESUMO'!$C$24) -> 0 | N31: =('BUDGET RESUMO'!P21*(1+'BUDGET RESUMO'!$C$23))*(1+'BUDGET RESUMO'!$C$24) -> 0 | O31: =('BUDGET RESUMO'!Q21*(1+'BUDGET RESUMO'!$C$23))*(1+'BUDGET RESUMO'!$C$24) -> 0 | P31: =('BUDGET RESUMO'!R21*(1+'BUDGET RESUMO'!$C$23))*(1+'BUDGET RESUMO'!$C$24) -> 0 | Q31: =('BUDGET RESUMO'!S21*(1+'BUDGET RESUMO'!$C$23))*(1+'BUDGET RESUMO'!$C$24) -> 0 | R31: =('BUDGET RESUMO'!T21*(1+'BUDGET RESUMO'!$C$23))*(1+'BUDGET RESUMO'!$C$24) -> 0 | S31: =('BUDGET RESUMO'!U21*(1+'BUDGET RESUMO'!$C$23))*(1+'BUDGET RESUMO'!$C$24) -> 0 | T31: =('BUDGET RESUMO'!V21*(1+'BUDGET RESUMO'!$C$23))*(1+'BUDGET RESUMO'!$C$24) -> 0
B33: GANHO COMISSÃO AGÊNCIA | E33: =E27*'BUDGET RESUMO'!$C$23 -> 0
B35: CONTROLE PAGAMENTO COMISSÕES
B36: PARCELA | C36: DATA | D36: VALOR | E36: SALDO A PAGAR
D37: 0 | E37: =E33-D37 -> 0
D38: 0 | E38: =E37-D38 -> 0
D39: 0 | E39: =E38-D39 -> 0
D40: 0 | E40: =E39-D40 -> 0

Sheet BUDGET COIGUE 1
C3: COIGUE
A5: TOTAL PAX ADULT | B5: 1 | E5: COIGUE
A6: TOTAL PAX INFANT | B6: 0 | D6: BUDGET TOTAL | F6: =D21 -> 0
A7: CHECK IN. | B7: =CALENDAR!C2 -> 0 | D7: SUBTOTAL PAGO | F7: =SUM(F12:F20) -> 0
A8: CHECK OUT. | B8: =CALENDAR!C3 -> 0 | D8: SUBTOTAL A RECEBER | F8: =F6-F7 -> 0
A9: TOTAL NIGHTS. | B9: =CALENDAR!J2 -> 0 | D9: TIP |
A11: RESUMO. | B11: PREÇO CLIENTE CASH CLP $ | C11: TAXA CC | D11: PREÇO CLIENTE PAGTO CC $ | F11: =E5 -> COIGUE | I11: CONTROLE PAGAMENTOS
C12: 0.05 | I12: DATA | J12: VALOR PAGO CLP $ | K12: FORMA PAGTO
A13: 1.LODGING | B13: =G28 -> 0 | C13: =B13*$C$12 -> 0 | D13: =B13+(B13*$C$12) -> 0
A14: 2.FOOD | B14: =J49 -> 0 | C14: =B14*$C$12 -> 0 | D14: =B14+(B14*$C$12) -> 0 | F14: =A14 -> 2.FOOD | G14: =G49 -> 0
A15: 3.DRINKS | B15: =E59 -> 0 | C15: =B15*$C$12 -> 0 | D15: =B15+(B15*$C$12) -> 0 | F15: =A15 -> 3.DRINKS | G15: =G59 -> 0
A16: 4. ACTIVITIES | B16: =$E$72 -> 0 | C16: =B16*$C$12 -> 0 | D16: =B16+(B16*$C$12) -> 0 | F16: =A16 -> 4. ACTIVITIES | G16: =G72 -> 0
A17: 5.TRANSPORT | B17: =$E$80 -> 0 | C17: =B17*$C$12 -> 0 | D17: =B17+(B17*$C$12) -> 0 | F17: =A17 -> 5.TRANSPORT | G17: =G80 -> 0
A18: 6.EXPERIENCES | B18: =$E$86 -> 0 | C18: =B18*$C$12 -> 0 | D18: =B18+(B18*$C$12) -> 0 | F18: =A18 -> 6.EXPERIENCES | G18: =G86 -> 0
A19: 7.EXTRAS | B19: =$E$95 -> 0 | C19: =B19*$C$12 -> 0 | D19: =B19+(B19*$C$12) -> 0 | F19: =A19 -> 7.EXTRAS | G19: =G95 -> 0
A20: 8. QUINCHO | B20: =$E$99 -> 0 | C20: =B20*$C$12 -> 0 | D20: =B20+(B20*$C$12) -> 0 | F20: SUBTOTAL COMISSÕES | G20: =G14+G15+G16+G17+G18+G19 -> 0
A21: SUBTOTAL 1 | B21: =SUM(B13:B20) -> 0 | D21: =SUM(D13:D20) -> 0
A23: 1. LODGING | B23: QUANT. | C23: $ CABIN / DIA | D23: $ ADICIONAL / DIA | E23: BASE CÁLCULO | F23: DESCONTOS | G23: $ SUBTOTAL
A24: COIGUE (até 2 pax) - até 06 noites | B24: 1 | C24: =249200 -> 249200 | E24: =(C24+D24)*$B$9*B24 -> 0 | F24: 0 | G24: =E24-(E24*F24) -> 0
A25: COIGUE ( 2 + baby) - até 06 noites | B25: 0 | C25: =249200 -> 249200 | D25: 50000 | E25: =(C25+D25)*$B$9*B25 -> 0 | F25: 0 | G25: =E25-(E25*F25) -> 0
A26: COIGUE (até 2 pax) - 7 noites ou + | B26: 0 | C26: =224280 -> 224280 | E26: =(C26+D26)*$B$9*B26 -> 0 | F26: 0 | G26: =E26-(E26*F26) -> 0
A27: COIGUE ( 2 + baby) - 7 noites ou + | B27: 0 | C27: =224280 -> 224280 | D27: 50000 | E27: =(C27+D27)*$B$9*B27 -> 0 | F27: 0 | G27: =E27-(E27*F27) -> 0
A28: SUBTOTAL LODGING | G28: =SUM(G24:G27) -> 0
A30: 2. FOOD | B30: QUANT. | C30: $ CUSTO | D30: $ VENDA | E30: SUBTOTAL $ VENDA | F30: SUBTOTAL $ CUSTO | G30: COMISSÕES
A31: ='BASE PAX'!A6 -> BREAKFAST | B31: =(B5*B9*'BASE PAX'!G6)+('BASE PAX'!H6*B6*B9) -> 0 | E31: 0 | F31: =B31*C31 -> 0 | G31: =0.2*B31 -> 0 | H31: =A31 -> BREAKFAST | I31: =B31 -> 0
A32: ='BASE PAX'!A7 -> LUNCH 1 | B32: =($B$5+$B$6)*'BASE PAX'!B7 -> 0 | C32: ='BASE PAX'!C7 -> 40000 | D32: ='BASE PAX'!D7 -> 48000 | E32: =D32*B32 -> 0 | F32: =B32*C32 -> 0 | G32: =E32-F32 -> 0
A33: ='BASE PAX'!A8 -> LUNCH 2 | B33: =($B$5+$B$6)*'BASE PAX'!B8 -> 0 | C33: ='BASE PAX'!C8 -> 40000 | D33: ='BASE PAX'!D8 -> 48000 | E33: =D33*B33 -> 0 | F33: =B33*C33 -> 0 | G33: =E33-F33 -> 0
A34: ='BASE PAX'!A9 -> LUNCH 3 | B34: =($B$5+$B$6)*'BASE PAX'!B9 -> 0 | C34: ='BASE PAX'!C9 -> 40000 | D34: ='BASE PAX'!D9 -> 48000 | E34: =D34*B34 -> 0 | F34: =B34*C34 -> 0 | G34: =E34-F34 -> 0
A35: ='BASE PAX'!A10 -> LUNCH 4 | B35: =($B$5+$B$6)*'BASE PAX'!B10 -> 0 | C35: ='BASE PAX'!C10 -> 45000 | D35: ='BASE PAX'!D10 -> 54000 | E35: =D35*B35 -> 0 | F35: =B35*C35 -> 0 | G35: =E35-F35 -> 0
A36: ='BASE PAX'!A11 -> LUNCH 5 | B36: =($B$5+$B$6)*'BASE PAX'!B11 -> 0 | C36: ='BASE PAX'!C11 -> 50000 | D36: ='BASE PAX'!D11 -> 60000 | E36: =D36*B36 -> 0 | F36: =B36*C36 -> 0 | G36: =E36-F36 -> 0
A37: ='BASE PAX'!A12 -> LUNCH 6 | B37: =($B$5+$B$6)*'BASE PAX'!B12 -> 0 | C37: ='BASE PAX'!C12 -> 0 | D37: ='BASE PAX'!D12 -> 0 | E37: =D37*B37 -> 0 | F37: =B37*C37 -> 0 | G37: =E37-F37 -> 0
A38: ='BASE PAX'!A13 -> LUNCH 7 | B38: =($B$5+$B$6)*'BASE PAX'!B13 -> 0 | C38: ='BASE PAX'!C13 -> 5000 | D38: ='BASE PAX'!D13 -> 6000 | E38: =D38*B38 -> 0 | F38: =B38*C38 -> 0 | G38: =E38-F38 -> 0
A39: ='BASE PAX'!A14 -> SNACKS | B39: =($B$5+$B$6)*'BASE PAX'!B14 -> 0 | C39: ='BASE PAX'!C14 -> 8000 | D39: ='BASE PAX'!D14 -> 9600 | E39: =D39*B39 -> 0 | F39: =B39*C39 -> 0 | G39: =E39-F39 -> 0
A40: ='BASE PAX'!A15 -> DINNER 1 | B40: =($B$5+$B$6)*'BASE PAX'!B15 -> 0 | C40: ='BASE PAX'!C15 -> 70000 | D40: ='BASE PAX'!D15 -> 84000 | E40: =D40*B40 -> 0 | F40: =B40*C40 -> 0 | G40: =E40-F40 -> 0
A41: ='BASE PAX'!A16 -> DINNER 2 | B41: =($B$5+$B$6)*'BASE PAX'!B16 -> 0 | C41: ='BASE PAX'!C16 -> 25000 | D41: ='BASE PAX'!D16 -> 30000 | E41: =D41*B41 -> 0 | F41: =B41*C41 -> 0 | G41: =E41-F41 -> 0
A42: ='BASE PAX'!A17 -> DINNER 3 | B42: =($B$5+$B$6)*'BASE PAX'!B17 -> 0 | C42: ='BASE PAX'!C17 -> 50000 | D42: ='BASE PAX'!D17 -> 60000 | E42: =D42*B42 -> 0 | F42: =B42*C42 -> 0 | G42: =E42-F42 -> 0
A43: ='BASE PAX'!A18 -> DINNER 4 | B43: =($B$5+$B$6)*'BASE PAX'!B18 -> 0 | C43: ='BASE PAX'!C18 -> 65000 | D43: ='BASE PAX'!D18 -> 78000 | E43: =D43*B43 -> 0 | F43: =B43*C43 -> 0 | G43: =E43-F43 -> 0
... A46: ='BASE PAX'!A21 -> DINNER 7 | B46: =($B$5+$B$6)*'BASE PAX'!B21 -> 0 | C46: ='BASE PAX'!C21 -> 75000 | D46: ='BASE PAX'!D21 -> 90000 | E46: =D46*B46 -> 0 | F46: =B46*C46 -> 0 | G46: =E46-F46 -> 0
A47: ='BASE PAX'!A22 -> QUANT. TOTAL | PADRAO ALMOÇO | B47: ='BASE PAX'!B22 -> 0 | G47: =0.2*I47 -> 0 | H47: =A47 -> QUANT. TOTAL | PADRAO ALMOÇO | I47: =(B5*B47*'BASE PAX'!G22)+(B6*B47*'BASE PAX'!H22) -> 0
A48: ='BASE PAX'!A23 -> QUANT. TOTAL | PADRAO JANTAR | B48: ='BASE PAX'!B23 -> 0 | G48: =0.2*I48 -> 0 | H48: =A48 -> QUANT. TOTAL | PADRAO JANTAR | I48: =(B5*B48*'BASE PAX'!G23)+(B6*B48*'BASE PAX'!H23) -> 0
A49: SUBTOTAL FOOD | E49: =SUM(E31:E48) -> 0 | F49: =SUM(F31:F48) -> 0 | G49: =SUM(G31:G48) -> 0 | H49: SUBTOTAL | I49: =I31+I47+I48 -> 0 | J49: =I49+E49 -> 0 | K49: TOTAL FOOD
A51: 3. DRINKS (por cabin) | B51: QUANT. | C51: $ CUSTO | D51: $ VENDA | E51: SUBTOTAL | F51: SUBTOTAL $ CUSTO | G51: COMISSÕES
A52: ='BASE PAX'!A27 -> SUCOS | B52: ='BASE PAX'!B27 -> 0 | C52: ='BASE PAX'!C27 -> 0 | D52: =(C52*0.2)+C52 -> 0 | E52: =D52*B52 -> 0 | F52: =B52*C52 -> 0 | G52: =E52-F52 -> 0
A53: ='BASE PAX'!A28 -> SUCOS | B53: ='BASE PAX'!B28 -> 0 | C53: ='BASE PAX'!C28 -> 0 | D53: =(C53*0.2)+C53 -> 0 | E53: =D53*B53 -> 0 | F53: =B53*C53 -> 0 | G53: =E53-F53 -> 0
A54: ='BASE PAX'!A29 -> CERVEJAS | B54: ='BASE PAX'!B29 -> 0 | C54: ='BASE PAX'!C29 -> 2000 | D54: =(C54*0.2)+C54 -> 2400 | E54: =D54*B54 -> 0 | F54: =B54*C54 -> 0 | G54: =E54-F54 -> 0
A55: ='BASE PAX'!A30 -> VINHOS | B55: ='BASE PAX'!B30 -> 0 | C55: ='BASE PAX'!C30 -> 8000 | D55: =(C55*0.2)+C55 -> 9600 | E55: =D55*B55 -> 0 | F55: =B55*C55 -> 0 | G55: =E55-F55 -> 0
A56: ='BASE PAX'!A31 -> DRINKS | B56: ='BASE PAX'!B31 -> 0 | C56: ='BASE PAX'!C31 -> 15000 | D56: =(C56*0.2)+C56 -> 18000 | E56: =D56*B56 -> 0 | F56: =B56*C56 -> 0 | G56: =E56-F56 -> 0
A57: ='BASE PAX'!A32 -> COOLER | B57: ='BASE PAX'!B32 -> 0 | C57: ='BASE PAX'!C32 -> 5000 | D57: =(C57*0.2)+C57 -> 6000 | E57: =D57*B57 -> 0 | F57: =B57*C57 -> 0 | G57: =E57-F57 -> 0
A58: ='BASE PAX'!A33 -> 0 | B58: ='BASE PAX'!B33 -> 0 | C58: ='BASE PAX'!C33 -> 0 | D58: =(C58*0.2)+C58 -> 0 | E58: =D58*B58 -> 0 | F58: =B58*C58 -> 0 | G58: =E58-F58 -> 0
A59: SUBTOTAL DRINKS | E59: =SUM(E52:E58) -> 0 | F59: =SUM(F52:F58) -> 0 | G59: =E59-F59 -> 0
A61: 4. ACTIVITIES | B61: QUANT. | C61: $ CUSTO | D61: $ VENDA | E61: SUBTOTAL | F61: SUBTOTAL $ CUSTO | G61: COMISSÕES
A62: ='BASE PAX'!A37 -> HOTTUBE | B62: ='BASE PAX'!B37 -> 0 | C62: ='BASE PAX'!C37 -> 12000 | D62: =C62*0.2+C62 -> 14400 | E62: =D62*B62 -> 0 | F62: =B62*C62 -> 0 | G62: =E62-F62 -> 0
A63: ='BASE PAX'!A38 -> TREKKING 1/2 DAY | B63: ='BASE PAX'!B38 -> 0 | C63: ='BASE PAX'!C38 -> 60000 | D63: =C63*0.2+C63 -> 72000 | E63: =D63*B63 -> 0 | F63: =B63*C63 -> 0 | G63: =E63-F63 -> 0
A64: ='BASE PAX'!A39 -> TREKKING FUK DAY | B64: ='BASE PAX'!B39 -> 0 | C64: ='BASE PAX'!C39 -> 90000 | D64: =C64*0.2+C64 -> 108000 | E64: =D64*B64 -> 0 | F64: =B64*C64 -> 0 | G64: =E64-F64 -> 0
A65: ='BASE PAX'!A40 -> FLOTADA FAMILIAR | B65: ='BASE PAX'!B40 -> 0 | C65: ='BASE PAX'!C40 -> 60000 | D65: =C65*0.2+C65 -> 72000 | E65: =D65*B65 -> 0 | F65: =B65*C65 -> 0 | G65: =E65-F65 -> 0
A66: ='BASE PAX'!A41 -> RAFTING 1/2 DAY | B66: ='BASE PAX'!B41 -> 0 | C66: ='BASE PAX'!C41 -> 75000 | D66: =C66*0.2+C66 -> 90000 | E66: =D66*B66 -> 0 | F66: =B66*C66 -> 0 | G66: =E66-F66 -> 0
A67: ='BASE PAX'!A42 -> RAFTING FULL DAY | B67: ='BASE PAX'!B42 -> 0 | C67: ='BASE PAX'!C42 -> 110000 | D67: =C67*0.2+C67 -> 132000 | E67: =D67*B67 -> 0 | F67: =B67*C67 -> 0 | G67: =E67-F67 -> 0
A68: ='BASE PAX'!A43 -> CABALGADA 1/2 DAy | B68: ='BASE PAX'!B43 -> 0 | C68: ='BASE PAX'!C43 -> 90000 | D68: =C68*0.2+C68 -> 108000 | E68: =D68*B68 -> 0 | F68: =B68*C68 -> 0 | G68: =E68-F68 -> 0
A69: ='BASE PAX'!A44 -> CABALGADA FULL DAY | B69: ='BASE PAX'!B44 -> 0 | C69: ='BASE PAX'!C44 -> 140000 | D69: =C69*0.2+C69 -> 168000 | E69: =D69*B69 -> 0 | F69: =B69*C69 -> 0 | G69: =E69-F69 -> 0
A70: ='BASE PAX'!A45 -> LANCHA YELCHO | B70: ='BASE PAX'!B45 -> 0 | C70: ='BASE PAX'!C45 -> 120000 | D70: =C70*0.2+C70 -> 144000 | E70: =D70*B70 -> 0 | F70: =B70*C70 -> 0 | G70: =E70-F70 -> 0
A71: ='BASE PAX'!A46 -> RECREACAO INFANTIL 3HS | B71: ='BASE PAX'!B46 -> 0 | C71: ='BASE PAX'!C46 -> 30000 | D71: =C71*0.2+C71 -> 36000 | E71: =D71*B71 -> 0 | F71: =B71*C71 -> 0 | G71: =E71-F71 -> 0
A72: SUBTOTAL ACTIVITIES | E72: =SUM(E62:E71) -> 0 | F72: =B72*C72 -> 0 | G72: =E72-F72 -> 0
A74: 5. TRANSPORT | B74: QUANT. | C74: $ CUSTO | D74: $ VENDA | E74: SUBTOTAL | F74: SUBTOTAL CUSTO | G74: COMISSÕES
A75: ='BASE PAX'!A50 -> TRANSFER AEROPORTO CHEGADA | B75: ='BASE PAX'!B50 -> 0 | C75: ='BASE PAX'!C50 -> 80000 | D75: =C75*0.2+C75 -> 96000 | E75: =D75*B75 -> 0 | F75: =B75*C75 -> 0 | G75: =E75-F75 -> 0
A76: ='BASE PAX'!A51 -> TRANSFER AEROPORTO PARTIDA | B76: ='BASE PAX'!B51 -> 0 | C76: ='BASE PAX'!C51 -> 80000 | D76: =C76*0.2+C76 -> 96000 | E76: =D76*B76 -> 0 | F76: =B76*C76 -> 0 | G76: =E76-F76 -> 0
A77: ='BASE PAX'!A52 -> TRANSFERS INTERNO | B77: ='BASE PAX'!B52 -> 0 | C77: ='BASE PAX'!C52 -> 18000 | D77: =C77*0.2+C77 -> 21600 | E77: =D77*B77 -> 0 | F77: =B77*C77 -> 0 | G77: =E77-F77 -> 0
A78: ='BASE PAX'!A53 -> EXTRAS 1 | B78: ='BASE PAX'!B53 -> 0 | C78: ='BASE PAX'!C53 -> 150000 | D78: =C78*0.2+C78 -> 180000 | E78: =D78*B78 -> 0 | F78: =B78*C78 -> 0 | G78: =E78-F78 -> 0
A79: ='BASE PAX'!A54 -> EXTRAS 2 | B79: ='BASE PAX'!B54 -> 0 | C79: ='BASE PAX'!C54 -> 0 | D79: =C79*0.2+C79 -> 0 | E79: =D79*B79 -> 0 | F79: =B79*C79 -> 0 | G79: =E79-F79 -> 0
A80: SUBTOTAL TRANSPORT | E80: =SUM(E75:E79) -> 0 | F80: =SUM(F75:F79) -> 0 | G80: =E80-F80 -> 0
A82: 6. EXPERIENCES | B82: QUANT. | C82: $ CUSTO | D82: $ VENDA | E82: SUBTOTAL | F82: SUBTOTAL CUSTO | G82: COMISSÕES
A83: ='BASE PAX'!A58 -> WS INSTRUCTOR | B83: ='BASE PAX'!B58 -> 0 | C83: ='BASE PAX'!C58 -> 3415000 | D83: =(C83*0.15)+C83 -> 3927250 | E83: =D83*B83 -> 0 | F83: =B83*C83 -> 0 | G83: =E83-F83 -> 0
A84: ='BASE PAX'!A59 -> PRODUCER FEE | B84: ='BASE PAX'!B59 -> 0 | C84: ='BASE PAX'!C59 -> 180000 | D84: =(C84*0.15)+C84 -> 207000 | E84: =D84*B84 -> 0 | F84: =B84*C84 -> 0 | G84: =E84-F84 -> 0
A85: ='BASE PAX'!A60 -> 0 | B85: ='BASE PAX'!B60 -> 0 | C85: ='BASE PAX'!C60 -> 20000 | D85: =(C85*0.15)+C85 -> 23000 | E85: =D85*B85 -> 0 | F85: =B85*C85 -> 0 | G85: =E85-F85 -> 0
A86: SUBTOTAL EXPERIENCES | E86: =SUM(E83:E85) -> 0 | F86: =SUM(F81:F85) -> 0 | G86: =E86-F86 -> 0
A88: 7. EXTRAS ( por cabin ) | B88: USOS | C88: $ CUSTO | D88: $ VENDA | E88: SUBTOTAL | G88: COMISSÕES
A89: ='BASE PAX'!A64 -> COORDENAÇÃO PRODUÇÃO | B89: ='BASE PAX'!B64 -> 0 | C89: ='BASE PAX'!C64 -> 50000 | D89: ='BASE PAX'!D64 -> 0 | E89: =D89*B89 -> 0 | G89: =E89*0.2 -> 0
A90: ='BASE PAX'!A65 -> EXTRA MÃO DE OBRA | B90: ='BASE PAX'!B65 -> 0 | C90: ='BASE PAX'!C65 -> 50000 | D90: ='BASE PAX'!D65 -> 0 | E90: =D90*B90 -> 0 | G90: =E90*0.2 -> 0
A91: ='BASE PAX'!A66 -> TAXA LIMPEZA CHECK IN / CHECKOUT | B91: ='BASE PAX'!B66 -> 0 | C91: ='BASE PAX'!C66 -> 40000 | D91: ='BASE PAX'!D66 -> 0 | E91: =D91*B91 -> 0 | G91: =E91*0.2 -> 0
A92: ='BASE PAX'!A67 -> TAXA LIMPEZA DIARIA | B92: ='BASE PAX'!B67 -> 0 | C92: ='BASE PAX'!C67 -> 30000 | D92: ='BASE PAX'!D67 -> 0 | E92: =D92*B92 -> 0 | G92: =E92*0.2 -> 0
A93: ='BASE PAX'!A68 -> SOUVENIR | B93: ='BASE PAX'!B68 -> 0 | C93: ='BASE PAX'!C68 -> 15000 | D93: ='BASE PAX'!D68 -> 0 | E93: =D93*B93 -> 0 | G93: =E93*0.2 -> 0
A94: ='BASE PAX'!A69 -> ASSISTENTE COORDENAÇÃO | B94: ='BASE PAX'!B69 -> 0 | C94: ='BASE PAX'!C69 -> 30000 | D94: ='BASE PAX'!D69 -> 0 | E94: =D94*B94 -> 0 | G94: =E94*0.2 -> 0
A95: SUBTOTAL EXTRAS | E95: =SUM(E89:E94) -> 0 | G95: =SUM(G89:G94) -> 0
A97: 8. QUINCHO (por cabin) | B97: USOS | C97: $ CUSTO | D97: $ VENDA | E97: SUBTOTAL
A98: ='BASE PAX'!A73 -> QUINCHO DAY USE / CABIN | B98: ='BASE PAX'!B73 -> 0 | C98: ='BASE PAX'!C73 -> 15000 | D98: =C98+(C98*0.2) -> 18000 | E98: =D98*B98 -> 0
A99: SUBTOTAL QUINCHO | E99: =E98 -> 0

Sheet BUDGET COIGUE 2
C3: COIGUE
A5: TOTAL PAX ADULT | B5: 2 | E5: COIGUE
A6: TOTAL PAX INFANT | B6: 0 | D6: BUDGET TOTAL | F6: =D21 -> 0
A7: CHECK IN. | B7: =CALENDAR!C2 -> 0 | D7: SUBTOTAL PAGO | F7: =SUM(F12:F20) -> 0
A8: CHECK OUT. | B8: =CALENDAR!C3 -> 0 | D8: SUBTOTAL A RECEBER | F8: =F6-F7 -> 0
A9: TOTAL NIGHTS. | B9: =CALENDAR!J2 -> 0 | D9: TIP |
A11: RESUMO. | B11: PREÇO CLIENTE CASH CLP $ | C11: TAXA CC | D11: PREÇO CLIENTE PAGTO CC $ | F11: =E5 -> COIGUE | I11: CONTROLE PAGAMENTOS
C12: 0.05 | I12: DATA | J12: VALOR PAGO CLP $ | K12: FORMA PAGTO
A13: 1.LODGING | B13: =G28 -> 0 | C13: =B13*$C$12 -> 0 | D13: =B13+(B13*$C$12) -> 0
A14: 2.FOOD | B14: =J49 -> 0 | C14: =B14*$C$12 -> 0 | D14: =B14+(B14*$C$12) -> 0 | F14: =A14 -> 2.FOOD | G14: =G49 -> 0
A15: 3.DRINKS | B15: =E59 -> 0 | C15: =B15*$C$12 -> 0 | D15: =B15+(B15*$C$12) -> 0 | F15: =A15 -> 3.DRINKS | G15: =G59 -> 0
A16: 4. ACTIVITIES | B16: =$E$72 -> 0 | C16: =B16*$C$12 -> 0 | D16: =B16+(B16*$C$12) -> 0 | F16: =A16 -> 4. ACTIVITIES | G16: =G72 -> 0
A17: 5.TRANSPORT | B17: =$E$80 -> 0 | C17: =B17*$C$12 -> 0 | D17: =B17+(B17*$C$12) -> 0 | F17: =A17 -> 5.TRANSPORT | G17: =G80 -> 0
A18: 6.EXPERIENCES | B18: =$E$86 -> 0 | C18: =B18*$C$12 -> 0 | D18: =B18+(B18*$C$12) -> 0 | F18: =A18 -> 6.EXPERIENCES | G18: =G86 -> 0
A19: 7.EXTRAS | B19: =$E$95 -> 0 | C19: =B19*$C$12 -> 0 | D19: =B19+(B19*$C$12) -> 0 | F19: =A19 -> 7.EXTRAS | G19: =G95 -> 0
A20: 8. QUINCHO | B20: =$E$99 -> 0 | C20: =B20*$C$12 -> 0 | D20: =B20+(B20*$C$12) -> 0 | F20: SUBTOTAL COMISSÕES | G20: =G14+G15+G16+G17+G18+G19 -> 0
A21: SUBTOTAL 1 | B21: =SUM(B13:B20) -> 0 | D21: =SUM(D13:D20) -> 0
A23: 1. LODGING | B23: QUANT. | C23: $ CABIN / DIA | D23: $ ADICIONAL / DIA | E23: BASE CÁLCULO | F23: DESCONTOS | G23: $ SUBTOTAL
A24: COIGUE (até 2 pax) - até 06 noites | B24: 1 | C24: =249200 -> 249200 | E24: =(C24+D24)*$B$9*B24 -> 0 | F24: 0 | G24: =E24-(E24*F24) -> 0
A25: COIGUE ( 2 + baby) - até 06 noites | B25: 0 | C25: =249200 -> 249200 | D25: 50000 | E25: =(C25+D25)*$B$9*B25 -> 0 | F25: 0 | G25: =E25-(E25*F25) -> 0
A26: COIGUE (até 2 pax) - 7 noites ou + | B26: 0 | C26: =224280 -> 224280 | E26: =(C26+D26)*$B$9*B26 -> 0 | F26: 0 | G26: =E26-(E26*F26) -> 0
A27: COIGUE ( 2 + baby) - 7 noites ou + | B27: 0 | C27: =224280 -> 224280 | D27: 50000 | E27: =(C27+D27)*$B$9*B27 -> 0 | F27: 0 | G27: =E27-(E27*F27) -> 0
A28: SUBTOTAL LODGING | G28: =SUM(G24:G27) -> 0
A30: 2. FOOD | B30: QUANT. | C30: $ CUSTO | D30: $ VENDA | E30: SUBTOTAL $ VENDA | F30: SUBTOTAL $ CUSTO | G30: COMISSÕES
A31: ='BASE PAX'!A6 -> BREAKFAST | B31: =(B5*B9*'BASE PAX'!G6)+('BASE PAX'!H6*B6*B9) -> 0 | E31: 0 | F31: =B31*C31 -> 0 | G31: =0.2*B31 -> 0 | H31: =A31 -> BREAKFAST | I31: =B31 -> 0
A32: ='BASE PAX'!A7 -> LUNCH 1 | B32: =($B$5+$B$6)*'BASE PAX'!B7 -> 0 | C32: ='BASE PAX'!C7 -> 40000 | D32: ='BASE PAX'!D7 -> 48000 | E32: =D32*B32 -> 0 | F32: =B32*C32 -> 0 | G32: =E32-F32 -> 0
A33: ='BASE PAX'!A8 -> LUNCH 2 | B33: =($B$5+$B$6)*'BASE PAX'!B8 -> 0 | C33: ='BASE PAX'!C8 -> 40000 | D33: ='BASE PAX'!D8 -> 48000 | E33: =D33*B33 -> 0 | F33: =B33*C33 -> 0 | G33: =E33-F33 -> 0
A34: ='BASE PAX'!A9 -> LUNCH 3 | B34: =($B$5+$B$6)*'BASE PAX'!B9 -> 0 | C34: ='BASE PAX'!C9 -> 40000 | D34: ='BASE PAX'!D9 -> 48000 | E34: =D34*B34 -> 0 | F34: =B34*C34 -> 0 | G34: =E34-F34 -> 0
A35: ='BASE PAX'!A10 -> LUNCH 4 | B35: =($B$5+$B$6)*'BASE PAX'!B10 -> 0 | C35: ='BASE PAX'!C10 -> 45000 | D35: ='BASE PAX'!D10 -> 54000 | E35: =D35*B35 -> 0 | F35: =B35*C35 -> 0 | G35: =E35-F35 -> 0
A36: ='BASE PAX'!A11 -> LUNCH 5 | B36: =($B$5+($B$6*0.6))*'BASE PAX'!B11 -> 0 | C36: ='BASE PAX'!C11 -> 50000 | D36: ='BASE PAX'!D11 -> 60000 | E36: =D36*B36 -> 0 | F36: =B36*C36 -> 0 | G36: =E36-F36 -> 0
A37: ='BASE PAX'!A12 -> LUNCH 6 | B37: =($B$5+$B$6)*'BASE PAX'!B12 -> 0 | C37: ='BASE PAX'!C12 -> 0 | D37: ='BASE PAX'!D12 -> 0 | E37: =D37*B37 -> 0 | F37: =B37*C37 -> 0 | G37: =E37-F37 -> 0
A38: ='BASE PAX'!A13 -> LUNCH 7 | B38: =($B$5+$B$6)*'BASE PAX'!B13 -> 0 | C38: ='BASE PAX'!C13 -> 5000 | D38: ='BASE PAX'!D13 -> 6000 | E38: =D38*B38 -> 0 | F38: =B38*C38 -> 0 | G38: =E38-F38 -> 0
A39: ='BASE PAX'!A14 -> SNACKS | B39: =($B$5+$B$6)*'BASE PAX'!B14 -> 0 | C39: ='BASE PAX'!C14 -> 8000 | D39: ='BASE PAX'!D14 -> 9600 | E39: =D39*B39 -> 0 | F39: =B39*C39 -> 0 | G39: =E39-F39 -> 0
A40: ='BASE PAX'!A15 -> DINNER 1 | B40: =($B$5+($B$6*0.6))*'BASE PAX'!B15 -> 0 | C40: ='BASE PAX'!C15 -> 70000 | D40: ='BASE PAX'!D15 -> 84000 | E40: =D40*B40 -> 0 | F40: =B40*C40 -> 0 | G40: =E40-F40 -> 0
A41: ='BASE PAX'!A16 -> DINNER 2 | B41: =($B$5+($B$6*0.6))*'BASE PAX'!B16 -> 0 | C41: ='BASE PAX'!C16 -> 25000 | D41: ='BASE PAX'!D16 -> 30000 | E41: =D41*B41 -> 0 | F41: =B41*C41 -> 0 | G41: =E41-F41 -> 0
A42: ='BASE PAX'!A17 -> DINNER 3 | B42: =($B$5+($B$6*0.6))*'BASE PAX'!B17 -> 0 | C42: ='BASE PAX'!C17 -> 50000 | D42: ='BASE PAX'!D17 -> 60000 | E42: =D42*B42 -> 0 | F42: =B42*C42 -> 0 | G42: =E42-F42 -> 0
A43: ='BASE PAX'!A18 -> DINNER 4 | B43: =($B$5+$B$6)*'BASE PAX'!B18 -> 0 | C43: ='BASE PAX'!C18 -> 65000 | D43: ='BASE PAX'!D18 -> 78000 | E43: =D43*B43 -> 0 | F43: =B43*C43 -> 0 | G43: =E43-F43 -> 0
A44: ='BASE PAX'!A19 -> DINNER 5 | B44: =($B$5+($B$6*0.6))*'BASE PAX'!B19 -> 0 | C44: ='BASE PAX'!C19 -> 75000 | D44: ='BASE PAX'!D19 -> 90000 | E44: =D44*B44 -> 0 | F44: =B44*C44 -> 0 | G44: =E44-F44 -> 0
A45: ='BASE PAX'!A20 -> DINNER 6 | B45: =($B$5+$B$6)*'BASE PAX'!B20 -> 0 | C45: ='BASE PAX'!C20 -> 0 | D45: ='BASE PAX'!D20 -> 0 | E45: =D45*B45 -> 0 | F45: =B45*C45 -> 0 | G45: =E45-F45 -> 0
A46: ='BASE PAX'!A21 -> DINNER 7 | B46: =($B$5+($B$6*0.6))*'BASE PAX'!B21 -> 0 | C46: ='BASE PAX'!C21 -> 75000 | D46: ='BASE PAX'!D21 -> 90000 | E46: =D46*B46 -> 0 | F46: =B46*C46 -> 0 | G46: =E46-F46 -> 0
A47: ='BASE PAX'!A22 -> QUANT. TOTAL | PADRAO ALMOÇO | B47: ='BASE PAX'!B22 -> 0 | G47: =0.2*I47 -> 0 | H47: =A47 -> QUANT. TOTAL | PADRAO ALMOÇO | I47: =(B5*B47*'BASE PAX'!G22)+(B6*B47*'BASE PAX'!H22) -> 0
A48: ='BASE PAX'!A23 -> QUANT. TOTAL | PADRAO JANTAR | B48: ='BASE PAX'!B23 -> 0 | G48: =0.2*I48 -> 0 | H48: =A48 -> QUANT. TOTAL | PADRAO JANTAR | I48: =(B5*B48*'BASE PAX'!G23)+(B6*B48*'BASE PAX'!H23) -> 0
A49: SUBTOTAL FOOD | E49: =SUM(E31:E48) -> 0 | F49: =SUM(F31:F48) -> 0 | G49: =SUM(G31:G48) -> 0 | H49: SUBTOTAL | I49: =I31+I47+I48 -> 0 | J49: =I49+E49 -> 0 | K49: TOTAL FOOD
A51: 3. DRINKS (por cabin) | B51: QUANT. | C51: $ CUSTO | D51: $ VENDA | E51: SUBTOTAL | F51: SUBTOTAL $ CUSTO | G51: COMISSÕES
A52: ='BASE PAX'!A27 -> SUCOS | B52: ='BASE PAX'!B27 -> 0 | C52: ='BASE PAX'!C27 -> 0 | D52: =(C52*0.2)+C52 -> 0 | E52: =D52*B52 -> 0 | F52: =B52*C52 -> 0 | G52: =E52-F52 -> 0
A53: ='BASE PAX'!A28 -> SUCOS | B53: ='BASE PAX'!B28 -> 0 | C53: ='BASE PAX'!C28 -> 0 | D53: =(C53*0.2)+C53 -> 0 | E53: =D53*B53 -> 0 | F53: =B53*C53 -> 0 | G53: =E53-F53 -> 0
A54: ='BASE PAX'!A29 -> CERVEJAS | B54: ='BASE PAX'!B29 -> 0 | C54: ='BASE PAX'!C29 -> 2000 | D54: =(C54*0.2)+C54 -> 2400 | E54: =D54*B54 -> 0 | F54: =B54*C54 -> 0 | G54: =E54-F54 -> 0
A55: ='BASE PAX'!A30 -> VINHOS | B55: ='BASE PAX'!B30 -> 0 | C55: ='BASE PAX'!C30 -> 8000 | D55: =(C55*0.2)+C55 -> 9600 | E55: =D55*B55 -> 0 | F55: =B55*C55 -> 0 | G55: =E55-F55 -> 0
A56: ='BASE PAX'!A31 -> DRINKS | B56: ='BASE PAX'!B31 -> 0 | C56: ='BASE PAX'!C31 -> 15000 | D56: =(C56*0.2)+C56 -> 18000 | E56: =D56*B56 -> 0 | F56: =B56*C56 -> 0 | G56: =E56-F56 -> 0
A57: ='BASE PAX'!A32 -> COOLER | B57: ='BASE PAX'!B32 -> 0 | C57: ='BASE PAX'!C32 -> 5000 | D57: =(C57*0.2)+C57 -> 6000 | E57: =D57*B57 -> 0 | F57: =B57*C57 -> 0 | G57: =E57-F57 -> 0
A58: ='BASE PAX'!A33 -> 0 | B58: ='BASE PAX'!B33 -> 0 | C58: ='BASE PAX'!C33 -> 0 | D58: =(C58*0.2)+C58 -> 0 | E58: =D58*B58 -> 0 | F58: =B58*C58 -> 0 | G58: =E58-F58 -> 0
A59: SUBTOTAL DRINKS | E59: =SUM(E52:E58) -> 0 | F59: =SUM(F52:F58) -> 0 | G59: =E59-F59 -> 0
A61: 4. ACTIVITIES | B61: QUANT. | C61: $ CUSTO | D61: $ VENDA | E61: SUBTOTAL | F61: SUBTOTAL $ CUSTO | G61: COMISSÕES
A62: ='BASE PAX'!A37 -> HOTTUBE | B62: ='BASE PAX'!B37 -> 0 | C62: ='BASE PAX'!C37 -> 12000 | D62: =C62*0.2+C62 -> 14400 | E62: =D62*B62 -> 0 | F62: =B62*C62 -> 0 | G62: =E62-F62 -> 0
A63: ='BASE PAX'!A38 -> TREKKING 1/2 DAY | B63: ='BASE PAX'!B38 -> 0 | C63: ='BASE PAX'!C38 -> 60000 | D63: =C63*0.2+C63 -> 72000 | E63: =D63*B63 -> 0 | F63: =B63*C63 -> 0 | G63: =E63-F63 -> 0
A64: ='BASE PAX'!A39 -> TREKKING FUK DAY | B64: ='BASE PAX'!B39 -> 0 | C64: ='BASE PAX'!C39 -> 90000 | D64: =C64*0.2+C64 -> 108000 | E64: =D64*B64 -> 0 | F64: =B64*C64 -> 0 | G64: =E64-F64 -> 0
A65: ='BASE PAX'!A40 -> FLOTADA FAMILIAR | B65: ='BASE PAX'!B40 -> 0 | C65: ='BASE PAX'!C40 -> 60000 | D65: =C65*0.2+C65 -> 72000 | E65: =D65*B65 -> 0 | F65: =B65*C65 -> 0 | G65: =E65-F65 -> 0
A66: ='BASE PAX'!A41 -> RAFTING 1/2 DAY | B66: ='BASE PAX'!B41 -> 0 | C66: ='BASE PAX'!C41 -> 75000 | D66: =C66*0.2+C66 -> 90000 | E66: =D66*B66 -> 0 | F66: =B66*C66 -> 0 | G66: =E66-F66 -> 0
A67: ='BASE PAX'!A42 -> RAFTING FULL DAY | B67: ='BASE PAX'!B42 -> 0 | C67: ='BASE PAX'!C42 -> 110000 | D67: =C67*0.2+C67 -> 132000 | E67: =D67*B67 -> 0 | F67: =B67*C67 -> 0 | G67: =E67-F67 -> 0
A68: ='BASE PAX'!A43 -> CABALGADA 1/2 DAy | B68: ='BASE PAX'!B43 -> 0 | C68: ='BASE PAX'!C43 -> 90000 | D68: =C68*0.2+C68 -> 108000 | E68: =D68*B68 -> 0 | F68: =B68*C68 -> 0 | G68: =E68-F68 -> 0
A69: ='BASE PAX'!A44 -> CABALGADA FULL DAY | B69: ='BASE PAX'!B44 -> 0 | C69: ='BASE PAX'!C44 -> 140000 | D69: =C69*0.2+C69 -> 168000 | E69: =D69*B69 -> 0 | F69: =B69*C69 -> 0 | G69: =E69-F69 -> 0
A70: ='BASE PAX'!A45 -> LANCHA YELCHO | B70: ='BASE PAX'!B45 -> 0 | C70: ='BASE PAX'!C45 -> 120000 | D70: =C70*0.2+C70 -> 144000 | E70: =D70*B70 -> 0 | F70: =B70*C70 -> 0 | G70: =E70-F70 -> 0
A71: ='BASE PAX'!A46 -> RECREACAO INFANTIL 3HS | B71: ='BASE PAX'!B46 -> 0 | C71: ='BASE PAX'!C46 -> 30000 | D71: =C71*0.2+C71 -> 36000 | E71: =D71*B71 -> 0 | F71: =B71*C71 -> 0 | G71: =E71-F71 -> 0
A72: SUBTOTAL ACTIVITIES | E72: =SUM(E62:E71) -> 0 | F72: =B72*C72 -> 0 | G72: =E72-F72 -> 0
A74: 5. TRANSPORT | B74: QUANT. | C74: $ CUSTO | D74: $ VENDA | E74: SUBTOTAL | F74: SUBTOTAL CUSTO | G74: COMISSÕES
A75: ='BASE PAX'!A50 -> TRANSFER AEROPORTO CHEGADA | B75: ='BASE PAX'!B50 -> 0 | C75: 50000 | D75: =C75*0.2+C75 -> 60000 | E75: =D75*B75 -> 0 | F75: =B75*C75 -> 0 | G75: =E75-F75 -> 0
A76: ='BASE PAX'!A51 -> TRANSFER AEROPORTO PARTIDA | B76: ='BASE PAX'!B51 -> 0 | C76: ='BASE PAX'!C51 -> 80000 | D76: =C76*0.2+C76 -> 96000 | E76: =D76*B76 -> 0 | F76: =B76*C76 -> 0 | G76: =E76-F76 -> 0
A77: ='BASE PAX'!A52 -> TRANSFERS INTERNO | B77: ='BASE PAX'!B52 -> 0 | C77: ='BASE PAX'!C52 -> 18000 | D77: =C77*0.2+C77 -> 21600 | E77: =D77*B77 -> 0 | F77: =B77*C77 -> 0 | G77: =E77-F77 -> 0
A78: ='BASE PAX'!A53 -> EXTRAS 1 | B78: ='BASE PAX'!B53 -> 0 | C78: ='BASE PAX'!C53 -> 150000 | D78: =C78*0.2+C78 -> 180000 | E78: =D78*B78 -> 0 | F78: =B78*C78 -> 0 | G78: =E78-F78 -> 0
A79: ='BASE PAX'!A54 -> EXTRAS 2 | B79: ='BASE PAX'!B54 -> 0 | C79: ='BASE PAX'!C54 -> 0 | D79: =C79*0.2+C79 -> 0 | E79: =D79*B79 -> 0 | F79: =B79*C79 -> 0 | G79: =E79-F79 -> 0
A80: SUBTOTAL TRANSPORT | E80: =SUM(E75:E79) -> 0 | F80: =SUM(F75:F79) -> 0 | G80: =E80-F80 -> 0
A82: 6. EXPERIENCES | B82: QUANT. | C82: $ CUSTO | D82: $ VENDA | E82: SUBTOTAL | F82: SUBTOTAL CUSTO | G82: COMISSÕES
A83: ='BASE PAX'!A58 -> WS INSTRUCTOR | B83: ='BASE PAX'!B58 -> 0 | C83: ='BASE PAX'!C58 -> 3415000 | D83: =(C83*0.15)+C83 -> 3927250 | E83: =D83*B83 -> 0 | F83: =B83*C83 -> 0 | G83: =E83-F83 -> 0
A84: ='BASE PAX'!A59 -> PRODUCER FEE | B84: ='BASE PAX'!B59 -> 0 | C84: ='BASE PAX'!C59 -> 180000 | D84: =(C84*0.15)+C84 -> 207000 | E84: =D84*B84 -> 0 | F84: =B84*C84 -> 0 | G84: =E84-F84 -> 0
A85: ='BASE PAX'!A60 -> 0 | B85: ='BASE PAX'!B60 -> 0 | C85: ='BASE PAX'!C60 -> 20000 | D85: =(C85*0.15)+C85 -> 23000 | E85: =D85*B85 -> 0 | F85: =B85*C85 -> 0 | G85: =E85-F85 -> 0
A86: SUBTOTAL EXPERIENCES | E86: =SUM(E83:E85) -> 0 | F86: =SUM(F81:F85) -> 0 | G86: =E86-F86 -> 0
A88: 7. EXTRAS ( por cabin ) | B88: USOS | C88: $ CUSTO | D88: $ VENDA | E88: SUBTOTAL | G88: COMISSÕES
A89: ='BASE PAX'!A64 -> COORDENAÇÃO PRODUÇÃO | B89: ='BASE PAX'!B64 -> 0 | C89: ='BASE PAX'!C64 -> 50000 | D89: ='BASE PAX'!D64 -> 0 | E89: =D89*B89 -> 0 | G89: =E89*0.2 -> 0
A90: ='BASE PAX'!A65 -> EXTRA MÃO DE OBRA | B90: ='BASE PAX'!B65 -> 0 | C90: ='BASE PAX'!C65 -> 50000 | D90: ='BASE PAX'!D65 -> 0 | E90: =D90*B90 -> 0 | G90: =E90*0.2 -> 0
A91: ='BASE PAX'!A66 -> TAXA LIMPEZA CHECK IN / CHECKOUT | B91: ='BASE PAX'!B66 -> 0 | C91: ='BASE PAX'!C66 -> 40000 | D91: ='BASE PAX'!D66 -> 0 | E91: =D91*B91 -> 0 | G91: =E91*0.2 -> 0
A92: ='BASE PAX'!A67 -> TAXA LIMPEZA DIARIA | B92: ='BASE PAX'!B67 -> 0 | C92: ='BASE PAX'!C67 -> 30000 | D92: ='BASE PAX'!D67 -> 0 | E92: =D92*B92 -> 0 | G92: =E92*0.2 -> 0
A93: ='BASE PAX'!A68 -> SOUVENIR | B93: ='BASE PAX'!B68 -> 0 | C93: ='BASE PAX'!C68 -> 15000 | D93: ='BASE PAX'!D68 -> 0 | E93: =D93*B93 -> 0 | G93: =E93*0.2 -> 0
A94: ='BASE PAX'!A69 -> ASSISTENTE COORDENAÇÃO | B94: ='BASE PAX'!B69 -> 0 | C94: ='BASE PAX'!C69 -> 30000 | D94: ='BASE PAX'!D69 -> 0 | E94: =D94*B94 -> 0 | G94: =E94*0.2 -> 0
A95: SUBTOTAL EXTRAS | E95: =SUM(E89:E94) -> 0 | G95: =SUM(G89:G94) -> 0
A97: 8. QUINCHO (por cabin) | B97: USOS | C97: $ CUSTO | D97: $ VENDA | E97: SUBTOTAL
A98: ='BASE PAX'!A73 -> QUINCHO DAY USE / CABIN | B98: ='BASE PAX'!B73 -> 0 | C98: ='BASE PAX'!C73 -> 15000 | D98: =C98+(C98*0.2) -> 18000 | E98: =D98*B98 -> 0
A99: SUBTOTAL QUINCHO | E99: =E98 -> 0

Sheet BUDGET COIGUE 2+1
C3: COIGUE
A5: TOTAL PAX ADULT | B5: 2 | E5: COIGUE
A6: TOTAL PAX INFANT | B6: 1 | D6: BUDGET TOTAL | F6: =D21 -> 0
A7: CHECK IN. | B7: =CALENDAR!C2 -> 0 | D7: SUBTOTAL PAGO | F7: =SUM(F12:F20) -> 0
A8: CHECK OUT. | B8: =CALENDAR!C3 -> 0 | D8: SUBTOTAL A RECEBER | F8: =F6-F7 -> 0
A9: TOTAL NIGHTS. | B9: =CALENDAR!J2 -> 0 | D9: TIP |
A11: RESUMO. | B11: PREÇO CLIENTE CASH CLP $ | C11: TAXA CC | D11: PREÇO CLIENTE PAGTO CC $ | F11: =E5 -> COIGUE | I11: CONTROLE PAGAMENTOS
C12: 0.05 | I12: DATA | J12: VALOR PAGO CLP $ | K12: FORMA PAGTO
A13: 1.LODGING | B13: =G28 -> 0 | C13: =B13*$C$12 -> 0 | D13: =B13+(B13*$C$12) -> 0
A14: 2.FOOD | B14: =J49 -> 0 | C14: =B14*$C$12 -> 0 | D14: =B14+(B14*$C$12) -> 0 | F14: =A14 -> 2.FOOD | G14: =G49 -> 0
A15: 3.DRINKS | B15: =E59 -> 0 | C15: =B15*$C$12 -> 0 | D15: =B15+(B15*$C$12) -> 0 | F15: =A15 -> 3.DRINKS | G15: =G59 -> 0
A16: 4. ACTIVITIES | B16: =$E$72 -> 0 | C16: =B16*$C$12 -> 0 | D16: =B16+(B16*$C$12) -> 0 | F16: =A16 -> 4. ACTIVITIES | G16: =G72 -> 0
A17: 5.TRANSPORT | B17: =$E$80 -> 0 | C17: =B17*$C$12 -> 0 | D17: =B17+(B17*$C$12) -> 0 | F17: =A17 -> 5.TRANSPORT | G17: =G80 -> 0
A18: 6.EXPERIENCES | B18: =$E$86 -> 0 | C18: =B18*$C$12 -> 0 | D18: =B18+(B18*$C$12) -> 0 | F18: =A18 -> 6.EXPERIENCES | G18: =G86 -> 0
A19: 7.EXTRAS | B19: =$E$95 -> 0 | C19: =B19*$C$12 -> 0 | D19: =B19+(B19*$C$12) -> 0 | F19: =A19 -> 7.EXTRAS | G19: =G95 -> 0
A20: 8. QUINCHO | B20: =$E$99 -> 0 | C20: =B20*$C$12 -> 0 | D20: =B20+(B20*$C$12) -> 0 | F20: SUBTOTAL COMISSÕES | G20: =G14+G15+G16+G17+G18+G19 -> 0
A21: SUBTOTAL 1 | B21: =SUM(B13:B20) -> 0 | D21: =SUM(D13:D20) -> 0
A23: 1. LODGING | B23: QUANT. | C23: $ CABIN / DIA | D23: $ ADICIONAL / DIA | E23: BASE CÁLCULO | F23: DESCONTOS | G23: $ SUBTOTAL
A24: COIGUE (até 2 pax) - até 06 noites | B24: 0 | C24: =249200 -> 249200 | E24: =(C24+D24)*$B$9*B24 -> 0 | F24: 0 | G24: =E24-(E24*F24) -> 0
A25: COIGUE ( 2 + baby) - até 06 noites | B25: 1 | C25: =249200 -> 249200 | D25: 50000 | E25: =(C25+D25)*$B$9*B25 -> 0 | F25: 0 | G25: =E25-(E25*F25) -> 0
A26: COIGUE (até 2 pax) - 7 noites ou + | B26: 0 | C26: =224280 -> 224280 | E26: =(C26+D26)*$B$9*B26 -> 0 | F26: 0 | G26: =E26-(E26*F26) -> 0
A27: COIGUE ( 2 + baby) - 7 noites ou + | B27: 0 | C27: =224280 -> 224280 | D27: 50000 | E27: =(C27+D27)*$B$9*B27 -> 0 | F27: 0 | G27: =E27-(E27*F27) -> 0
A28: SUBTOTAL LODGING | G28: =SUM(G24:G27) -> 0
A30: 2. FOOD | B30: QUANT. | C30: $ CUSTO | D30: $ VENDA | E30: SUBTOTAL $ VENDA | F30: SUBTOTAL $ CUSTO | G30: COMISSÕES
A31: ='BASE PAX'!A6 -> BREAKFAST | B31: =(B5*B9*'BASE PAX'!G6)+('BASE PAX'!H6*B6*B9) -> 0 | E31: 0 | F31: =B31*C31 -> 0 | G31: =0.2*B31 -> 0 | H31: =A31 -> BREAKFAST | I31: =B31 -> 0
A32: ='BASE PAX'!A7 -> LUNCH 1 | B32: =($B$5+$B$6)*'BASE PAX'!B7 -> 0 | C32: ='BASE PAX'!C7 -> 40000 | D32: ='BASE PAX'!D7 -> 48000 | E32: =D32*B32 -> 0 | F32: =B32*C32 -> 0 | G32: =E32-F32 -> 0
A33: ='BASE PAX'!A8 -> LUNCH 2 | B33: =($B$5+$B$6)*'BASE PAX'!B8 -> 0 | C33: ='BASE PAX'!C8 -> 40000 | D33: ='BASE PAX'!D8 -> 48000 | E33: =D33*B33 -> 0 | F33: =B33*C33 -> 0 | G33: =E33-F33 -> 0
A34: ='BASE PAX'!A9 -> LUNCH 3 | B34: =($B$5+$B$6)*'BASE PAX'!B9 -> 0 | C34: ='BASE PAX'!C9 -> 40000 | D34: ='BASE PAX'!D9 -> 48000 | E34: =D34*B34 -> 0 | F34: =B34*C34 -> 0 | G34: =E34-F34 -> 0
A35: ='BASE PAX'!A10 -> LUNCH 4 | B35: =($B$5+$B$6)*'BASE PAX'!B10 -> 0 | C35: ='BASE PAX'!C10 -> 45000 | D35: ='BASE PAX'!D10 -> 54000 | E35: =D35*B35 -> 0 | F35: =B35*C35 -> 0 | G35: =E35-F35 -> 0
A36: ='BASE PAX'!A11 -> LUNCH 5 | B36: =($B$5+($B$6*0.6))*'BASE PAX'!B11 -> 0 | C36: ='BASE PAX'!C11 -> 50000 | D36: ='BASE PAX'!D11 -> 60000 | E36: =D36*B36 -> 0 | F36: =B36*C36 -> 0 | G36: =E36-F36 -> 0
A37: ='BASE PAX'!A12 -> LUNCH 6 | B37: =($B$5+$B$6)*'BASE PAX'!B12 -> 0 | C37: ='BASE PAX'!C12 -> 0 | D37: ='BASE PAX'!D12 -> 0 | E37: =D37*B37 -> 0 | F37: =B37*C37 -> 0 | G37: =E37-F37 -> 0
A38: ='BASE PAX'!A13 -> LUNCH 7 | B38: =($B$5+$B$6)*'BASE PAX'!B13 -> 0 | C38: ='BASE PAX'!C13 -> 5000 | D38: ='BASE PAX'!D13 -> 6000 | E38: =D38*B38 -> 0 | F38: =B38*C38 -> 0 | G38: =E38-F38 -> 0
A39: ='BASE PAX'!A14 -> SNACKS | B39: =($B$5+$B$6)*'BASE PAX'!B14 -> 0 | C39: ='BASE PAX'!C14 -> 8000 | D39: ='BASE PAX'!D14 -> 9600 | E39: =D39*B39 -> 0 | F39: =B39*C39 -> 0 | G39: =E39-F39 -> 0
A40: ='BASE PAX'!A15 -> DINNER 1 | B40: =($B$5+($B$6*0.6))*'BASE PAX'!B15 -> 0 | C40: ='BASE PAX'!C15 -> 70000 | D40: ='BASE PAX'!D15 -> 84000 | E40: =D40*B40 -> 0 | F40: =B40*C40 -> 0 | G40: =E40-F40 -> 0
A41: ='BASE PAX'!A16 -> DINNER 2 | B41: =($B$5+($B$6*0.6))*'BASE PAX'!B16 -> 0 | C41: ='BASE PAX'!C16 -> 25000 | D41: ='BASE PAX'!D16 -> 30000 | E41: =D41*B41 -> 0 | F41: =B41*C41 -> 0 | G41: =E41-F41 -> 0
A42: ='BASE PAX'!A17 -> DINNER 3 | B42: =($B$5+($B$6*0.6))*'BASE PAX'!B17 -> 0 | C42: ='BASE PAX'!C17 -> 50000 | D42: ='BASE PAX'!D17 -> 60000 | E42: =D42*B42 -> 0 | F42: =B42*C42 -> 0 | G42: =E42-F42 -> 0
A43: ='BASE PAX'!A18 -> DINNER 4 | B43: =($B$5+$B$6)*'BASE PAX'!B18 -> 0 | C43: ='BASE PAX'!C18 -> 65000 | D43: ='BASE PAX'!D18 -> 78000 | E43: =D43*B43 -> 0 | F43: =B43*C43 -> 0 | G43: =E43-F43 -> 0
A44: ='BASE PAX'!A19 -> DINNER 5 | B44: =($B$5+($B$6*0.6))*'BASE PAX'!B19 -> 0 | C44: ='BASE PAX'!C19 -> 75000 | D44: ='BASE PAX'!D19 -> 90000 | E44: =D44*B44 -> 0 | F44: =B44*C44 -> 0 | G44: =E44-F44 -> 0
A45: ='BASE PAX'!A20 -> DINNER 6 | B45: =($B$5+$B$6)*'BASE PAX'!B20 -> 0 | C45: ='BASE PAX'!C20 -> 0 | D45: ='BASE PAX'!D20 -> 0 | E45: =D45*B45 -> 0 | F45: =B45*C45 -> 0 | G45: =E45-F45 -> 0
A46: ='BASE PAX'!A21 -> DINNER 7 | B46: =($B$5+($B$6*0.6))*'BASE PAX'!B21 -> 0 | C46: ='BASE PAX'!C21 -> 75000 | D46: ='BASE PAX'!D21 -> 90000 | E46: =D46*B46 -> 0 | F46: =B46*C46 -> 0 | G46: =E46-F46 -> 0
A47: ='BASE PAX'!A22 -> QUANT. TOTAL | PADRAO ALMOÇO | B47: ='BASE PAX'!B22 -> 0 | G47: =0.2*I47 -> 0 | H47: =A47 -> QUANT. TOTAL | PADRAO ALMOÇO | I47: =(B5*B47*'BASE PAX'!G22)+(B6*B47*'BASE PAX'!H22) -> 0
A48: ='BASE PAX'!A23 -> QUANT. TOTAL | PADRAO JANTAR | B48: ='BASE PAX'!B23 -> 0 | G48: =0.2*I48 -> 0 | H48: =A48 -> QUANT. TOTAL | PADRAO JANTAR | I48: =(B5*B48*'BASE PAX'!G23)+(B6*B48*'BASE PAX'!H23) -> 0
A49: SUBTOTAL FOOD | E49: =SUM(E31:E48) -> 0 | F49: =SUM(F31:F48) -> 0 | G49: =SUM(G31:G48) -> 0 | H49: SUBTOTAL | I49: =I31+I47+I48 -> 0 | J49: =I49+E49 -> 0 | K49: TOTAL FOOD
A51: 3. DRINKS (por cabin) | B51: QUANT. | C51: $ CUSTO | D51: $ VENDA | E51: SUBTOTAL | F51: SUBTOTAL $ CUSTO | G51: COMISSÕES
A52: ='BASE PAX'!A27 -> SUCOS | B52: ='BASE PAX'!B27 -> 0 | C52: ='BASE PAX'!C27 -> 0 | D52: =(C52*0.2)+C52 -> 0 | E52: =D52*B52 -> 0 | F52: =B52*C52 -> 0 | G52: =E52-F52 -> 0
A53: ='BASE PAX'!A28 -> SUCOS | B53: ='BASE PAX'!B28 -> 0 | C53: ='BASE PAX'!C28 -> 0 | D53: =(C53*0.2)+C53 -> 0 | E53: =D53*B53 -> 0 | F53: =B53*C53 -> 0 | G53: =E53-F53 -> 0
A54: ='BASE PAX'!A29 -> CERVEJAS | B54: ='BASE PAX'!B29 -> 0 | C54: ='BASE PAX'!C29 -> 2000 | D54: =(C54*0.2)+C54 -> 2400 | E54: =D54*B54 -> 0 | F54: =B54*C54 -> 0 | G54: =E54-F54 -> 0
A55: ='BASE PAX'!A30 -> VINHOS | B55: ='BASE PAX'!B30 -> 0 | C55: ='BASE PAX'!C30 -> 8000 | D55: =(C55*0.2)+C55 -> 9600 | E55: =D55*B55 -> 0 | F55: =B55*C55 -> 0 | G55: =E55-F55 -> 0
A56: ='BASE PAX'!A31 -> DRINKS | B56: ='BASE PAX'!B31 -> 0 | C56: ='BASE PAX'!C31 -> 15000 | D56: =(C56*0.2)+C56 -> 18000 | E56: =D56*B56 -> 0 | F56: =B56*C56 -> 0 | G56: =E56-F56 -> 0
A57: ='BASE PAX'!A32 -> COOLER | B57: ='BASE PAX'!B32 -> 0 | C57: ='BASE PAX'!C32 -> 5000 | D57: =(C57*0.2)+C57 -> 6000 | E57: =D57*B57 -> 0 | F57: =B57*C57 -> 0 | G57: =E57-F57 -> 0
A58: ='BASE PAX'!A33 -> 0 | B58: ='BASE PAX'!B33 -> 0 | C58: ='BASE PAX'!C33 -> 0 | D58: =(C58*0.2)+C58 -> 0 | E58: =D58*B58 -> 0 | F58: =B58*C58 -> 0 | G58: =E58-F58 -> 0
A59: SUBTOTAL DRINKS | E59: =SUM(E52:E58) -> 0 | F59: =SUM(F52:F58) -> 0 | G59: =E59-F59 -> 0
A61: 4. ACTIVITIES | B61: QUANT. | C61: $ CUSTO | D61: $ VENDA | E61: SUBTOTAL | F61: SUBTOTAL $ CUSTO | G61: COMISSÕES
A62: ='BASE PAX'!A37 -> HOTTUBE | B62: ='BASE PAX'!B37 -> 0 | C62: ='BASE PAX'!C37 -> 12000 | D62: =C62*0.2+C62 -> 14400 | E62: =D62*B62 -> 0 | F62: =B62*C62 -> 0 | G62: =E62-F62 -> 0
A63: ='BASE PAX'!A38 -> TREKKING 1/2 DAY | B63: ='BASE PAX'!B38 -> 0 | C63: ='BASE PAX'!C38 -> 60000 | D63: =C63*0.2+C63 -> 72000 | E63: =D63*B63 -> 0 | F63: =B63*C63 -> 0 | G63: =E63-F63 -> 0
A64: ='BASE PAX'!A39 -> TREKKING FUK DAY | B64: ='BASE PAX'!B39 -> 0 | C64: ='BASE PAX'!C39 -> 90000 | D64: =C64*0.2+C64 -> 108000 | E64: =D64*B64 -> 0 | F64: =B64*C64 -> 0 | G64: =E64-F64 -> 0
A65: ='BASE PAX'!A40 -> FLOTADA FAMILIAR | B65: ='BASE PAX'!B40 -> 0 | C65: ='BASE PAX'!C40 -> 60000 | D65: =C65*0.2+C65 -> 72000 | E65: =D65*B65 -> 0 | F65: =B65*C65 -> 0 | G65: =E65-F65 -> 0
A66: ='BASE PAX'!A41 -> RAFTING 1/2 DAY | B66: ='BASE PAX'!B41 -> 0 | C66: ='BASE PAX'!C41 -> 75000 | D66: =C66*0.2+C66 -> 90000 | E66: =D66*B66 -> 0 | F66: =B66*C66 -> 0 | G66: =E66-F66 -> 0
A67: ='BASE PAX'!A42 -> RAFTING FULL DAY | B67: ='BASE PAX'!B42 -> 0 | C67: ='BASE PAX'!C42 -> 110000 | D67: =C67*0.2+C67 -> 132000 | E67: =D67*B67 -> 0 | F67: =B67*C67 -> 0 | G67: =E67-F67 -> 0
A68: ='BASE PAX'!A43 -> CABALGADA 1/2 DAy | B68: ='BASE PAX'!B43 -> 0 | C68: ='BASE PAX'!C43 -> 90000 | D68: =C68*0.2+C68 -> 108000 | E68: =D68*B68 -> 0 | F68: =B68*C68 -> 0 | G68: =E68-F68 -> 0
A69: ='BASE PAX'!A44 -> CABALGADA FULL DAY | B69: ='BASE PAX'!B44 -> 0 | C69: ='BASE PAX'!C44 -> 140000 | D69: =C69*0.2+C69 -> 168000 | E69: =D69*B69 -> 0 | F69: =B69*C69 -> 0 | G69: =E69-F69 -> 0
A70: ='BASE PAX'!A45 -> LANCHA YELCHO | B70: ='BASE PAX'!B45 -> 0 | C70: ='BASE PAX'!C45 -> 120000 | D70: =C70*0.2+C70 -> 144000 | E70: =D70*B70 -> 0 | F70: =B70*C70 -> 0 | G70: =E70-F70 -> 0
A71: ='BASE PAX'!A46 -> RECREACAO INFANTIL 3HS | B71: ='BASE PAX'!B46 -> 0 | C71: ='BASE PAX'!C46 -> 30000 | D71: =C71*0.2+C71 -> 36000 | E71: =D71*B71 -> 0 | F71: =B71*C71 -> 0 | G71: =E71-F71 -> 0
A72: SUBTOTAL ACTIVITIES | E72: =SUM(E62:E71) -> 0 | F72: =B72*C72 -> 0 | G72: =E72-F72 -> 0
A74: 5. TRANSPORT | B74: QUANT. | C74: $ CUSTO | D74: $ VENDA | E74: SUBTOTAL | F74: SUBTOTAL CUSTO | G74: COMISSÕES
A75: ='BASE PAX'!A50 -> TRANSFER AEROPORTO CHEGADA | B75: ='BASE PAX'!B50 -> 0 | C75: 50000 | D75: =C75*0.2+C75 -> 60000 | E75: =D75*B75 -> 0 | F75: =B75*C75 -> 0 | G75: =E75-F75 -> 0
A76: ='BASE PAX'!A51 -> TRANSFER AEROPORTO PARTIDA | B76: ='BASE PAX'!B51 -> 0 | C76: ='BASE PAX'!C51 -> 80000 | D76: =C76*0.2+C76 -> 96000 | E76: =D76*B76 -> 0 | F76: =B76*C76 -> 0 | G76: =E76-F76 -> 0
A77: ='BASE PAX'!A52 -> TRANSFERS INTERNO | B77: ='BASE PAX'!B52 -> 0 | C77: ='BASE PAX'!C52 -> 18000 | D77: =C77*0.2+C77 -> 21600 | E77: =D77*B77 -> 0 | F77: =B77*C77 -> 0 | G77: =E77-F77 -> 0
A78: ='BASE PAX'!A53 -> EXTRAS 1 | B78: ='BASE PAX'!B53 -> 0 | C78: ='BASE PAX'!C53 -> 150000 | D78: =C78*0.2+C78 -> 180000 | E78: =D78*B78 -> 0 | F78: =B78*C78 -> 0 | G78: =E78-F78 -> 0
A79: ='BASE PAX'!A54 -> EXTRAS 2 | B79: ='BASE PAX'!B54 -> 0 | C79: ='BASE PAX'!C54 -> 0 | D79: =C79*0.2+C79 -> 0 | E79: =D79*B79 -> 0 | F79: =B79*C79 -> 0 | G79: =E79-F79 -> 0
A80: SUBTOTAL TRANSPORT | E80: =SUM(E75:E79) -> 0 | F80: =SUM(F75:F79) -> 0 | G80: =E80-F80 -> 0
A82: 6. EXPERIENCES | B82: QUANT. | C82: $ CUSTO | D82: $ VENDA | E82: SUBTOTAL | F82: SUBTOTAL CUSTO | G82: COMISSÕES
A83: ='BASE PAX'!A58 -> WS INSTRUCTOR | B83: ='BASE PAX'!B58 -> 0 | C83: ='BASE PAX'!C58 -> 3415000 | D83: =(C83*0.15)+C83 -> 3927250 | E83: =D83*B83 -> 0 | F83: =B83*C83 -> 0 | G83: =E83-F83 -> 0
A84: ='BASE PAX'!A59 -> PRODUCER FEE | B84: ='BASE PAX'!B59 -> 0 | C84: ='BASE PAX'!C59 -> 180000 | D84: =(C84*0.15)+C84 -> 207000 | E84: =D84*B84 -> 0 | F84: =B84*C84 -> 0 | G84: =E84-F84 -> 0
A85: ='BASE PAX'!A60 -> 0 | B85: ='BASE PAX'!B60 -> 0 | C85: ='BASE PAX'!C60 -> 20000 | D85: =(C85*0.15)+C85 -> 23000 | E85: =D85*B85 -> 0 | F85: =B85*C85 -> 0 | G85: =E85-F85 -> 0
A86: SUBTOTAL EXPERIENCES | E86: =SUM(E83:E85) -> 0 | F86: =SUM(F81:F85) -> 0 | G86: =E86-F86 -> 0
A88: 7. EXTRAS ( por cabin ) | B88: USOS | C88: $ CUSTO | D88: $ VENDA | E88: SUBTOTAL | G88: COMISSÕES
A89: ='BASE PAX'!A64 -> COORDENAÇÃO PRODUÇÃO | B89: ='BASE PAX'!B64 -> 0 | C89: ='BASE PAX'!C64 -> 50000 | D89: ='BASE PAX'!D64 -> 0 | E89: =D89*B89 -> 0 | G89: =E89*0.2 -> 0
A90: ='BASE PAX'!A65 -> EXTRA MÃO DE OBRA | B90: ='BASE PAX'!B65 -> 0 | C90: ='BASE PAX'!C65 -> 50000 | D90: ='BASE PAX'!D65 -> 0 | E90: =D90*B90 -> 0 | G90: =E90*0.2 -> 0
A91: ='BASE PAX'!A66 -> TAXA LIMPEZA CHECK IN / CHECKOUT | B91: ='BASE PAX'!B66 -> 0 | C91: ='BASE PAX'!C66 -> 40000 | D91: ='BASE PAX'!D66 -> 0 | E91: =D91*B91 -> 0 | G91: =E91*0.2 -> 0
A92: ='BASE PAX'!A67 -> TAXA LIMPEZA DIARIA | B92: ='BASE PAX'!B67 -> 0 | C92: ='BASE PAX'!C67 -> 30000 | D92: ='BASE PAX'!D67 -> 0 | E92: =D92*B92 -> 0 | G92: =E92*0.2 -> 0
A93: ='BASE PAX'!A68 -> SOUVENIR | B93: ='BASE PAX'!B68 -> 0 | C93: ='BASE PAX'!C68 -> 15000 | D93: ='BASE PAX'!D68 -> 0 | E93: =D93*B93 -> 0 | G93: =E93*0.2 -> 0
A94: ='BASE PAX'!A69 -> ASSISTENTE COORDENAÇÃO | B94: ='BASE PAX'!B69 -> 0 | C94: ='BASE PAX'!C69 -> 30000 | D94: ='BASE PAX'!D69 -> 0 | E94: =D94*B94 -> 0 | G94: =E94*0.2 -> 0
A95: SUBTOTAL EXTRAS | E95: =SUM(E89:E94) -> 0 | G95: =SUM(G89:G94) -> 0
A97: 8. QUINCHO (por cabin) | B97: USOS | C97: $ CUSTO | D97: $ VENDA | E97: SUBTOTAL
A98: ='BASE PAX'!A73 -> QUINCHO DAY USE / CABIN | B98: ='BASE PAX'!B73 -> 0 | C98: ='BASE PAX'!C73 -> 15000 | D98: =C98+(C98*0.2) -> 18000 | E98: =D98*B98 -> 0
A99: SUBTOTAL QUINCHO | E99: =E98 -> 0

Sheet BUDGET NIRE 1
C3: COIGUE
A5: TOTAL PAX ADULT | B5: 1 | E5: NIRE
A6: TOTAL PAX INFANT | B6: 0 | D6: BUDGET TOTAL | F6: =D21 -> 0
A7: CHECK IN. | B7: =CALENDAR!C2 -> 0 | D7: SUBTOTAL PAGO | F7: =SUM(F12:F20) -> 0
A8: CHECK OUT. | B8: =CALENDAR!C3 -> 0 | D8: SUBTOTAL A RECEBER | F8: =F6-F7 -> 0
A9: TOTAL NIGHTS. | B9: =CALENDAR!J2 -> 0 | D9: TIP |
A11: RESUMO. | B11: PREÇO CLIENTE CASH CLP $ | C11: TAXA CC | D11: PREÇO CLIENTE PAGTO CC $ | F11: =E5 -> NIRE | I11: CONTROLE PAGAMENTOS
C12: 0.05 | I12: DATA | J12: VALOR PAGO CLP $ | K12: FORMA PAGTO
A13: 1.LODGING | B13: =G28 -> 0 | C13: =B13*$C$12 -> 0 | D13: =B13+(B13*$C$12) -> 0
A14: 2.FOOD | B14: =J49 -> 0 | C14: =B14*$C$12 -> 0 | D14: =B14+(B14*$C$12) -> 0 | F14: =A14 -> 2.FOOD | G14: =G49 -> 0
A15: 3.DRINKS | B15: =E59 -> 0 | C15: =B15*$C$12 -> 0 | D15: =B15+(B15*$C$12) -> 0 | F15: =A15 -> 3.DRINKS | G15: =G59 -> 0
A16: 4. ACTIVITIES | B16: =$E$72 -> 0 | C16: =B16*$C$12 -> 0 | D16: =B16+(B16*$C$12) -> 0 | F16: =A16 -> 4. ACTIVITIES | G16: =G72 -> 0
A17: 5.TRANSPORT | B17: =$E$80 -> 0 | C17: =B17*$C$12 -> 0 | D17: =B17+(B17*$C$12) -> 0 | F17: =A17 -> 5.TRANSPORT | G17: =G80 -> 0
A18: 6.EXPERIENCES | B18: =$E$86 -> 0 | C18: =B18*$C$12 -> 0 | D18: =B18+(B18*$C$12) -> 0 | F18: =A18 -> 6.EXPERIENCES | G18: =G86 -> 0
A19: 7.EXTRAS | B19: =$E$95 -> 0 | C19: =B19*$C$12 -> 0 | D19: =B19+(B19*$C$12) -> 0 | F19: =A19 -> 7.EXTRAS | G19: =G95 -> 0
A20: 8. QUINCHO | B20: =$E$99 -> 0 | C20: =B20*$C$12 -> 0 | D20: =B20+(B20*$C$12) -> 0 | F20: SUBTOTAL COMISSÕES | G20: =G14+G15+G16+G17+G18+G19 -> 0
A21: SUBTOTAL 1 | B21: =SUM(B13:B20) -> 0 | D21: =SUM(D13:D20) -> 0
A23: 1. LODGING | B23: QUANT. | C23: $ CABIN / DIA | D23: $ ADICIONAL / DIA | E23: BASE CÁLCULO | F23: DESCONTOS | G23: $ SUBTOTAL
A24: NIRE (até 2 pax) - até 06 noites | B24: 1 | C24: =249200 -> 249200 | E24: =(C24+D24)*$B$9*B24 -> 0 | F24: 0 | G24: =E24-(E24*F24) -> 0
A25: NIRE ( 2 + baby) - até 06 noites | B25: 0 | C25: =249200 -> 249200 | D25: 50000 | E25: =(C25+D25)*$B$9*B25 -> 0 | F25: 0 | G25: =E25-(E25*F25) -> 0
A26: NIRE (até 2 pax) - 7 noites ou + | B26: 0 | C26: =224280 -> 224280 | E26: =(C26+D26)*$B$9*B26 -> 0 | F26: 0 | G26: =E26-(E26*F26) -> 0
A27: NIRE ( 2 + baby) - 7 noites ou + | B27: 0 | C27: =224280 -> 224280 | D27: 50000 | E27: =(C27+D27)*$B$9*B27 -> 0 | F27: 0 | G27: =E27-(E27*F27) -> 0
A28: SUBTOTAL LODGING | G28: =SUM(G24:G27) -> 0
A30: 2. FOOD | B30: QUANT. | C30: $ CUSTO | D30: $ VENDA | E30: SUBTOTAL $ VENDA | F30: SUBTOTAL $ CUSTO | G30: COMISSÕES
A31: ='BASE PAX'!A6 -> BREAKFAST | B31: =(B5*B9*'BASE PAX'!G6)+('BASE PAX'!H6*B6*B9) -> 0 | E31: 0 | F31: =B31*C31 -> 0 | G31: =0.2*B31 -> 0 | H31: =A31 -> BREAKFAST | I31: =B31 -> 0
A32: ='BASE PAX'!A7 -> LUNCH 1 | B32: =($B$5+$B$6)*'BASE PAX'!B7 -> 0 | C32: ='BASE PAX'!C7 -> 40000 | D32: ='BASE PAX'!D7 -> 48000 | E32: =D32*B32 -> 0 | F32: =B32*C32 -> 0 | G32: =E32-F32 -> 0
A33: ='BASE PAX'!A8 -> LUNCH 2 | B33: =($B$5+$B$6)*'BASE PAX'!B8 -> 0 | C33: ='BASE PAX'!C8 -> 40000 | D33: ='BASE PAX'!D8 -> 48000 | E33: =D33*B33 -> 0 | F33: =B33*C33 -> 0 | G33: =E33-F33 -> 0
A34: ='BASE PAX'!A9 -> LUNCH 3 | B34: =($B$5+$B$6)*'BASE PAX'!B9 -> 0 | C34: ='BASE PAX'!C9 -> 40000 | D34: ='BASE PAX'!D9 -> 48000 | E34: =D34*B34 -> 0 | F34: =B34*C34 -> 0 | G34: =E34-F34 -> 0
A35: ='BASE PAX'!A10 -> LUNCH 4 | B35: =($B$5+$B$6)*'BASE PAX'!B10 -> 0 | C35: ='BASE PAX'!C10 -> 45000 | D35: ='BASE PAX'!D10 -> 54000 | E35: =D35*B35 -> 0 | F35: =B35*C35 -> 0 | G35: =E35-F35 -> 0
A36: ='BASE PAX'!A11 -> LUNCH 5 | B36: =($B$5+$B$6)*'BASE PAX'!B11 -> 0 | C36: ='BASE PAX'!C11 -> 50000 | D36: ='BASE PAX'!D11 -> 60000 | E36: =D36*B36 -> 0 | F36: =B36*C36 -> 0 | G36: =E36-F36 -> 0
A37: ='BASE PAX'!A12 -> LUNCH 6 | B37: =($B$5+$B$6)*'BASE PAX'!B12 -> 0 | C37: ='BASE PAX'!C12 -> 0 | D37: ='BASE PAX'!D12 -> 0 | E37: =D37*B37 -> 0 | F37: =B37*C37 -> 0 | G37: =E37-F37 -> 0
A38: ='BASE PAX'!A13 -> LUNCH 7 | B38: =($B$5+$B$6)*'BASE PAX'!B13 -> 0 | C38: ='BASE PAX'!C13 -> 5000 | D38: ='BASE PAX'!D13 -> 6000 | E38: =D38*B38 -> 0 | F38: =B38*C38 -> 0 | G38: =E38-F38 -> 0
A39: ='BASE PAX'!A14 -> SNACKS | B39: =($B$5+$B$6)*'BASE PAX'!B14 -> 0 | C39: ='BASE PAX'!C14 -> 8000 | D39: ='BASE PAX'!D14 -> 9600 | E39: =D39*B39 -> 0 | F39: =B39*C39 -> 0 | G39: =E39-F39 -> 0
A40: ='BASE PAX'!A15 -> DINNER 1 | B40: =($B$5+$B$6)*'BASE PAX'!B15 -> 0 | C40: ='BASE PAX'!C15 -> 70000 | D40: ='BASE PAX'!D15 -> 84000 | E40: =D40*B40 -> 0 | F40: =B40*C40 -> 0 | G40: =E40-F40 -> 0
A41: ='BASE PAX'!A16 -> DINNER 2 | B41: =($B$5+$B$6)*'BASE PAX'!B16 -> 0 | C41: ='BASE PAX'!C16 -> 25000 | D41: ='BASE PAX'!D16 -> 30000 | E41: =D41*B41 -> 0 | F41: =B41*C41 -> 0 | G41: =E41-F41 -> 0
A42: ='BASE PAX'!A17 -> DINNER 3 | B42: =($B$5+$B$6)*'BASE PAX'!B17 -> 0 | C42: ='BASE PAX'!C17 -> 50000 | D42: ='BASE PAX'!D17 -> 60000 | E42: =D42*B42 -> 0 | F42: =B42*C42 -> 0 | G42: =E42-F42 -> 0
A43: ='BASE PAX'!A18 -> DINNER 4 | B43: =($B$5+$B$6)*'BASE PAX'!B18 -> 0 | C43: ='BASE PAX'!C18 -> 65000 | D43: ='BASE PAX'!D18 -> 78000 | E43: =D43*B43 -> 0 | F43: =B43*C43 -> 0 | G43: =E43-F43 -> 0
... A46: ='BASE PAX'!A21 -> DINNER 7 | B46: =($B$5+$B$6)*'BASE PAX'!B21 -> 0 | C46: ='BASE PAX'!C21 -> 75000 | D46: ='BASE PAX'!D21 -> 90000 | E46: =D46*B46 -> 0 | F46: =B46*C46 -> 0 | G46: =E46-F46 -> 0
A47: ='BASE PAX'!A22 -> QUANT. TOTAL | PADRAO ALMOÇO | B47: ='BASE PAX'!B22 -> 0 | G47: =0.2*I47 -> 0 | H47: =A47 -> QUANT. TOTAL | PADRAO ALMOÇO | I47: =(B5*B47*'BASE PAX'!G22)+(B6*B47*'BASE PAX'!H22) -> 0
A48: ='BASE PAX'!A23 -> QUANT. TOTAL | PADRAO JANTAR | B48: ='BASE PAX'!B23 -> 0 | G48: =0.2*I48 -> 0 | H48: =A48 -> QUANT. TOTAL | PADRAO JANTAR | I48: =(B5*B48*'BASE PAX'!G23)+(B6*B48*'BASE PAX'!H23) -> 0
A49: SUBTOTAL FOOD | E49: =SUM(E31:E48) -> 0 | F49: =SUM(F31:F48) -> 0 | G49: =SUM(G31:G48) -> 0 | H49: SUBTOTAL | I49: =I31+I47+I48 -> 0 | J49: =I49+E49 -> 0 | K49: TOTAL FOOD
A51: 3. DRINKS (por cabin) | B51: QUANT. | C51: $ CUSTO | D51: $ VENDA | E51: SUBTOTAL | F51: SUBTOTAL $ CUSTO | G51: COMISSÕES
A52: ='BASE PAX'!A27 -> SUCOS | B52: ='BASE PAX'!B27 -> 0 | C52: ='BASE PAX'!C27 -> 0 | D52: =(C52*0.2)+C52 -> 0 | E52: =D52*B52 -> 0 | F52: =B52*C52 -> 0 | G52: =E52-F52 -> 0
A53: ='BASE PAX'!A28 -> SUCOS | B53: ='BASE PAX'!B28 -> 0 | C53: ='BASE PAX'!C28 -> 0 | D53: =(C53*0.2)+C53 -> 0 | E53: =D53*B53 -> 0 | F53: =B53*C53 -> 0 | G53: =E53-F53 -> 0
A54: ='BASE PAX'!A29 -> CERVEJAS | B54: ='BASE PAX'!B29 -> 0 | C54: ='BASE PAX'!C29 -> 2000 | D54: =(C54*0.2)+C54 -> 2400 | E54: =D54*B54 -> 0 | F54: =B54*C54 -> 0 | G54: =E54-F54 -> 0
A55: ='BASE PAX'!A30 -> VINHOS | B55: ='BASE PAX'!B30 -> 0 | C55: ='BASE PAX'!C30 -> 8000 | D55: =(C55*0.2)+C55 -> 9600 | E55: =D55*B55 -> 0 | F55: =B55*C55 -> 0 | G55: =E55-F55 -> 0
A56: ='BASE PAX'!A31 -> DRINKS | B56: ='BASE PAX'!B31 -> 0 | C56: ='BASE PAX'!C31 -> 15000 | D56: =(C56*0.2)+C56 -> 18000 | E56: =D56*B56 -> 0 | F56: =B56*C56 -> 0 | G56: =E56-F56 -> 0
A57: ='BASE PAX'!A32 -> COOLER | B57: ='BASE PAX'!B32 -> 0 | C57: ='BASE PAX'!C32 -> 5000 | D57: =(C57*0.2)+C57 -> 6000 | E57: =D57*B57 -> 0 | F57: =B57*C57 -> 0 | G57: =E57-F57 -> 0
A58: ='BASE PAX'!A33 -> 0 | B58: ='BASE PAX'!B33 -> 0 | C58: ='BASE PAX'!C33 -> 0 | D58: =(C58*0.2)+C58 -> 0 | E58: =D58*B58 -> 0 | F58: =B58*C58 -> 0 | G58: =E58-F58 -> 0
A59: SUBTOTAL DRINKS | E59: =SUM(E52:E58) -> 0 | F59: =SUM(F52:F58) -> 0 | G59: =E59-F59 -> 0
A61: 4. ACTIVITIES | B61: QUANT. | C61: $ CUSTO | D61: $ VENDA | E61: SUBTOTAL | F61: SUBTOTAL $ CUSTO | G61: COMISSÕES
A62: ='BASE PAX'!A37 -> HOTTUBE | B62: ='BASE PAX'!B37 -> 0 | C62: ='BASE PAX'!C37 -> 12000 | D62: =C62*0.2+C62 -> 14400 | E62: =D62*B62 -> 0 | F62: =B62*C62 -> 0 | G62: =E62-F62 -> 0
A63: ='BASE PAX'!A38 -> TREKKING 1/2 DAY | B63: ='BASE PAX'!B38 -> 0 | C63: ='BASE PAX'!C38 -> 60000 | D63: =C63*0.2+C63 -> 72000 | E63: =D63*B63 -> 0 | F63: =B63*C63 -> 0 | G63: =E63-F63 -> 0
A64: ='BASE PAX'!A39 -> TREKKING FUK DAY | B64: ='BASE PAX'!B39 -> 0 | C64: ='BASE PAX'!C39 -> 90000 | D64: =C64*0.2+C64 -> 108000 | E64: =D64*B64 -> 0 | F64: =B64*C64 -> 0 | G64: =E64-F64 -> 0
A65: ='BASE PAX'!A40 -> FLOTADA FAMILIAR | B65: ='BASE PAX'!B40 -> 0 | C65: ='BASE PAX'!C40 -> 60000 | D65: =C65*0.2+C65 -> 72000 | E65: =D65*B65 -> 0 | F65: =B65*C65 -> 0 | G65: =E65-F65 -> 0
A66: ='BASE PAX'!A41 -> RAFTING 1/2 DAY | B66: ='BASE PAX'!B41 -> 0 | C66: ='BASE PAX'!C41 -> 75000 | D66: =C66*0.2+C66 -> 90000 | E66: =D66*B66 -> 0 | F66: =B66*C66 -> 0 | G66: =E66-F66 -> 0
A67: ='BASE PAX'!A42 -> RAFTING FULL DAY | B67: ='BASE PAX'!B42 -> 0 | C67: ='BASE PAX'!C42 -> 110000 | D67: =C67*0.2+C67 -> 132000 | E67: =D67*B67 -> 0 | F67: =B67*C67 -> 0 | G67: =E67-F67 -> 0
A68: ='BASE PAX'!A43 -> CABALGADA 1/2 DAy | B68: ='BASE PAX'!B43 -> 0 | C68: ='BASE PAX'!C43 -> 90000 | D68: =C68*0.2+C68 -> 108000 | E68: =D68*B68 -> 0 | F68: =B68*C68 -> 0 | G68: =E68-F68 -> 0
A69: ='BASE PAX'!A44 -> CABALGADA FULL DAY | B69: ='BASE PAX'!B44 -> 0 | C69: ='BASE PAX'!C44 -> 140000 | D69: =C69*0.2+C69 -> 168000 | E69: =D69*B69 -> 0 | F69: =B69*C69 -> 0 | G69: =E69-F69 -> 0
A70: ='BASE PAX'!A45 -> LANCHA YELCHO | B70: ='BASE PAX'!B45 -> 0 | C70: ='BASE PAX'!C45 -> 120000 | D70: =C70*0.2+C70 -> 144000 | E70: =D70*B70 -> 0 | F70: =B70*C70 -> 0 | G70: =E70-F70 -> 0
A71: ='BASE PAX'!A46 -> RECREACAO INFANTIL 3HS | B71: ='BASE PAX'!B46 -> 0 | C71: ='BASE PAX'!C46 -> 30000 | D71: =C71*0.2+C71 -> 36000 | E71: =D71*B71 -> 0 | F71: =B71*C71 -> 0 | G71: =E71-F71 -> 0
A72: SUBTOTAL ACTIVITIES | E72: =SUM(E62:E71) -> 0 | F72: =B72*C72 -> 0 | G72: =E72-F72 -> 0
A74: 5. TRANSPORT | B74: QUANT. | C74: $ CUSTO | D74: $ VENDA | E74: SUBTOTAL | F74: SUBTOTAL CUSTO | G74: COMISSÕES
A75: ='BASE PAX'!A50 -> TRANSFER AEROPORTO CHEGADA | B75: ='BASE PAX'!B50 -> 0 | C75: ='BASE PAX'!C50 -> 80000 | D75: =C75*0.2+C75 -> 96000 | E75: =D75*B75 -> 0 | F75: =B75*C75 -> 0 | G75: =E75-F75 -> 0
A76: ='BASE PAX'!A51 -> TRANSFER AEROPORTO PARTIDA | B76: ='BASE PAX'!B51 -> 0 | C76: ='BASE PAX'!C51 -> 80000 | D76: =C76*0.2+C76 -> 96000 | E76: =D76*B76 -> 0 | F76: =B76*C76 -> 0 | G76: =E76-F76 -> 0
A77: ='BASE PAX'!A52 -> TRANSFERS INTERNO | B77: ='BASE PAX'!B52 -> 0 | C77: ='BASE PAX'!C52 -> 18000 | D77: =C77*0.2+C77 -> 21600 | E77: =D77*B77 -> 0 | F77: =B77*C77 -> 0 | G77: =E77-F77 -> 0
A78: ='BASE PAX'!A53 -> EXTRAS 1 | B78: ='BASE PAX'!B53 -> 0 | C78: ='BASE PAX'!C53 -> 150000 | D78: =C78*0.2+C78 -> 180000 | E78: =D78*B78 -> 0 | F78: =B78*C78 -> 0 | G78: =E78-F78 -> 0
A79: ='BASE PAX'!A54 -> EXTRAS 2 | B79: ='BASE PAX'!B54 -> 0 | C79: ='BASE PAX'!C54 -> 0 | D79: =C79*0.2+C79 -> 0 | E79: =D79*B79 -> 0 | F79: =B79*C79 -> 0 | G79: =E79-F79 -> 0
A80: SUBTOTAL TRANSPORT | E80: =SUM(E75:E79) -> 0 | F80: =SUM(F75:F79) -> 0 | G80: =E80-F80 -> 0
A82: 6. EXPERIENCES | B82: QUANT. | C82: $ CUSTO | D82: $ VENDA | E82: SUBTOTAL | F82: SUBTOTAL CUSTO | G82: COMISSÕES
A83: ='BASE PAX'!A58 -> WS INSTRUCTOR | B83: ='BASE PAX'!B58 -> 0 | C83: ='BASE PAX'!C58 -> 3415000 | D83: =(C83*0.15)+C83 -> 3927250 | E83: =D83*B83 -> 0 | F83: =B83*C83 -> 0 | G83: =E83-F83 -> 0
A84: ='BASE PAX'!A59 -> PRODUCER FEE | B84: ='BASE PAX'!B59 -> 0 | C84: ='BASE PAX'!C59 -> 180000 | D84: =(C84*0.15)+C84 -> 207000 | E84: =D84*B84 -> 0 | F84: =B84*C84 -> 0 | G84: =E84-F84 -> 0
A85: ='BASE PAX'!A60 -> 0 | B85: ='BASE PAX'!B60 -> 0 | C85: ='BASE PAX'!C60 -> 20000 | D85: =(C85*0.15)+C85 -> 23000 | E85: =D85*B85 -> 0 | F85: =B85*C85 -> 0 | G85: =E85-F85 -> 0
A86: SUBTOTAL EXPERIENCES | E86: =SUM(E83:E85) -> 0 | F86: =SUM(F81:F85) -> 0 | G86: =E86-F86 -> 0
A88: 7. EXTRAS ( por cabin ) | B88: USOS | C88: $ CUSTO | D88: $ VENDA | E88: SUBTOTAL | G88: COMISSÕES
A89: ='BASE PAX'!A64 -> COORDENAÇÃO PRODUÇÃO | B89: ='BASE PAX'!B64 -> 0 | C89: ='BASE PAX'!C64 -> 50000 | D89: ='BASE PAX'!D64 -> 0 | E89: =D89*B89 -> 0 | G89: =E89*0.2 -> 0
A90: ='BASE PAX'!A65 -> EXTRA MÃO DE OBRA | B90: ='BASE PAX'!B65 -> 0 | C90: ='BASE PAX'!C65 -> 50000 | D90: ='BASE PAX'!D65 -> 0 | E90: =D90*B90 -> 0 | G90: =E90*0.2 -> 0
A91: ='BASE PAX'!A66 -> TAXA LIMPEZA CHECK IN / CHECKOUT | B91: ='BASE PAX'!B66 -> 0 | C91: ='BASE PAX'!C66 -> 40000 | D91: ='BASE PAX'!D66 -> 0 | E91: =D91*B91 -> 0 | G91: =E91*0.2 -> 0
A92: ='BASE PAX'!A67 -> TAXA LIMPEZA DIARIA | B92: ='BASE PAX'!B67 -> 0 | C92: ='BASE PAX'!C67 -> 30000 | D92: ='BASE PAX'!D67 -> 0 | E92: =D92*B92 -> 0 | G92: =E92*0.2 -> 0
A93: ='BASE PAX'!A68 -> SOUVENIR | B93: ='BASE PAX'!B68 -> 0 | C93: ='BASE PAX'!C68 -> 15000 | D93: ='BASE PAX'!D68 -> 0 | E93: =D93*B93 -> 0 | G93: =E93*0.2 -> 0
A94: ='BASE PAX'!A69 -> ASSISTENTE COORDENAÇÃO | B94: ='BASE PAX'!B69 -> 0 | C94: ='BASE PAX'!C69 -> 30000 | D94: ='BASE PAX'!D69 -> 0 | E94: =D94*B94 -> 0 | G94: =E94*0.2 -> 0
A95: SUBTOTAL EXTRAS | E95: =SUM(E89:E94) -> 0 | G95: =SUM(G89:G94) -> 0
A97: 8. QUINCHO (por cabin) | B97: USOS | C97: $ CUSTO | D97: $ VENDA | E97: SUBTOTAL
A98: ='BASE PAX'!A73 -> QUINCHO DAY USE / CABIN | B98: ='BASE PAX'!B73 -> 0 | C98: ='BASE PAX'!C73 -> 15000 | D98: =C98+(C98*0.2) -> 18000 | E98: =D98*B98 -> 0
A99: SUBTOTAL QUINCHO | E99: =E98 -> 0

Sheet BUDGET NIRE 2
C3: COIGUE
A5: TOTAL PAX ADULT | B5: 2 | E5: NIRE
A6: TOTAL PAX INFANT | B6: 0 | D6: BUDGET TOTAL | F6: =D21 -> 0
A7: CHECK IN. | B7: =CALENDAR!C2 -> 0 | D7: SUBTOTAL PAGO | F7: =SUM(F12:F20) -> 0
A8: CHECK OUT. | B8: =CALENDAR!C3 -> 0 | D8: SUBTOTAL A RECEBER | F8: =F6-F7 -> 0
A9: TOTAL NIGHTS. | B9: =CALENDAR!J2 -> 0 | D9: TIP |
A11: RESUMO. | B11: PREÇO CLIENTE CASH CLP $ | C11: TAXA CC | D11: PREÇO CLIENTE PAGTO CC $ | F11: =E5 -> NIRE | I11: CONTROLE PAGAMENTOS
C12: 0.05 | I12: DATA | J12: VALOR PAGO CLP $ | K12: FORMA PAGTO
A13: 1.LODGING | B13: =G28 -> 0 | C13: =B13*$C$12 -> 0 | D13: =B13+(B13*$C$12) -> 0
A14: 2.FOOD | B14: =J49 -> 0 | C14: =B14*$C$12 -> 0 | D14: =B14+(B14*$C$12) -> 0 | F14: =A14 -> 2.FOOD | G14: =G49 -> 0
A15: 3.DRINKS | B15: =E59 -> 0 | C15: =B15*$C$12 -> 0 | D15: =B15+(B15*$C$12) -> 0 | F15: =A15 -> 3.DRINKS | G15: =G59 -> 0
A16: 4. ACTIVITIES | B16: =$E$72 -> 0 | C16: =B16*$C$12 -> 0 | D16: =B16+(B16*$C$12) -> 0 | F16: =A16 -> 4. ACTIVITIES | G16: =G72 -> 0
A17: 5.TRANSPORT | B17: =$E$80 -> 0 | C17: =B17*$C$12 -> 0 | D17: =B17+(B17*$C$12) -> 0 | F17: =A17 -> 5.TRANSPORT | G17: =G80 -> 0
A18: 6.EXPERIENCES | B18: =$E$86 -> 0 | C18: =B18*$C$12 -> 0 | D18: =B18+(B18*$C$12) -> 0 | F18: =A18 -> 6.EXPERIENCES | G18: =G86 -> 0
A19: 7.EXTRAS | B19: =$E$95 -> 0 | C19: =B19*$C$12 -> 0 | D19: =B19+(B19*$C$12) -> 0 | F19: =A19 -> 7.EXTRAS | G19: =G95 -> 0
A20: 8. QUINCHO | B20: =$E$99 -> 0 | C20: =B20*$C$12 -> 0 | D20: =B20+(B20*$C$12) -> 0 | F20: SUBTOTAL COMISSÕES | G20: =G14+G15+G16+G17+G18+G19 -> 0
A21: SUBTOTAL 1 | B21: =SUM(B13:B20) -> 0 | D21: =SUM(D13:D20) -> 0
A23: 1. LODGING | B23: QUANT. | C23: $ CABIN / DIA | D23: $ ADICIONAL / DIA | E23: BASE CÁLCULO | F23: DESCONTOS | G23: $ SUBTOTAL
A24: NIRE (até 2 pax) - até 06 noites | B24: 0 | C24: =249200 -> 249200 | E24: =(C24+D24)*$B$9*B24 -> 0 | F24: 0 | G24: =E24-(E24*F24) -> 0
A25: NIRE ( 2 + baby) - até 06 noites | B25: 1 | C25: =249200 -> 249200 | D25: 50000 | E25: =(C25+D25)*$B$9*B25 -> 0 | F25: 0 | G25: =E25-(E25*F25) -> 0
A26: NIRE (até 2 pax) - 7 noites ou + | B26: 0 | C26: =224280 -> 224280 | E26: =(C26+D26)*$B$9*B26 -> 0 | F26: 0 | G26: =E26-(E26*F26) -> 0
A27: NIRE ( 2 + baby) - 7 noites ou + | B27: 0 | C27: =224280 -> 224280 | D27: 50000 | E27: =(C27+D27)*$B$9*B27 -> 0 | F27: 0 | G27: =E27-(E27*F27) -> 0
A28: SUBTOTAL LODGING | G28: =SUM(G24:G27) -> 0
A30: 2. FOOD | B30: QUANT. | C30: $ CUSTO | D30: $ VENDA | E30: SUBTOTAL $ VENDA | F30: SUBTOTAL $ CUSTO | G30: COMISSÕES
A31: ='BASE PAX'!A6 -> BREAKFAST | B31: =(B5*B9*'BASE PAX'!G6)+('BASE PAX'!H6*B6*B9) -> 0 | E31: 0 | F31: =B31*C31 -> 0 | G31: =0.2*B31 -> 0 | H31: =A31 -> BREAKFAST | I31: =B31 -> 0
A32: ='BASE PAX'!A7 -> LUNCH 1 | B32: =($B$5+$B$6)*'BASE PAX'!B7 -> 0 | C32: ='BASE PAX'!C7 -> 40000 | D32: ='BASE PAX'!D7 -> 48000 | E32: =D32*B32 -> 0 | F32: =B32*C32 -> 0 | G32: =E32-F32 -> 0
A33: ='BASE PAX'!A8 -> LUNCH 2 | B33: =($B$5+$B$6)*'BASE PAX'!B8 -> 0 | C33: ='BASE PAX'!C8 -> 40000 | D33: ='BASE PAX'!D8 -> 48000 | E33: =D33*B33 -> 0 | F33: =B33*C33 -> 0 | G33: =E33-F33 -> 0
A34: ='BASE PAX'!A9 -> LUNCH 3 | B34: =($B$5+$B$6)*'BASE PAX'!B9 -> 0 | C34: ='BASE PAX'!C9 -> 40000 | D34: ='BASE PAX'!D9 -> 48000 | E34: =D34*B34 -> 0 | F34: =B34*C34 -> 0 | G34: =E34-F34 -> 0
A35: ='BASE PAX'!A10 -> LUNCH 4 | B35: =($B$5+$B$6)*'BASE PAX'!B10 -> 0 | C35: ='BASE PAX'!C10 -> 45000 | D35: ='BASE PAX'!D10 -> 54000 | E35: =D35*B35 -> 0 | F35: =B35*C35 -> 0 | G35: =E35-F35 -> 0
A36: ='BASE PAX'!A11 -> LUNCH 5 | B36: =($B$5+($B$6*0.6))*'BASE PAX'!B11 -> 0 | C36: ='BASE PAX'!C11 -> 50000 | D36: ='BASE PAX'!D11 -> 60000 | E36: =D36*B36 -> 0 | F36: =B36*C36 -> 0 | G36: =E36-F36 -> 0
A37: ='BASE PAX'!A12 -> LUNCH 6 | B37: =($B$5+$B$6)*'BASE PAX'!B12 -> 0 | C37: ='BASE PAX'!C12 -> 0 | D37: ='BASE PAX'!D12 -> 0 | E37: =D37*B37 -> 0 | F37: =B37*C37 -> 0 | G37: =E37-F37 -> 0
A38: ='BASE PAX'!A13 -> LUNCH 7 | B38: =($B$5+$B$6)*'BASE PAX'!B13 -> 0 | C38: ='BASE PAX'!C13 -> 5000 | D38: ='BASE PAX'!D13 -> 6000 | E38: =D38*B38 -> 0 | F38: =B38*C38 -> 0 | G38: =E38-F38 -> 0
A39: ='BASE PAX'!A14 -> SNACKS | B39: =($B$5+$B$6)*'BASE PAX'!B14 -> 0 | C39: ='BASE PAX'!C14 -> 8000 | D39: ='BASE PAX'!D14 -> 9600 | E39: =D39*B39 -> 0 | F39: =B39*C39 -> 0 | G39: =E39-F39 -> 0
A40: ='BASE PAX'!A15 -> DINNER 1 | B40: =($B$5+($B$6*0.6))*'BASE PAX'!B15 -> 0 | C40: ='BASE PAX'!C15 -> 70000 | D40: ='BASE PAX'!D15 -> 84000 | E40: =D40*B40 -> 0 | F40: =B40*C40 -> 0 | G40: =E40-F40 -> 0
A41: ='BASE PAX'!A16 -> DINNER 2 | B41: =($B$5+($B$6*0.6))*'BASE PAX'!B16 -> 0 | C41: ='BASE PAX'!C16 -> 25000 | D41: ='BASE PAX'!D16 -> 30000 | E41: =D41*B41 -> 0 | F41: =B41*C41 -> 0 | G41: =E41-F41 -> 0
A42: ='BASE PAX'!A17 -> DINNER 3 | B42: =($B$5+($B$6*0.6))*'BASE PAX'!B17 -> 0 | C42: ='BASE PAX'!C17 -> 50000 | D42: ='BASE PAX'!D17 -> 60000 | E42: =D42*B42 -> 0 | F42: =B42*C42 -> 0 | G42: =E42-F42 -> 0
A43: ='BASE PAX'!A18 -> DINNER 4 | B43: =($B$5+$B$6)*'BASE PAX'!B18 -> 0 | C43: ='BASE PAX'!C18 -> 65000 | D43: ='BASE PAX'!D18 -> 78000 | E43: =D43*B43 -> 0 | F43: =B43*C43 -> 0 | G43: =E43-F43 -> 0
A44: ='BASE PAX'!A19 -> DINNER 5 | B44: =($B$5+($B$6*0.6))*'BASE PAX'!B19 -> 0 | C44: ='BASE PAX'!C19 -> 75000 | D44: ='BASE PAX'!D19 -> 90000 | E44: =D44*B44 -> 0 | F44: =B44*C44 -> 0 | G44: =E44-F44 -> 0
A45: ='BASE PAX'!A20 -> DINNER 6 | B45: =($B$5+$B$6)*'BASE PAX'!B20 -> 0 | C45: ='BASE PAX'!C20 -> 0 | D45: ='BASE PAX'!D20 -> 0 | E45: =D45*B45 -> 0 | F45: =B45*C45 -> 0 | G45: =E45-F45 -> 0
A46: ='BASE PAX'!A21 -> DINNER 7 | B46: =($B$5+($B$6*0.6))*'BASE PAX'!B21 -> 0 | C46: ='BASE PAX'!C21 -> 75000 | D46: ='BASE PAX'!D21 -> 90000 | E46: =D46*B46 -> 0 | F46: =B46*C46 -> 0 | G46: =E46-F46 -> 0
A47: ='BASE PAX'!A22 -> QUANT. TOTAL | PADRAO ALMOÇO | B47: ='BASE PAX'!B22 -> 0 | G47: =0.2*I47 -> 0 | H47: =A47 -> QUANT. TOTAL | PADRAO ALMOÇO | I47: =(B5*B47*'BASE PAX'!G22)+(B6*B47*'BASE PAX'!H22) -> 0
A48: ='BASE PAX'!A23 -> QUANT. TOTAL | PADRAO JANTAR | B48: ='BASE PAX'!B23 -> 0 | G48: =0.2*I48 -> 0 | H48: =A48 -> QUANT. TOTAL | PADRAO JANTAR | I48: =(B5*B48*'BASE PAX'!G23)+(B6*B48*'BASE PAX'!H23) -> 0
A49: SUBTOTAL FOOD | E49: =SUM(E31:E48) -> 0 | F49: =SUM(F31:F48) -> 0 | G49: =SUM(G31:G48) -> 0 | H49: SUBTOTAL | I49: =I31+I47+I48 -> 0 | J49: =I49+E49 -> 0 | K49: TOTAL FOOD
A51: 3. DRINKS (por cabin) | B51: QUANT. | C51: $ CUSTO | D51: $ VENDA | E51: SUBTOTAL | F51: SUBTOTAL $ CUSTO | G51: COMISSÕES
A52: ='BASE PAX'!A27 -> SUCOS | B52: ='BASE PAX'!B27 -> 0 | C52: ='BASE PAX'!C27 -> 0 | D52: =(C52*0.2)+C52 -> 0 | E52: =D52*B52 -> 0 | F52: =B52*C52 -> 0 | G52: =E52-F52 -> 0
A53: ='BASE PAX'!A28 -> SUCOS | B53: ='BASE PAX'!B28 -> 0 | C53: ='BASE PAX'!C28 -> 0 | D53: =(C53*0.2)+C53 -> 0 | E53: =D53*B53 -> 0 | F53: =B53*C53 -> 0 | G53: =E53-F53 -> 0
A54: ='BASE PAX'!A29 -> CERVEJAS | B54: ='BASE PAX'!B29 -> 0 | C54: ='BASE PAX'!C29 -> 2000 | D54: =(C54*0.2)+C54 -> 2400 | E54: =D54*B54 -> 0 | F54: =B54*C54 -> 0 | G54: =E54-F54 -> 0
A55: ='BASE PAX'!A30 -> VINHOS | B55: ='BASE PAX'!B30 -> 0 | C55: ='BASE PAX'!C30 -> 8000 | D55: =(C55*0.2)+C55 -> 9600 | E55: =D55*B55 -> 0 | F55: =B55*C55 -> 0 | G55: =E55-F55 -> 0
A56: ='BASE PAX'!A31 -> DRINKS | B56: ='BASE PAX'!B31 -> 0 | C56: ='BASE PAX'!C31 -> 15000 | D56: =(C56*0.2)+C56 -> 18000 | E56: =D56*B56 -> 0 | F56: =B56*C56 -> 0 | G56: =E56-F56 -> 0
A57: ='BASE PAX'!A32 -> COOLER | B57: ='BASE PAX'!B32 -> 0 | C57: ='BASE PAX'!C32 -> 5000 | D57: =(C57*0.2)+C57 -> 6000 | E57: =D57*B57 -> 0 | F57: =B57*C57 -> 0 | G57: =E57-F57 -> 0
A58: ='BASE PAX'!A33 -> 0 | B58: ='BASE PAX'!B33 -> 0 | C58: ='BASE PAX'!C33 -> 0 | D58: =(C58*0.2)+C58 -> 0 | E58: =D58*B58 -> 0 | F58: =B58*C58 -> 0 | G58: =E58-F58 -> 0
A59: SUBTOTAL DRINKS | E59: =SUM(E52:E58) -> 0 | F59: =SUM(F52:F58) -> 0 | G59: =E59-F59 -> 0
A61: 4. ACTIVITIES | B61: QUANT. | C61: $ CUSTO | D61: $ VENDA | E61: SUBTOTAL | F61: SUBTOTAL $ CUSTO | G61: COMISSÕES
A62: ='BASE PAX'!A37 -> HOTTUBE | B62: ='BASE PAX'!B37 -> 0 | C62: ='BASE PAX'!C37 -> 12000 | D62: =C62*0.2+C62 -> 14400 | E62: =D62*B62 -> 0 | F62: =B62*C62 -> 0 | G62: =E62-F62 -> 0
A63: ='BASE PAX'!A38 -> TREKKING 1/2 DAY | B63: ='BASE PAX'!B38 -> 0 | C63: ='BASE PAX'!C38 -> 60000 | D63: =C63*0.2+C63 -> 72000 | E63: =D63*B63 -> 0 | F63: =B63*C63 -> 0 | G63: =E63-F63 -> 0
A64: ='BASE PAX'!A39 -> TREKKING FUK DAY | B64: ='BASE PAX'!B39 -> 0 | C64: ='BASE PAX'!C39 -> 90000 | D64: =C64*0.2+C64 -> 108000 | E64: =D64*B64 -> 0 | F64: =B64*C64 -> 0 | G64: =E64-F64 -> 0
A65: ='BASE PAX'!A40 -> FLOTADA FAMILIAR | B65: ='BASE PAX'!B40 -> 0 | C65: ='BASE PAX'!C40 -> 60000 | D65: =C65*0.2+C65 -> 72000 | E65: =D65*B65 -> 0 | F65: =B65*C65 -> 0 | G65: =E65-F65 -> 0
A66: ='BASE PAX'!A41 -> RAFTING 1/2 DAY | B66: ='BASE PAX'!B41 -> 0 | C66: ='BASE PAX'!C41 -> 75000 | D66: =C66*0.2+C66 -> 90000 | E66: =D66*B66 -> 0 | F66: =B66*C66 -> 0 | G66: =E66-F66 -> 0
A67: ='BASE PAX'!A42 -> RAFTING FULL DAY | B67: ='BASE PAX'!B42 -> 0 | C67: ='BASE PAX'!C42 -> 110000 | D67: =C67*0.2+C67 -> 132000 | E67: =D67*B67 -> 0 | F67: =B67*C67 -> 0 | G67: =E67-F67 -> 0
A68: ='BASE PAX'!A43 -> CABALGADA 1/2 DAy | B68: ='BASE PAX'!B43 -> 0 | C68: ='BASE PAX'!C43 -> 90000 | D68: =C68*0.2+C68 -> 108000 | E68: =D68*B68 -> 0 | F68: =B68*C68 -> 0 | G68: =E68-F68 -> 0
A69: ='BASE PAX'!A44 -> CABALGADA FULL DAY | B69: ='BASE PAX'!B44 -> 0 | C69: ='BASE PAX'!C44 -> 140000 | D69: =C69*0.2+C69 -> 168000 | E69: =D69*B69 -> 0 | F69: =B69*C69 -> 0 | G69: =E69-F69 -> 0
A70: ='BASE PAX'!A45 -> LANCHA YELCHO | B70: ='BASE PAX'!B45 -> 0 | C70: ='BASE PAX'!C45 -> 120000 | D70: =C70*0.2+C70 -> 144000 | E70: =D70*B70 -> 0 | F70: =B70*C70 -> 0 | G70: =E70-F70 -> 0
A71: ='BASE PAX'!A46 -> RECREACAO INFANTIL 3HS | B71: ='BASE PAX'!B46 -> 0 | C71: ='BASE PAX'!C46 -> 30000 | D71: =C71*0.2+C71 -> 36000 | E71: =D71*B71 -> 0 | F71: =B71*C71 -> 0 | G71: =E71-F71 -> 0
A72: SUBTOTAL ACTIVITIES | E72: =SUM(E62:E71) -> 0 | F72: =B72*C72 -> 0 | G72: =E72-F72 -> 0
A74: 5. TRANSPORT | B74: QUANT. | C74: $ CUSTO | D74: $ VENDA | E74: SUBTOTAL | F74: SUBTOTAL CUSTO | G74: COMISSÕES
A75: ='BASE PAX'!A50 -> TRANSFER AEROPORTO CHEGADA | B75: ='BASE PAX'!B50 -> 0 | C75: 50000 | D75: =C75*0.2+C75 -> 60000 | E75: =D75*B75 -> 0 | F75: =B75*C75 -> 0 | G75: =E75-F75 -> 0
A76: ='BASE PAX'!A51 -> TRANSFER AEROPORTO PARTIDA | B76: ='BASE PAX'!B51 -> 0 | C76: ='BASE PAX'!C51 -> 80000 | D76: =C76*0.2+C76 -> 96000 | E76: =D76*B76 -> 0 | F76: =B76*C76 -> 0 | G76: =E76-F76 -> 0
A77: ='BASE PAX'!A52 -> TRANSFERS INTERNO | B77: ='BASE PAX'!B52 -> 0 | C77: ='BASE PAX'!C52 -> 18000 | D77: =C77*0.2+C77 -> 21600 | E77: =D77*B77 -> 0 | F77: =B77*C77 -> 0 | G77: =E77-F77 -> 0
A78: ='BASE PAX'!A53 -> EXTRAS 1 | B78: ='BASE PAX'!B53 -> 0 | C78: ='BASE PAX'!C53 -> 150000 | D78: =C78*0.2+C78 -> 180000 | E78: =D78*B78 -> 0 | F78: =B78*C78 -> 0 | G78: =E78-F78 -> 0
A79: ='BASE PAX'!A54 -> EXTRAS 2 | B79: ='BASE PAX'!B54 -> 0 | C79: ='BASE PAX'!C54 -> 0 | D79: =C79*0.2+C79 -> 0 | E79: =D79*B79 -> 0 | F79: =B79*C79 -> 0 | G79: =E79-F79 -> 0
A80: SUBTOTAL TRANSPORT | E80: =SUM(E75:E79) -> 0 | F80: =SUM(F75:F79) -> 0 | G80: =E80-F80 -> 0
A82: 6. EXPERIENCES | B82: QUANT. | C82: $ CUSTO | D82: $ VENDA | E82: SUBTOTAL | F82: SUBTOTAL CUSTO | G82: COMISSÕES
A83: ='BASE PAX'!A58 -> WS INSTRUCTOR | B83: ='BASE PAX'!B58 -> 0 | C83: ='BASE PAX'!C58 -> 3415000 | D83: =(C83*0.15)+C83 -> 3927250 | E83: =D83*B83 -> 0 | F83: =B83*C83 -> 0 | G83: =E83-F83 -> 0
A84: ='BASE PAX'!A59 -> PRODUCER FEE | B84: ='BASE PAX'!B59 -> 0 | C84: ='BASE PAX'!C59 -> 180000 | D84: =(C84*0.15)+C84 -> 207000 | E84: =D84*B84 -> 0 | F84: =B84*C84 -> 0 | G84: =E84-F84 -> 0
A85: ='BASE PAX'!A60 -> 0 | B85: ='BASE PAX'!B60 -> 0 | C85: ='BASE PAX'!C60 -> 20000 | D85: =(C85*0.15)+C85 -> 23000 | E85: =D85*B85 -> 0 | F85: =B85*C85 -> 0 | G85: =E85-F85 -> 0
A86: SUBTOTAL EXPERIENCES | E86: =SUM(E83:E85) -> 0 | F86: =SUM(F81:F85) -> 0 | G86: =E86-F86 -> 0
A88: 7. EXTRAS ( por cabin ) | B88: USOS | C88: $ CUSTO | D88: $ VENDA | E88: SUBTOTAL | G88: COMISSÕES
A89: ='BASE PAX'!A64 -> COORDENAÇÃO PRODUÇÃO | B89: ='BASE PAX'!B64 -> 0 | C89: ='BASE PAX'!C64 -> 50000 | D89: ='BASE PAX'!D64 -> 0 | E89: =D89*B89 -> 0 | G89: =E89*0.2 -> 0
A90: ='BASE PAX'!A65 -> EXTRA MÃO DE OBRA | B90: ='BASE PAX'!B65 -> 0 | C90: ='BASE PAX'!C65 -> 50000 | D90: ='BASE PAX'!D65 -> 0 | E90: =D90*B90 -> 0 | G90: =E90*0.2 -> 0
A91: ='BASE PAX'!A66 -> TAXA LIMPEZA CHECK IN / CHECKOUT | B91: ='BASE PAX'!B66 -> 0 | C91: ='BASE PAX'!C66 -> 40000 | D91: ='BASE PAX'!D66 -> 0 | E91: =D91*B91 -> 0 | G91: =E91*0.2 -> 0
A92: ='BASE PAX'!A67 -> TAXA LIMPEZA DIARIA | B92: ='BASE PAX'!B67 -> 0 | C92: ='BASE PAX'!C67 -> 30000 | D92: ='BASE PAX'!D67 -> 0 | E92: =D92*B92 -> 0 | G92: =E92*0.2 -> 0
A93: ='BASE PAX'!A68 -> SOUVENIR | B93: ='BASE PAX'!B68 -> 0 | C93: ='BASE PAX'!C68 -> 15000 | D93: ='BASE PAX'!D68 -> 0 | E93: =D93*B93 -> 0 | G93: =E93*0.2 -> 0
A94: ='BASE PAX'!A69 -> ASSISTENTE COORDENAÇÃO | B94: ='BASE PAX'!B69 -> 0 | C94: ='BASE PAX'!C69 -> 30000 | D94: ='BASE PAX'!D69 -> 0 | E94: =D94*B94 -> 0 | G94: =E94*0.2 -> 0
A95: SUBTOTAL EXTRAS | E95: =SUM(E89:E94) -> 0 | G95: =SUM(G89:G94) -> 0
A97: 8. QUINCHO (por cabin) | B97: USOS | C97: $ CUSTO | D97: $ VENDA | E97: SUBTOTAL
A98: ='BASE PAX'!A73 -> QUINCHO DAY USE / CABIN | B98: ='BASE PAX'!B73 -> 0 | C98: ='BASE PAX'!C73 -> 15000 | D98: =C98+(C98*0.2) -> 18000 | E98: =D98*B98 -> 0
A99: SUBTOTAL QUINCHO | E99: =E98 -> 0

Sheet BUDGET NIRE 2+1
C3: COIGUE
A5: TOTAL PAX ADULT | B5: 2 | E5: NIRE
A6: TOTAL PAX INFANT | B6: 1 | D6: BUDGET TOTAL | F6: =D21 -> 0
A7: CHECK IN. | B7: =CALENDAR!C2 -> 0 | D7: SUBTOTAL PAGO | F7: =SUM(F12:F20) -> 0
A8: CHECK OUT. | B8: =CALENDAR!C3 -> 0 | D8: SUBTOTAL A RECEBER | F8: =F6-F7 -> 0
A9: TOTAL NIGHTS. | B9: =CALENDAR!J2 -> 0 | D9: TIP |
A11: RESUMO. | B11: PREÇO CLIENTE CASH CLP $ | C11: TAXA CC | D11: PREÇO CLIENTE PAGTO CC $ | F11: =E5 -> NIRE | I11: CONTROLE PAGAMENTOS
C12: 0.05 | I12: DATA | J12: VALOR PAGO CLP $ | K12: FORMA PAGTO
A13: 1.LODGING | B13: =G28 -> 0 | C13: =B13*$C$12 -> 0 | D13: =B13+(B13*$C$12) -> 0
A14: 2.FOOD | B14: =J49 -> 0 | C14: =B14*$C$12 -> 0 | D14: =B14+(B14*$C$12) -> 0 | F14: =A14 -> 2.FOOD | G14: =G49 -> 0
A15: 3.DRINKS | B15: =E59 -> 0 | C15: =B15*$C$12 -> 0 | D15: =B15+(B15*$C$12) -> 0 | F15: =A15 -> 3.DRINKS | G15: =G59 -> 0
A16: 4. ACTIVITIES | B16: =$E$72 -> 0 | C16: =B16*$C$12 -> 0 | D16: =B16+(B16*$C$12) -> 0 | F16: =A16 -> 4. ACTIVITIES | G16: =G72 -> 0
A17: 5.TRANSPORT | B17: =$E$80 -> 0 | C17: =B17*$C$12 -> 0 | D17: =B17+(B17*$C$12) -> 0 | F17: =A17 -> 5.TRANSPORT | G17: =G80 -> 0
A18: 6.EXPERIENCES | B18: =$E$86 -> 0 | C18: =B18*$C$12 -> 0 | D18: =B18+(B18*$C$12) -> 0 | F18: =A18 -> 6.EXPERIENCES | G18: =G86 -> 0
A19: 7.EXTRAS | B19: =$E$95 -> 0 | C19: =B19*$C$12 -> 0 | D19: =B19+(B19*$C$12) -> 0 | F19: =A19 -> 7.EXTRAS | G19: =G95 -> 0
A20: 8. QUINCHO | B20: =$E$99 -> 0 | C20: =B20*$C$12 -> 0 | D20: =B20+(B20*$C$12) -> 0 | F20: SUBTOTAL COMISSÕES | G20: =G14+G15+G16+G17+G18+G19 -> 0
A21: SUBTOTAL 1 | B21: =SUM(B13:B20) -> 0 | D21: =SUM(D13:D20) -> 0
A23: 1. LODGING | B23: QUANT. | C23: $ CABIN / DIA | D23: $ ADICIONAL / DIA | E23: BASE CÁLCULO | F23: DESCONTOS | G23: $ SUBTOTAL
A24: NIRE (até 2 pax) - até 06 noites | B24: 0 | C24: =249200 -> 249200 | E24: =(C24+D24)*$B$9*B24 -> 0 | F24: 0 | G24: =E24-(E24*F24) -> 0
A25: NIRE ( 2 + baby) - até 06 noites | B25: 1 | C25: =249200 -> 249200 | D25: 50000 | E25: =(C25+D25)*$B$9*B25 -> 0 | F25: 0 | G25: =E25-(E25*F25) -> 0
A26: NIRE (até 2 pax) - 7 noites ou + | B26: 0 | C26: =224280 -> 224280 | E26: =(C26+D26)*$B$9*B26 -> 0 | F26: 0 | G26: =E26-(E26*F26) -> 0
A27: NIRE ( 2 + baby) - 7 noites ou + | B27: 0 | C27: =224280 -> 224280 | D27: 50000 | E27: =(C27+D27)*$B$9*B27 -> 0 | F27: 0 | G27: =E27-(E27*F27) -> 0
A28: SUBTOTAL LODGING | G28: =SUM(G24:G27) -> 0
A30: 2. FOOD | B30: QUANT. | C30: $ CUSTO | D30: $ VENDA | E30: SUBTOTAL $ VENDA | F30: SUBTOTAL $ CUSTO | G30: COMISSÕES
A31: ='BASE PAX'!A6 -> BREAKFAST | B31: =(B5*B9*'BASE PAX'!G6)+('BASE PAX'!H6*B6*B9) -> 0 | E31: 0 | F31: =B31*C31 -> 0 | G31: =0.2*B31 -> 0 | H31: =A31 -> BREAKFAST | I31: =B31 -> 0
A32: ='BASE PAX'!A7 -> LUNCH 1 | B32: =($B$5+$B$6)*'BASE PAX'!B7 -> 0 | C32: ='BASE PAX'!C7 -> 40000 | D32: ='BASE PAX'!D7 -> 48000 | E32: =D32*B32 -> 0 | F32: =B32*C32 -> 0 | G32: =E32-F32 -> 0
A33: ='BASE PAX'!A8 -> LUNCH 2 | B33: =($B$5+$B$6)*'BASE PAX'!B8 -> 0 | C33: ='BASE PAX'!C8 -> 40000 | D33: ='BASE PAX'!D8 -> 48000 | E33: =D33*B33 -> 0 | F33: =B33*C33 -> 0 | G33: =E33-F33 -> 0
A34: ='BASE PAX'!A9 -> LUNCH 3 | B34: =($B$5+$B$6)*'BASE PAX'!B9 -> 0 | C34: ='BASE PAX'!C9 -> 40000 | D34: ='BASE PAX'!D9 -> 48000 | E34: =D34*B34 -> 0 | F34: =B34*C34 -> 0 | G34: =E34-F34 -> 0
A35: ='BASE PAX'!A10 -> LUNCH 4 | B35: =($B$5+$B$6)*'BASE PAX'!B10 -> 0 | C35: ='BASE PAX'!C10 -> 45000 | D35: ='BASE PAX'!D10 -> 54000 | E35: =D35*B35 -> 0 | F35: =B35*C35 -> 0 | G35: =E35-F35 -> 0
A36: ='BASE PAX'!A11 -> LUNCH 5 | B36: =($B$5+($B$6*0.6))*'BASE PAX'!B11 -> 0 | C36: ='BASE PAX'!C11 -> 50000 | D36: ='BASE PAX'!D11 -> 60000 | E36: =D36*B36 -> 0 | F36: =B36*C36 -> 0 | G36: =E36-F36 -> 0
A37: ='BASE PAX'!A12 -> LUNCH 6 | B37: =($B$5+$B$6)*'BASE PAX'!B12 -> 0 | C37: ='BASE PAX'!C12 -> 0 | D37: ='BASE PAX'!D12 -> 0 | E37: =D37*B37 -> 0 | F37: =B37*C37 -> 0 | G37: =E37-F37 -> 0
A38: ='BASE PAX'!A13 -> LUNCH 7 | B38: =($B$5+$B$6)*'BASE PAX'!B13 -> 0 | C38: ='BASE PAX'!C13 -> 5000 | D38: ='BASE PAX'!D13 -> 6000 | E38: =D38*B38 -> 0 | F38: =B38*C38 -> 0 | G38: =E38-F38 -> 0
A39: ='BASE PAX'!A14 -> SNACKS | B39: =($B$5+$B$6)*'BASE PAX'!B14 -> 0 | C39: ='BASE PAX'!C14 -> 8000 | D39: ='BASE PAX'!D14 -> 9600 | E39: =D39*B39 -> 0 | F39: =B39*C39 -> 0 | G39: =E39-F39 -> 0
A40: ='BASE PAX'!A15 -> DINNER 1 | B40: =($B$5+($B$6*0.6))*'BASE PAX'!B15 -> 0 | C40: ='BASE PAX'!C15 -> 70000 | D40: ='BASE PAX'!D15 -> 84000 | E40: =D40*B40 -> 0 | F40: =B40*C40 -> 0 | G40: =E40-F40 -> 0
A41: ='BASE PAX'!A16 -> DINNER 2 | B41: =($B$5+($B$6*0.6))*'BASE PAX'!B16 -> 0 | C41: ='BASE PAX'!C16 -> 25000 | D41: ='BASE PAX'!D16 -> 30000 | E41: =D41*B41 -> 0 | F41: =B41*C41 -> 0 | G41: =E41-F41 -> 0
A42: ='BASE PAX'!A17 -> DINNER 3 | B42: =($B$5+($B$6*0.6))*'BASE PAX'!B17 -> 0 | C42: ='BASE PAX'!C17 -> 50000 | D42: ='BASE PAX'!D17 -> 60000 | E42: =D42*B42 -> 0 | F42: =B42*C42 -> 0 | G42: =E42-F42 -> 0
A43: ='BASE PAX'!A18 -> DINNER 4 | B43: =($B$5+$B$6)*'BASE PAX'!B18 -> 0 | C43: ='BASE PAX'!C18 -> 65000 | D43: ='BASE PAX'!D18 -> 78000 | E43: =D43*B43 -> 0 | F43: =B43*C43 -> 0 | G43: =E43-F43 -> 0
A44: ='BASE PAX'!A19 -> DINNER 5 | B44: =($B$5+($B$6*0.6))*'BASE PAX'!B19 -> 0 | C44: ='BASE PAX'!C19 -> 75000 | D44: ='BASE PAX'!D19 -> 90000 | E44: =D44*B44 -> 0 | F44: =B44*C44 -> 0 | G44: =E44-F44 -> 0
A45: ='BASE PAX'!A20 -> DINNER 6 | B45: =($B$5+$B$6)*'BASE PAX'!B20 -> 0 | C45: ='BASE PAX'!C20 -> 0 | D45: ='BASE PAX'!D20 -> 0 | E45: =D45*B45 -> 0 | F45: =B45*C45 -> 0 | G45: =E45-F45 -> 0
A46: ='BASE PAX'!A21 -> DINNER 7 | B46: =($B$5+($B$6*0.6))*'BASE PAX'!B21 -> 0 | C46: ='BASE PAX'!C21 -> 75000 | D46: ='BASE PAX'!D21 -> 90000 | E46: =D46*B46 -> 0 | F46: =B46*C46 -> 0 | G46: =E46-F46 -> 0
A47: ='BASE PAX'!A22 -> QUANT. TOTAL | PADRAO ALMOÇO | B47: ='BASE PAX'!B22 -> 0 | G47: =0.2*I47 -> 0 | H47: =A47 -> QUANT. TOTAL | PADRAO ALMOÇO | I47: =(B5*B47*'BASE PAX'!G22)+(B6*B47*'BASE PAX'!H22) -> 0
A48: ='BASE PAX'!A23 -> QUANT. TOTAL | PADRAO JANTAR | B48: ='BASE PAX'!B23 -> 0 | G48: =0.2*I48 -> 0 | H48: =A48 -> QUANT. TOTAL | PADRAO JANTAR | I48: =(B5*B48*'BASE PAX'!G23)+(B6*B48*'BASE PAX'!H23) -> 0
A49: SUBTOTAL FOOD | E49: =SUM(E31:E48) -> 0 | F49: =SUM(F31:F48) -> 0 | G49: =SUM(G31:G48) -> 0 | H49: SUBTOTAL | I49: =I31+I47+I48 -> 0 | J49: =I49+E49 -> 0 | K49: TOTAL FOOD
A51: 3. DRINKS (por cabin) | B51: QUANT. | C51: $ CUSTO | D51: $ VENDA | E51: SUBTOTAL | F51: SUBTOTAL $ CUSTO | G51: COMISSÕES
A52: ='BASE PAX'!A27 -> SUCOS | B52: ='BASE PAX'!B27 -> 0 | C52: ='BASE PAX'!C27 -> 0 | D52: =(C52*0.2)+C52 -> 0 | E52: =D52*B52 -> 0 | F52: =B52*C52 -> 0 | G52: =E52-F52 -> 0
A53: ='BASE PAX'!A28 -> SUCOS | B53: ='BASE PAX'!B28 -> 0 | C53: ='BASE PAX'!C28 -> 0 | D53: =(C53*0.2)+C53 -> 0 | E53: =D53*B53 -> 0 | F53: =B53*C53 -> 0 | G53: =E53-F53 -> 0
A54: ='BASE PAX'!A29 -> CERVEJAS | B54: ='BASE PAX'!B29 -> 0 | C54: ='BASE PAX'!C29 -> 2000 | D54: =(C54*0.2)+C54 -> 2400 | E54: =D54*B54 -> 0 | F54: =B54*C54 -> 0 | G54: =E54-F54 -> 0
A55: ='BASE PAX'!A30 -> VINHOS | B55: ='BASE PAX'!B30 -> 0 | C55: ='BASE PAX'!C30 -> 8000 | D55: =(C55*0.2)+C55 -> 9600 | E55: =D55*B55 -> 0 | F55: =B55*C55 -> 0 | G55: =E55-F55 -> 0
A56: ='BASE PAX'!A31 -> DRINKS | B56: ='BASE PAX'!B31 -> 0 | C56: ='BASE PAX'!C31 -> 15000 | D56: =(C56*0.2)+C56 -> 18000 | E56: =D56*B56 -> 0 | F56: =B56*C56 -> 0 | G56: =E56-F56 -> 0
A57: ='BASE PAX'!A32 -> COOLER | B57: ='BASE PAX'!B32 -> 0 | C57: ='BASE PAX'!C32 -> 5000 | D57: =(C57*0.2)+C57 -> 6000 | E57: =D57*B57 -> 0 | F57: =B57*C57 -> 0 | G57: =E57-F57 -> 0
A58: ='BASE PAX'!A33 -> 0 | B58: ='BASE PAX'!B33 -> 0 | C58: ='BASE PAX'!C33 -> 0 | D58: =(C58*0.2)+C58 -> 0 | E58: =D58*B58 -> 0 | F58: =B58*C58 -> 0 | G58: =E58-F58 -> 0
A59: SUBTOTAL DRINKS | E59: =SUM(E52:E58) -> 0 | F59: =SUM(F52:F58) -> 0 | G59: =E59-F59 -> 0
A61: 4. ACTIVITIES | B61: QUANT. | C61: $ CUSTO | D61: $ VENDA | E61: SUBTOTAL | F61: SUBTOTAL $ CUSTO | G61: COMISSÕES
A62: ='BASE PAX'!A37 -> HOTTUBE | B62: ='BASE PAX'!B37 -> 0 | C62: ='BASE PAX'!C37 -> 12000 | D62: =C62*0.2+C62 -> 14400 | E62: =D62*B62 -> 0 | F62: =B62*C62 -> 0 | G62: =E62-F62 -> 0
A63: ='BASE PAX'!A38 -> TREKKING 1/2 DAY | B63: ='BASE PAX'!B38 -> 0 | C63: ='BASE PAX'!C38 -> 60000 | D63: =C63*0.2+C63 -> 72000 | E63: =D63*B63 -> 0 | F63: =B63*C63 -> 0 | G63: =E63-F63 -> 0
A64: ='BASE PAX'!A39 -> TREKKING FUK DAY | B64: ='BASE PAX'!B39 -> 0 | C64: ='BASE PAX'!C39 -> 90000 | D64: =C64*0.2+C64 -> 108000 | E64: =D64*B64 -> 0 | F64: =B64*C64 -> 0 | G64: =E64-F64 -> 0
A65: ='BASE PAX'!A40 -> FLOTADA FAMILIAR | B65: ='BASE PAX'!B40 -> 0 | C65: ='BASE PAX'!C40 -> 60000 | D65: =C65*0.2+C65 -> 72000 | E65: =D65*B65 -> 0 | F65: =B65*C65 -> 0 | G65: =E65-F65 -> 0
A66: ='BASE PAX'!A41 -> RAFTING 1/2 DAY | B66: ='BASE PAX'!B41 -> 0 | C66: ='BASE PAX'!C41 -> 75000 | D66: =C66*0.2+C66 -> 90000 | E66: =D66*B66 -> 0 | F66: =B66*C66 -> 0 | G66: =E66-F66 -> 0
A67: ='BASE PAX'!A42 -> RAFTING FULL DAY | B67: ='BASE PAX'!B42 -> 0 | C67: ='BASE PAX'!C42 -> 110000 | D67: =C67*0.2+C67 -> 132000 | E67: =D67*B67 -> 0 | F67: =B67*C67 -> 0 | G67: =E67-F67 -> 0
A68: ='BASE PAX'!A43 -> CABALGADA 1/2 DAy | B68: ='BASE PAX'!B43 -> 0 | C68: ='BASE PAX'!C43 -> 90000 | D68: =C68*0.2+C68 -> 108000 | E68: =D68*B68 -> 0 | F68: =B68*C68 -> 0 | G68: =E68-F68 -> 0
A69: ='BASE PAX'!A44 -> CABALGADA FULL DAY | B69: ='BASE PAX'!B44 -> 0 | C69: ='BASE PAX'!C44 -> 140000 | D69: =C69*0.2+C69 -> 168000 | E69: =D69*B69 -> 0 | F69: =B69*C69 -> 0 | G69: =E69-F69 -> 0
A70: ='BASE PAX'!A45 -> LANCHA YELCHO | B70: ='BASE PAX'!B45 -> 0 | C70: ='BASE PAX'!C45 -> 120000 | D70: =C70*0.2+C70 -> 144000 | E70: =D70*B70 -> 0 | F70: =B70*C70 -> 0 | G70: =E70-F70 -> 0
A71: ='BASE PAX'!A46 -> RECREACAO INFANTIL 3HS | B71: ='BASE PAX'!B46 -> 0 | C71: ='BASE PAX'!C46 -> 30000 | D71: =C71*0.2+C71 -> 36000 | E71: =D71*B71 -> 0 | F71: =B71*C71 -> 0 | G71: =E71-F71 -> 0
A72: SUBTOTAL ACTIVITIES | E72: =SUM(E62:E71) -> 0 | F72: =B72*C72 -> 0 | G72: =E72-F72 -> 0
A74: 5. TRANSPORT | B74: QUANT. | C74: $ CUSTO | D74: $ VENDA | E74: SUBTOTAL | F74: SUBTOTAL CUSTO | G74: COMISSÕES
A75: ='BASE PAX'!A50 -> TRANSFER AEROPORTO CHEGADA | B75: ='BASE PAX'!B50 -> 0 | C75: 50000 | D75: =C75*0.2+C75 -> 60000 | E75: =D75*B75 -> 0 | F75: =B75*C75 -> 0 | G75: =E75-F75 -> 0
A76: ='BASE PAX'!A51 -> TRANSFER AEROPORTO PARTIDA | B76: ='BASE PAX'!B51 -> 0 | C76: ='BASE PAX'!C51 -> 80000 | D76: =C76*0.2+C76 -> 96000 | E76: =D76*B76 -> 0 | F76: =B76*C76 -> 0 | G76: =E76-F76 -> 0
A77: ='BASE PAX'!A52 -> TRANSFERS INTERNO | B77: ='BASE PAX'!B52 -> 0 | C77: ='BASE PAX'!C52 -> 18000 | D77: =C77*0.2+C77 -> 21600 | E77: =D77*B77 -> 0 | F77: =B77*C77 -> 0 | G77: =E77-F77 -> 0
A78: ='BASE PAX'!A53 -> EXTRAS 1 | B78: ='BASE PAX'!B53 -> 0 | C78: ='BASE PAX'!C53 -> 150000 | D78: =C78*0.2+C78 -> 180000 | E78: =D78*B78 -> 0 | F78: =B78*C78 -> 0 | G78: =E78-F78 -> 0
A79: ='BASE PAX'!A54 -> EXTRAS 2 | B79: ='BASE PAX'!B54 -> 0 | C79: ='BASE PAX'!C54 -> 0 | D79: =C79*0.2+C79 -> 0 | E79: =D79*B79 -> 0 | F79: =B79*C79 -> 0 | G79: =E79-F79 -> 0
A80: SUBTOTAL TRANSPORT | E80: =SUM(E75:E79) -> 0 | F80: =SUM(F75:F79) -> 0 | G80: =E80-F80 -> 0
A82: 6. EXPERIENCES | B82: QUANT. | C82: $ CUSTO | D82: $ VENDA | E82: SUBTOTAL | F82: SUBTOTAL CUSTO | G82: COMISSÕES
A83: ='BASE PAX'!A58 -> WS INSTRUCTOR | B83: ='BASE PAX'!B58 -> 0 | C83: ='BASE PAX'!C58 -> 3415000 | D83: =(C83*0.15)+C83 -> 3927250 | E83: =D83*B83 -> 0 | F83: =B83*C83 -> 0 | G83: =E83-F83 -> 0
A84: ='BASE PAX'!A59 -> PRODUCER FEE | B84: ='BASE PAX'!B59 -> 0 | C84: ='BASE PAX'!C59 -> 180000 | D84: =(C84*0.15)+C84 -> 207000 | E84: =D84*B84 -> 0 | F84: =B84*C84 -> 0 | G84: =E84-F84 -> 0
A85: ='BASE PAX'!A60 -> 0 | B85: ='BASE PAX'!B60 -> 0 | C85: ='BASE PAX'!C60 -> 20000 | D85: =(C85*0.15)+C85 -> 23000 | E85: =D85*B85 -> 0 | F85: =B85*C85 -> 0 | G85: =E85-F85 -> 0
A86: SUBTOTAL EXPERIENCES | E86: =SUM(E83:E85) -> 0 | F86: =SUM(F81:F85) -> 0 | G86: =E86-F86 -> 0
A88: 7. EXTRAS ( por cabin ) | B88: USOS | C88: $ CUSTO | D88: $ VENDA | E88: SUBTOTAL | G88: COMISSÕES
A89: ='BASE PAX'!A64 -> COORDENAÇÃO PRODUÇÃO | B89: ='BASE PAX'!B64 -> 0 | C89: ='BASE PAX'!C64 -> 50000 | D89: ='BASE PAX'!D64 -> 0 | E89: =D89*B89 -> 0 | G89: =E89*0.2 -> 0
A90: ='BASE PAX'!A65 -> EXTRA MÃO DE OBRA | B90: ='BASE PAX'!B65 -> 0 | C90: ='BASE PAX'!C65 -> 50000 | D90: ='BASE PAX'!D65 -> 0 | E90: =D90*B90 -> 0 | G90: =E90*0.2 -> 0
A91: ='BASE PAX'!A66 -> TAXA LIMPEZA CHECK IN / CHECKOUT | B91: ='BASE PAX'!B66 -> 0 | C91: ='BASE PAX'!C66 -> 40000 | D91: ='BASE PAX'!D66 -> 0 | E91: =D91*B91 -> 0 | G91: =E91*0.2 -> 0
A92: ='BASE PAX'!A67 -> TAXA LIMPEZA DIARIA | B92: ='BASE PAX'!B67 -> 0 | C92: ='BASE PAX'!C67 -> 30000 | D92: ='BASE PAX'!D67 -> 0 | E92: =D92*B92 -> 0 | G92: =E92*0.2 -> 0
A93: ='BASE PAX'!A68 -> SOUVENIR | B93: ='BASE PAX'!B68 -> 0 | C93: ='BASE PAX'!C68 -> 15000 | D93: ='BASE PAX'!D68 -> 0 | E93: =D93*B93 -> 0 | G93: =E93*0.2 -> 0
A94: ='BASE PAX'!A69 -> ASSISTENTE COORDENAÇÃO | B94: ='BASE PAX'!B69 -> 0 | C94: ='BASE PAX'!C69 -> 30000 | D94: ='BASE PAX'!D69 -> 0 | E94: =D94*B94 -> 0 | G94: =E94*0.2 -> 0
A95: SUBTOTAL EXTRAS | E95: =SUM(E89:E94) -> 0 | G95: =SUM(G89:G94) -> 0
A97: 8. QUINCHO (por cabin) | B97: USOS | C97: $ CUSTO | D97: $ VENDA | E97: SUBTOTAL
A98: ='BASE PAX'!A73 -> QUINCHO DAY USE / CABIN | B98: ='BASE PAX'!B73 -> 0 | C98: ='BASE PAX'!C73 -> 15000 | D98: =C98+(C98*0.2) -> 18000 | E98: =D98*B98 -> 0
A99: SUBTOTAL QUINCHO | E99: =E98 -> 0

Sheet BUDGET NIRE 2+2
C3: COIGUE
A5: TOTAL PAX ADULT | B5: 2 | E5: NIRE
A6: TOTAL PAX INFANT | B6: 2 | D6: BUDGET TOTAL | F6: =D21 -> 0
A7: CHECK IN. | B7: =CALENDAR!C2 -> 0 | D7: SUBTOTAL PAGO | F7: =SUM(F12:F20) -> 0
A8: CHECK OUT. | B8: =CALENDAR!C3 -> 0 | D8: SUBTOTAL A RECEBER | F8: =F6-F7 -> 0
A9: TOTAL NIGHTS. | B9: =CALENDAR!J2 -> 0 | D9: TIP |
A11: RESUMO. | B11: PREÇO CLIENTE CASH CLP $ | C11: TAXA CC | D11: PREÇO CLIENTE PAGTO CC $ | F11: =E5 -> CHAITEN | I11: CONTROLE PAGAMENTOS
C12: 0.05 | I12: DATA | J12: VALOR PAGO CLP $ | K12: FORMA PAGTO
A13: 1.LODGING | B13: =G28 -> 0 | C13: =B13*$C$12 -> 0 | D13: =B13+(B13*$C$12) -> 0
A14: 2.FOOD | B14: =J49 -> 0 | C14: =B14*$C$12 -> 0 | D14: =B14+(B14*$C$12) -> 0 | F14: =A14 -> 2.FOOD | G14: =G49 -> 0
A15: 3.DRINKS | B15: =E59 -> 0 | C15: =B15*$C$12 -> 0 | D15: =B15+(B15*$C$12) -> 0 | F15: =A15 -> 3.DRINKS | G15: =G59 -> 0
A16: 4. ACTIVITIES | B16: =$E$72 -> 0 | C16: =B16*$C$12 -> 0 | D16: =B16+(B16*$C$12) -> 0 | F16: =A16 -> 4. ACTIVITIES | G16: =G72 -> 0
A17: 5.TRANSPORT | B17: =$E$80 -> 0 | C17: =B17*$C$12 -> 0 | D17: =B17+(B17*$C$12) -> 0 | F17: =A17 -> 5.TRANSPORT | G17: =G80 -> 0
A18: 6.EXPERIENCES | B18: =$E$86 -> 0 | C18: =B18*$C$12 -> 0 | D18: =B18+(B18*$C$12) -> 0 | F18: =A18 -> 6.EXPERIENCES | G18: =G86 -> 0
A19: 7.EXTRAS | B19: =$E$95 -> 0 | C19: =B19*$C$12 -> 0 | D19: =B19+(B19*$C$12) -> 0 | F19: =A19 -> 7.EXTRAS | G19: =G95 -> 0
A20: 8. QUINCHO | B20: =$E$99 -> 0 | C20: =B20*$C$12 -> 0 | D20: =B20+(B20*$C$12) -> 0 | F20: SUBTOTAL COMISSÕES | G20: =G14+G15+G16+G17+G18+G19 -> 0
A21: SUBTOTAL 1 | B21: =SUM(B13:B20) -> 0 | D21: =SUM(D13:D20) -> 0
A23: 1. LODGING | B23: QUANT. | C23: $ CABIN / DIA | D23: $ ADICIONAL / DIA | E23: BASE CÁLCULO | F23: DESCONTOS | G23: $ SUBTOTAL
A24: NIRE (até 2 pax) - até 06 noites | B24: 0 | C24: =288190.9 -> 288190.9 | E24: =(C24+D24)*$B$9*B24 -> 0 | F24: 0 | G24: =E24-(E24*F24) -> 0
A25: NIRE ( 2 + baby) - até 06 noites | B25: 1 | C25: =288190.9 -> 288190.9 | D25: =$B$6*50000 -> 100000 | E25: =(C25+D25)*$B$9*B25 -> 0 | F25: 0 | G25: =E25-(E25*F25) -> 0
A26: NIRE (até 2 pax) - 7 noites ou + | B26: 0 | C26: =259371.81 -> 259371.81 | E26: =(C26+D26)*$B$9*B26 -> 0 | F26: 0 | G26: =E26-(E26*F26) -> 0
A27: NIRE ( 2 + baby) - 7 noites ou + | B27: 0 | C27: =259371.81 -> 259371.81 | D27: 50000 | E27: =(C27+D27)*$B$9*B27 -> 0 | F27: 0 | G27: =E27-(E27*F27) -> 0
A28: SUBTOTAL LODGING | G28: =SUM(G24:G27) -> 0
A30: 2. FOOD | B30: QUANT. | C30: $ CUSTO | D30: $ VENDA | E30: SUBTOTAL $ VENDA | F30: SUBTOTAL $ CUSTO | G30: COMISSÕES
A31: ='BASE PAX'!A6 -> BREAKFAST | B31: =(B5*B9*'BASE PAX'!G6)+('BASE PAX'!H6*B6*B9) -> 0 | F31: =B31*C31 -> 0 | G31: =0.2*B31 -> 0 | H31: ='BASE PAX'!A6 -> BREAKFAST | I31: =B31 -> 0
A32: ='BASE PAX'!A7 -> LUNCH 1 | B32: =($B$5+($B$6*0.5))*'BASE PAX'!B7 -> 0 | C32: ='BASE PAX'!C7 -> 40000 | D32: ='BASE PAX'!D7 -> 48000 | E32: =D32*B32 -> 0 | F32: =B32*C32 -> 0 | G32: =E32-F32 -> 0
A33: ='BASE PAX'!A8 -> LUNCH 2 | B33: =($B$5+($B$6*0.5))*'BASE PAX'!B8 -> 0 | C33: ='BASE PAX'!C8 -> 40000 | D33: ='BASE PAX'!D8 -> 48000 | E33: =D33*B33 -> 0 | F33: =B33*C33 -> 0 | G33: =E33-F33 -> 0
A34: ='BASE PAX'!A9 -> LUNCH 3 | B34: =($B$5+($B$6*0.5))*'BASE PAX'!B9 -> 0 | C34: ='BASE PAX'!C9 -> 40000 | D34: ='BASE PAX'!D9 -> 48000 | E34: =D34*B34 -> 0 | F34: =B34*C34 -> 0 | G34: =E34-F34 -> 0
A35: ='BASE PAX'!A10 -> LUNCH 4 | B35: =($B$5+($B$6*0.5))*'BASE PAX'!B10 -> 0 | C35: ='BASE PAX'!C10 -> 45000 | D35: ='BASE PAX'!D10 -> 54000 | E35: =D35*B35 -> 0 | F35: =B35*C35 -> 0 | G35: =E35-F35 -> 0
A36: ='BASE PAX'!A11 -> LUNCH 5 | B36: =($B$5+($B$6*0.6))*'BASE PAX'!B11 -> 0 | C36: ='BASE PAX'!C11 -> 50000 | D36: ='BASE PAX'!D11 -> 60000 | E36: =D36*B36 -> 0 | F36: =B36*C36 -> 0 | G36: =E36-F36 -> 0
A37: ='BASE PAX'!A12 -> LUNCH 6 | B37: =($B$5+($B$6*0.5))*'BASE PAX'!B12 -> 0 | C37: ='BASE PAX'!C12 -> 0 | D37: ='BASE PAX'!D12 -> 0 | E37: =D37*B37 -> 0 | F37: =B37*C37 -> 0 | G37: =E37-F37 -> 0
A38: ='BASE PAX'!A13 -> LUNCH 7 | B38: =($B$5+($B$6*0.5))*'BASE PAX'!B13 -> 0 | C38: ='BASE PAX'!C13 -> 5000 | D38: ='BASE PAX'!D13 -> 6000 | E38: =D38*B38 -> 0 | F38: =B38*C38 -> 0 | G38: =E38-F38 -> 0
A39: ='BASE PAX'!A14 -> SNACKS | B39: =($B$5+$B$6)*'BASE PAX'!B14 -> 0 | C39: ='BASE PAX'!C14 -> 8000 | D39: ='BASE PAX'!D14 -> 9600 | E39: =D39*B39 -> 0 | F39: =B39*C39 -> 0 | G39: =E39-F39 -> 0
A40: ='BASE PAX'!A15 -> DINNER 1 | B40: =($B$5+($B$6*0.6))*'BASE PAX'!B15 -> 0 | C40: ='BASE PAX'!C15 -> 70000 | D40: ='BASE PAX'!D15 -> 84000 | E40: =D40*B40 -> 0 | F40: =B40*C40 -> 0 | G40: =E40-F40 -> 0
A41: ='BASE PAX'!A16 -> DINNER 2 | B41: =($B$5+($B$6*0.6))*'BASE PAX'!B16 -> 0 | C41: ='BASE PAX'!C16 -> 25000 | D41: ='BASE PAX'!D16 -> 30000 | E41: =D41*B41 -> 0 | F41: =B41*C41 -> 0 | G41: =E41-F41 -> 0
A42: ='BASE PAX'!A17 -> DINNER 3 | B42: =($B$5+($B$6*0.6))*'BASE PAX'!B17 -> 0 | C42: ='BASE PAX'!C17 -> 50000 | D42: ='BASE PAX'!D17 -> 60000 | E42: =D42*B42 -> 0 | F42: =B42*C42 -> 0 | G42: =E42-F42 -> 0
A43: ='BASE PAX'!A18 -> DINNER 4 | B43: =($B$5+($B$6*0.5))*'BASE PAX'!B18 -> 0 | C43: ='BASE PAX'!C18 -> 65000 | D43: ='BASE PAX'!D18 -> 78000 | E43: =D43*B43 -> 0 | F43: =B43*C43 -> 0 | G43: =E43-F43 -> 0
A44: ='BASE PAX'!A19 -> DINNER 5 | B44: =($B$5+($B$6*0.6))*'BASE PAX'!B19 -> 0 | C44: ='BASE PAX'!C19 -> 75000 | D44: ='BASE PAX'!D19 -> 90000 | E44: =D44*B44 -> 0 | F44: =B44*C44 -> 0 | G44: =E44-F44 -> 0
A45: ='BASE PAX'!A20 -> DINNER 6 | B45: =($B$5+($B$6*0.5))*'BASE PAX'!B20 -> 0 | C45: ='BASE PAX'!C20 -> 0 | D45: ='BASE PAX'!D20 -> 0 | E45: =D45*B45 -> 0 | F45: =B45*C45 -> 0 | G45: =E45-F45 -> 0
A46: ='BASE PAX'!A21 -> DINNER 7 | B46: =($B$5+($B$6*0.6))*'BASE PAX'!B21 -> 0 | C46: ='BASE PAX'!C21 -> 75000 | D46: ='BASE PAX'!D21 -> 90000 | E46: =D46*B46 -> 0 | F46: =B46*C46 -> 0 | G46: =E46-F46 -> 0
A47: ='BASE PAX'!A22 -> QUANT. TOTAL | PADRAO ALMOÇO | B47: ='BASE PAX'!B22 -> 0 | G47: =0.2*I47 -> 0 | H47: ='BASE PAX'!A22 -> QUANT. TOTAL | PADRAO ALMOÇO | I47: =(B5*B47*'BASE PAX'!G22)+(B6*B47*'BASE PAX'!H22) -> 0
A48: ='BASE PAX'!A23 -> QUANT. TOTAL | PADRAO JANTAR | B48: ='BASE PAX'!B23 -> 0 | G48: =0.2*I48 -> 0 | H48: ='BASE PAX'!A23 -> QUANT. TOTAL | PADRAO JANTAR | I48: =(B5*B48*'BASE PAX'!G23)+(B6*B48*'BASE PAX'!H23) -> 0
A49: SUBTOTAL FOOD | E49: =SUM(E31:E48) -> 0 | F49: =SUM(F31:F48) -> 0 | G49: =SUM(G31:G48) -> 0 | H49: SUBTOTAL | I49: =I31+I47+I48 -> 0 | J49: =I49+E49 -> 0 | K49: TOTAL FOOD
A51: 3. DRINKS (por cabin) | B51: QUANT. | C51: $ CUSTO | D51: $ VENDA | E51: SUBTOTAL | F51: SUBTOTAL $ CUSTO | G51: COMISSÕES
A52: ='BASE PAX'!A27 -> SUCOS | B52: ='BASE PAX'!B27 -> 0 | C52: ='BASE PAX'!C27 -> 0 | D52: =(C52*0.2)+C52 -> 0 | E52: =D52*B52 -> 0 | F52: =B52*C52 -> 0 | G52: =E52-F52 -> 0
A53: ='BASE PAX'!A28 -> SUCOS | B53: ='BASE PAX'!B28 -> 0 | C53: ='BASE PAX'!C28 -> 0 | D53: =(C53*0.2)+C53 -> 0 | E53: =D53*B53 -> 0 | F53: =B53*C53 -> 0 | G53: =E53-F53 -> 0
A54: ='BASE PAX'!A29 -> CERVEJAS | B54: ='BASE PAX'!B29 -> 0 | C54: ='BASE PAX'!C29 -> 2000 | D54: =(C54*0.2)+C54 -> 2400 | E54: =D54*B54 -> 0 | F54: =B54*C54 -> 0 | G54: =E54-F54 -> 0
A55: ='BASE PAX'!A30 -> VINHOS | B55: ='BASE PAX'!B30 -> 0 | C55: ='BASE PAX'!C30 -> 8000 | D55: =(C55*0.2)+C55 -> 9600 | E55: =D55*B55 -> 0 | F55: =B55*C55 -> 0 | G55: =E55-F55 -> 0
A56: ='BASE PAX'!A31 -> DRINKS | B56: ='BASE PAX'!B31 -> 0 | C56: ='BASE PAX'!C31 -> 15000 | D56: =(C56*0.2)+C56 -> 18000 | E56: =D56*B56 -> 0 | F56: =B56*C56 -> 0 | G56: =E56-F56 -> 0
A57: ='BASE PAX'!A32 -> COOLER | B57: ='BASE PAX'!B32 -> 0 | C57: ='BASE PAX'!C32 -> 5000 | D57: =(C57*0.2)+C57 -> 6000 | E57: =D57*B57 -> 0 | F57: =B57*C57 -> 0 | G57: =E57-F57 -> 0
A58: ='BASE PAX'!A33 -> 0 | B58: ='BASE PAX'!B33 -> 0 | C58: ='BASE PAX'!C33 -> 0 | D58: =(C58*0.2)+C58 -> 0 | E58: =D58*B58 -> 0 | F58: =B58*C58 -> 0 | G58: =E58-F58 -> 0
A59: SUBTOTAL DRINKS | E59: =SUM(E52:E58) -> 0 | F59: =SUM(F52:F58) -> 0 | G59: =E59-F59 -> 0
A61: 4. ACTIVITIES | B61: QUANT. | C61: $ CUSTO | D61: $ VENDA | E61: SUBTOTAL | F61: SUBTOTAL $ CUSTO | G61: COMISSÕES
A62: ='BASE PAX'!A37 -> HOTTUBE | B62: ='BASE PAX'!B37 -> 0 | C62: ='BASE PAX'!C37 -> 12000 | D62: =C62*0.2+C62 -> 14400 | E62: =D62*B62 -> 0 | F62: =B62*C62 -> 0 | G62: =E62-F62 -> 0
A63: ='BASE PAX'!A38 -> TREKKING 1/2 DAY | B63: ='BASE PAX'!B38 -> 0 | C63: ='BASE PAX'!C38 -> 60000 | D63: =C63*0.2+C63 -> 72000 | E63: =D63*B63 -> 0 | F63: =B63*C63 -> 0 | G63: =E63-F63 -> 0
A64: ='BASE PAX'!A39 -> TREKKING FUK DAY | B64: ='BASE PAX'!B39 -> 0 | C64: ='BASE PAX'!C39 -> 90000 | D64: =C64*0.2+C64 -> 108000 | E64: =D64*B64 -> 0 | F64: =B64*C64 -> 0 | G64: =E64-F64 -> 0
A65: ='BASE PAX'!A40 -> FLOTADA FAMILIAR | B65: ='BASE PAX'!B40 -> 0 | C65: ='BASE PAX'!C40 -> 60000 | D65: =C65*0.2+C65 -> 72000 | E65: =D65*B65 -> 0 | F65: =B65*C65 -> 0 | G65: =E65-F65 -> 0
A66: ='BASE PAX'!A41 -> RAFTING 1/2 DAY | B66: ='BASE PAX'!B41 -> 0 | C66: ='BASE PAX'!C41 -> 75000 | D66: =C66*0.2+C66 -> 90000 | E66: =D66*B66 -> 0 | F66: =B66*C66 -> 0 | G66: =E66-F66 -> 0
A67: ='BASE PAX'!A42 -> RAFTING FULL DAY | B67: ='BASE PAX'!B42 -> 0 | C67: ='BASE PAX'!C42 -> 110000 | D67: =C67*0.2+C67 -> 132000 | E67: =D67*B67 -> 0 | F67: =B67*C67 -> 0 | G67: =E67-F67 -> 0
A68: ='BASE PAX'!A43 -> CABALGADA 1/2 DAy | B68: ='BASE PAX'!B43 -> 0 | C68: ='BASE PAX'!C43 -> 90000 | D68: =C68*0.2+C68 -> 108000 | E68: =D68*B68 -> 0 | F68: =B68*C68 -> 0 | G68: =E68-F68 -> 0
A69: ='BASE PAX'!A44 -> CABALGADA FULL DAY | B69: ='BASE PAX'!B44 -> 0 | C69: ='BASE PAX'!C44 -> 140000 | D69: =C69*0.2+C69 -> 168000 | E69: =D69*B69 -> 0 | F69: =B69*C69 -> 0 | G69: =E69-F69 -> 0
A70: ='BASE PAX'!A45 -> LANCHA YELCHO | B70: ='BASE PAX'!B45 -> 0 | C70: ='BASE PAX'!C45 -> 120000 | D70: =C70*0.2+C70 -> 144000 | E70: =D70*B70 -> 0 | F70: =B70*C70 -> 0 | G70: =E70-F70 -> 0
A71: ='BASE PAX'!A46 -> RECREACAO INFANTIL 3HS | B71: ='BASE PAX'!B46 -> 0 | C71: ='BASE PAX'!C46 -> 30000 | D71: =C71*0.2+C71 -> 36000 | E71: =D71*B71 -> 0 | F71: =B71*C71 -> 0 | G71: =E71-F71 -> 0
A72: SUBTOTAL ACTIVITIES | E72: =SUM(E62:E71) -> 0 | F72: =B72*C72 -> 0 | G72: =E72-F72 -> 0
A74: 5. TRANSPORT | B74: QUANT. | C74: $ CUSTO | D74: $ VENDA | E74: SUBTOTAL | F74: SUBTOTAL CUSTO | G74: COMISSÕES
A75: ='BASE PAX'!A50 -> TRANSFER AEROPORTO CHEGADA | B75: ='BASE PAX'!B50 -> 0 | C75: 50000 | D75: =C75*0.2+C75 -> 60000 | E75: =D75*B75 -> 0 | F75: =B75*C75 -> 0 | G75: =E75-F75 -> 0
A76: ='BASE PAX'!A51 -> TRANSFER AEROPORTO PARTIDA | B76: ='BASE PAX'!B51 -> 0 | C76: ='BASE PAX'!C51 -> 80000 | D76: =C76*0.2+C76 -> 96000 | E76: =D76*B76 -> 0 | F76: =B76*C76 -> 0 | G76: =E76-F76 -> 0
A77: ='BASE PAX'!A52 -> TRANSFERS INTERNO | B77: ='BASE PAX'!B52 -> 0 | C77: ='BASE PAX'!C52 -> 18000 | D77: =C77*0.2+C77 -> 21600 | E77: =D77*B77 -> 0 | F77: =B77*C77 -> 0 | G77: =E77-F77 -> 0
A78: ='BASE PAX'!A53 -> EXTRAS 1 | B78: ='BASE PAX'!B53 -> 0 | C78: ='BASE PAX'!C53 -> 150000 | D78: =C78*0.2+C78 -> 180000 | E78: =D78*B78 -> 0 | F78: =B78*C78 -> 0 | G78: =E78-F78 -> 0
A79: ='BASE PAX'!A54 -> EXTRAS 2 | B79: ='BASE PAX'!B54 -> 0 | C79: ='BASE PAX'!C54 -> 0 | D79: =C79*0.2+C79 -> 0 | E79: =D79*B79 -> 0 | F79: =B79*C79 -> 0 | G79: =E79-F79 -> 0
A80: SUBTOTAL TRANSPORT | E80: =SUM(E75:E79) -> 0 | F80: =SUM(F75:F79) -> 0 | G80: =E80-F80 -> 0
A82: 6. EXPERIENCES | B82: QUANT. | C82: $ CUSTO | D82: $ VENDA | E82: SUBTOTAL | F82: SUBTOTAL CUSTO | G82: COMISSÕES
A83: ='BASE PAX'!A58 -> WS INSTRUCTOR | B83: ='BASE PAX'!B58 -> 0 | C83: ='BASE PAX'!C58 -> 3415000 | D83: =(C83*0.15)+C83 -> 3927250 | E83: =D83*B83 -> 0 | F83: =B83*C83 -> 0 | G83: =E83-F83 -> 0
A84: ='BASE PAX'!A59 -> PRODUCER FEE | B84: ='BASE PAX'!B59 -> 0 | C84: ='BASE PAX'!C59 -> 180000 | D84: =(C84*0.15)+C84 -> 207000 | E84: =D84*B84 -> 0 | F84: =B84*C84 -> 0 | G84: =E84-F84 -> 0
A85: ='BASE PAX'!A60 -> 0 | B85: ='BASE PAX'!B60 -> 0 | C85: ='BASE PAX'!C60 -> 20000 | D85: =(C85*0.15)+C85 -> 23000 | E85: =D85*B85 -> 0 | F85: =B85*C85 -> 0 | G85: =E85-F85 -> 0
A86: SUBTOTAL EXPERIENCES | E86: =SUM(E83:E85) -> 0 | F86: =SUM(F81:F85) -> 0 | G86: =E86-F86 -> 0
A88: 7. EXTRAS ( por cabin ) | B88: USOS | C88: $ CUSTO | D88: $ VENDA | E88: SUBTOTAL | G88: COMISSÕES
A89: ='BASE PAX'!A64 -> COORDENAÇÃO PRODUÇÃO | B89: ='BASE PAX'!B64 -> 0 | C89: ='BASE PAX'!C64 -> 50000 | D89: ='BASE PAX'!D64 -> 0 | E89: =D89*B89 -> 0 | G89: =E89*0.2 -> 0
A90: ='BASE PAX'!A65 -> EXTRA MÃO DE OBRA | B90: ='BASE PAX'!B65 -> 0 | C90: ='BASE PAX'!C65 -> 50000 | D90: ='BASE PAX'!D65 -> 0 | E90: =D90*B90 -> 0 | G90: =E90*0.2 -> 0
A91: ='BASE PAX'!A66 -> TAXA LIMPEZA CHECK IN / CHECKOUT | B91: ='BASE PAX'!B66 -> 0 | C91: ='BASE PAX'!C66 -> 40000 | D91: ='BASE PAX'!D66 -> 0 | E91: =D91*B91 -> 0 | G91: =E91*0.2 -> 0
A92: ='BASE PAX'!A67 -> TAXA LIMPEZA DIARIA | B92: ='BASE PAX'!B67 -> 0 | C92: ='BASE PAX'!C67 -> 30000 | D92: ='BASE PAX'!D67 -> 0 | E92: =D92*B92 -> 0 | G92: =E92*0.2 -> 0
A93: ='BASE PAX'!A68 -> SOUVENIR | B93: ='BASE PAX'!B68 -> 0 | C93: ='BASE PAX'!C68 -> 15000 | D93: ='BASE PAX'!D68 -> 0 | E93: =D93*B93 -> 0 | G93: =E93*0.2 -> 0
A94: ='BASE PAX'!A69 -> ASSISTENTE COORDENAÇÃO | B94: ='BASE PAX'!B69 -> 0 | C94: ='BASE PAX'!C69 -> 30000 | D94: ='BASE PAX'!D69 -> 0 | E94: =D94*B94 -> 0 | G94: =E94*0.2 -> 0
A95: SUBTOTAL EXTRAS | E95: =SUM(E89:E94) -> 0 | G95: =SUM(G89:G94) -> 0
A97: 8. QUINCHO (por cabin) | B97: USOS | C97: $ CUSTO | D97: $ VENDA | E97: SUBTOTAL
A98: ='BASE PAX'!A73 -> QUINCHO DAY USE / CABIN | B98: ='BASE PAX'!B73 -> 0 | C98: ='BASE PAX'!C73 -> 15000 | D98: =C98+(C98*0.2) -> 18000 | E98: =D98*B98 -> 0
A99: SUBTOTAL QUINCHO | E99: =E98 -> 0

Sheet BUDGET CHAITEN 1
C3: COIGUE
A5: TOTAL PAX ADULT | B5: 1 | E5: CHAITEN
A6: TOTAL PAX INFANT | B6: 0 | D6: BUDGET TOTAL | F6: =D21 -> 0
A7: CHECK IN. | B7: =CALENDAR!C2 -> 0 | D7: SUBTOTAL PAGO | F7: =SUM(F12:F20) -> 0
A8: CHECK OUT. | B8: =CALENDAR!C3 -> 0 | D8: SUBTOTAL A RECEBER | F8: =F6-F7 -> 0
A9: TOTAL NIGHTS. | B9: =CALENDAR!J2 -> 0 | D9: TIP |
A11: RESUMO. | B11: PREÇO CLIENTE CASH CLP $ | C11: TAXA CC | D11: PREÇO CLIENTE PAGTO CC $ | F11: =E5 -> CHAITEN | I11: CONTROLE PAGAMENTOS
C12: 0.05 | I12: DATA | J12: VALOR PAGO CLP $ | K12: FORMA PAGTO
A13: 1.LODGING | B13: =G28 -> 0 | C13: =B13*$C$12 -> 0 | D13: =B13+(B13*$C$12) -> 0
A14: 2.FOOD | B14: =J49 -> 0 | C14: =B14*$C$12 -> 0 | D14: =B14+(B14*$C$12) -> 0 | F14: =A14 -> 2.FOOD | G14: =G49 -> 0
A15: 3.DRINKS | B15: =E59 -> 0 | C15: =B15*$C$12 -> 0 | D15: =B15+(B15*$C$12) -> 0 | F15: =A15 -> 3.DRINKS | G15: =G59 -> 0
A16: 4. ACTIVITIES | B16: =$E$72 -> 0 | C16: =B16*$C$12 -> 0 | D16: =B16+(B16*$C$12) -> 0 | F16: =A16 -> 4. ACTIVITIES | G16: =G72 -> 0
A17: 5.TRANSPORT | B17: =$E$80 -> 0 | C17: =B17*$C$12 -> 0 | D17: =B17+(B17*$C$12) -> 0 | F17: =A17 -> 5.TRANSPORT | G17: =G80 -> 0
A18: 6.EXPERIENCES | B18: =$E$86 -> 0 | C18: =B18*$C$12 -> 0 | D18: =B18+(B18*$C$12) -> 0 | F18: =A18 -> 6.EXPERIENCES | G18: =G86 -> 0
A19: 7.EXTRAS | B19: =$E$95 -> 0 | C19: =B19*$C$12 -> 0 | D19: =B19+(B19*$C$12) -> 0 | F19: =A19 -> 7.EXTRAS | G19: =G95 -> 0
A20: 8. QUINCHO | B20: =$E$99 -> 0 | C20: =B20*$C$12 -> 0 | D20: =B20+(B20*$C$12) -> 0 | F20: SUBTOTAL COMISSÕES | G20: =G14+G15+G16+G17+G18+G19 -> 0
A21: SUBTOTAL 1 | B21: =SUM(B13:B20) -> 0 | D21: =SUM(D13:D20) -> 0
A23: 1. LODGING | B23: QUANT. | C23: $ CABIN / DIA | D23: $ ADICIONAL / DIA | E23: BASE CÁLCULO | F23: DESCONTOS | G23: $ SUBTOTAL
A24: CHAITEN (até 2 pax) - até 06 noites | B24: 1 | C24: =288190.9 -> 288190.9 | E24: =(C24+D24)*$B$9*B24 -> 0 | F24: 0 | G24: =E24-(E24*F24) -> 0
A25: CHAITEN ( 2 + baby) - até 06 noites | B25: 0 | C25: =288190.9 -> 288190.9 | D25: 50000 | E25: =(C25+D25)*$B$9*B25 -> 0 | F25: 0 | G25: =E25-(E25*F25) -> 0
A26: CHAITEN (até 2 pax) - 7 noites ou + | B26: 0 | C26: =259371.81 -> 259371.81 | E26: =(C26+D26)*$B$9*B26 -> 0 | F26: 0 | G26: =E26-(E26*F26) -> 0
A27: CHAITEN ( 2 + baby) - 7 noites ou + | B27: 0 | C27: =259371.81 -> 259371.81 | D27: 50000 | E27: =(C27+D27)*$B$9*B27 -> 0 | F27: 0 | G27: =E27-(E27*F27) -> 0
A28: SUBTOTAL LODGING | G28: =SUM(G24:G27) -> 0
A30: 2. FOOD | B30: QUANT. | C30: $ CUSTO | D30: $ VENDA | E30: SUBTOTAL $ VENDA | F30: SUBTOTAL $ CUSTO | G30: COMISSÕES
A31: ='BASE PAX'!A6 -> BREAKFAST | B31: =(B5*B9*'BASE PAX'!G6)+('BASE PAX'!H6*B6*B9) -> 0 | E31: 0 | F31: =B31*C31 -> 0 | G31: =0.2*B31 -> 0 | H31: =A31 -> BREAKFAST | I31: =B31 -> 0
A32: ='BASE PAX'!A7 -> LUNCH 1 | B32: =($B$5+$B$6)*'BASE PAX'!B7 -> 0 | C32: ='BASE PAX'!C7 -> 40000 | D32: ='BASE PAX'!D7 -> 48000 | E32: =D32*B32 -> 0 | F32: =B32*C32 -> 0 | G32: =E32-F32 -> 0
A33: ='BASE PAX'!A8 -> LUNCH 2 | B33: =($B$5+$B$6)*'BASE PAX'!B8 -> 0 | C33: ='BASE PAX'!C8 -> 40000 | D33: ='BASE PAX'!D8 -> 48000 | E33: =D33*B33 -> 0 | F33: =B33*C33 -> 0 | G33: =E33-F33 -> 0
A34: ='BASE PAX'!A9 -> LUNCH 3 | B34: =($B$5+$B$6)*'BASE PAX'!B9 -> 0 | C34: ='BASE PAX'!C9 -> 40000 | D34: ='BASE PAX'!D9 -> 48000 | E34: =D34*B34 -> 0 | F34: =B34*C34 -> 0 | G34: =E34-F34 -> 0
A35: ='BASE PAX'!A10 -> LUNCH 4 | B35: =($B$5+$B$6)*'BASE PAX'!B10 -> 0 | C35: ='BASE PAX'!C10 -> 45000 | D35: ='BASE PAX'!D10 -> 54000 | E35: =D35*B35 -> 0 | F35: =B35*C35 -> 0 | G35: =E35-F35 -> 0
A36: ='BASE PAX'!A11 -> LUNCH 5 | B36: =($B$5+$B$6)*'BASE PAX'!B11 -> 0 | C36: ='BASE PAX'!C11 -> 50000 | D36: ='BASE PAX'!D11 -> 60000 | E36: =D36*B36 -> 0 | F36: =B36*C36 -> 0 | G36: =E36-F36 -> 0
A37: ='BASE PAX'!A12 -> LUNCH 6 | B37: =($B$5+$B$6)*'BASE PAX'!B12 -> 0 | C37: ='BASE PAX'!C12 -> 0 | D37: ='BASE PAX'!D12 -> 0 | E37: =D37*B37 -> 0 | F37: =B37*C37 -> 0 | G37: =E37-F37 -> 0
A38: ='BASE PAX'!A13 -> LUNCH 7 | B38: =($B$5+$B$6)*'BASE PAX'!B13 -> 0 | C38: ='BASE PAX'!C13 -> 5000 | D38: ='BASE PAX'!D13 -> 6000 | E38: =D38*B38 -> 0 | F38: =B38*C38 -> 0 | G38: =E38-F38 -> 0
A39: ='BASE PAX'!A14 -> SNACKS | B39: =($B$5+$B$6)*'BASE PAX'!B14 -> 0 | C39: ='BASE PAX'!C14 -> 8000 | D39: ='BASE PAX'!D14 -> 9600 | E39: =D39*B39 -> 0 | F39: =B39*C39 -> 0 | G39: =E39-F39 -> 0
A40: ='BASE PAX'!A15 -> DINNER 1 | B40: =($B$5+$B$6)*'BASE PAX'!B15 -> 0 | C40: ='BASE PAX'!C15 -> 70000 | D40: ='BASE PAX'!D15 -> 84000 | E40: =D40*B40 -> 0 | F40: =B40*C40 -> 0 | G40: =E40-F40 -> 0
A41: ='BASE PAX'!A16 -> DINNER 2 | B41: =($B$5+$B$6)*'BASE PAX'!B16 -> 0 | C41: ='BASE PAX'!C16 -> 25000 | D41: ='BASE PAX'!D16 -> 30000 | E41: =D41*B41 -> 0 | F41: =B41*C41 -> 0 | G41: =E41-F41 -> 0
A42: ='BASE PAX'!A17 -> DINNER 3 | B42: =($B$5+$B$6)*'BASE PAX'!B17 -> 0 | C42: ='BASE PAX'!C17 -> 50000 | D42: ='BASE PAX'!D17 -> 60000 | E42: =D42*B42 -> 0 | F42: =B42*C42 -> 0 | G42: =E42-F42 -> 0
A43: ='BASE PAX'!A18 -> DINNER 4 | B43: =($B$5+$B$6)*'BASE PAX'!B18 -> 0 | C43: ='BASE PAX'!C18 -> 65000 | D43: ='BASE PAX'!D18 -> 78000 | E43: =D43*B43 -> 0 | F43: =B43*C43 -> 0 | G43: =E43-F43 -> 0
... A46: ='BASE PAX'!A21 -> DINNER 7 | B46: =($B$5+$B$6)*'BASE PAX'!B21 -> 0 | C46: ='BASE PAX'!C21 -> 75000 | D46: ='BASE PAX'!D21 -> 90000 | E46: =D46*B46 -> 0 | F46: =B46*C46 -> 0 | G46: =E46-F46 -> 0
A47: ='BASE PAX'!A22 -> QUANT. TOTAL | PADRAO ALMOÇO | B47: ='BASE PAX'!B22 -> 0 | G47: =0.2*I47 -> 0 | H47: =A47 -> QUANT. TOTAL | PADRAO ALMOÇO | I47: =(B5*B47*'BASE PAX'!G22)+(B6*B47*'BASE PAX'!H22) -> 0
A48: ='BASE PAX'!A23 -> QUANT. TOTAL | PADRAO JANTAR | B48: ='BASE PAX'!B23 -> 0 | G48: =0.2*I48 -> 0 | H48: =A48 -> QUANT. TOTAL | PADRAO JANTAR | I48: =(B5*B48*'BASE PAX'!G23)+(B6*B48*'BASE PAX'!H23) -> 0
A49: SUBTOTAL FOOD | E49: =SUM(E31:E48) -> 0 | F49: =SUM(F31:F48) -> 0 | G49: =SUM(G31:G48) -> 0 | H49: SUBTOTAL | I49: =I31+I47+I48 -> 0 | J49: =I49+E49 -> 0 | K49: TOTAL FOOD
A51: 3. DRINKS (por cabin) | B51: QUANT. | C51: $ CUSTO | D51: $ VENDA | E51: SUBTOTAL | F51: SUBTOTAL $ CUSTO | G51: COMISSÕES
A52: ='BASE PAX'!A27 -> SUCOS | B52: ='BASE PAX'!B27 -> 0 | C52: ='BASE PAX'!C27 -> 0 | D52: =(C52*0.2)+C52 -> 0 | E52: =D52*B52 -> 0 | F52: =B52*C52 -> 0 | G52: =E52-F52 -> 0
A53: ='BASE PAX'!A28 -> SUCOS | B53: ='BASE PAX'!B28 -> 0 | C53: ='BASE PAX'!C28 -> 0 | D53: =(C53*0.2)+C53 -> 0 | E53: =D53*B53 -> 0 | F53: =B53*C53 -> 0 | G53: =E53-F53 -> 0
A54: ='BASE PAX'!A29 -> CERVEJAS | B54: ='BASE PAX'!B29 -> 0 | C54: ='BASE PAX'!C29 -> 2000 | D54: =(C54*0.2)+C54 -> 2400 | E54: =D54*B54 -> 0 | F54: =B54*C54 -> 0 | G54: =E54-F54 -> 0
A55: ='BASE PAX'!A30 -> VINHOS | B55: ='BASE PAX'!B30 -> 0 | C55: ='BASE PAX'!C30 -> 8000 | D55: =(C55*0.2)+C55 -> 9600 | E55: =D55*B55 -> 0 | F55: =B55*C55 -> 0 | G55: =E55-F55 -> 0
A56: ='BASE PAX'!A31 -> DRINKS | B56: ='BASE PAX'!B31 -> 0 | C56: ='BASE PAX'!C31 -> 15000 | D56: =(C56*0.2)+C56 -> 18000 | E56: =D56*B56 -> 0 | F56: =B56*C56 -> 0 | G56: =E56-F56 -> 0
A57: ='BASE PAX'!A32 -> COOLER | B57: ='BASE PAX'!B32 -> 0 | C57: ='BASE PAX'!C32 -> 5000 | D57: =(C57*0.2)+C57 -> 6000 | E57: =D57*B57 -> 0 | F57: =B57*C57 -> 0 | G57: =E57-F57 -> 0
A58: ='BASE PAX'!A33 -> 0 | B58: ='BASE PAX'!B33 -> 0 | C58: ='BASE PAX'!C33 -> 0 | D58: =(C58*0.2)+C58 -> 0 | E58: =D58*B58 -> 0 | F58: =B58*C58 -> 0 | G58: =E58-F58 -> 0
A59: SUBTOTAL DRINKS | E59: =SUM(E52:E58) -> 0 | F59: =SUM(F52:F58) -> 0 | G59: =E59-F59 -> 0
A61: 4. ACTIVITIES | B61: QUANT. | C61: $ CUSTO | D61: $ VENDA | E61: SUBTOTAL | F61: SUBTOTAL $ CUSTO | G61: COMISSÕES
A62: ='BASE PAX'!A37 -> HOTTUBE | B62: ='BASE PAX'!B37 -> 0 | C62: ='BASE PAX'!C37 -> 12000 | D62: =C62*0.2+C62 -> 14400 | E62: =D62*B62 -> 0 | F62: =B62*C62 -> 0 | G62: =E62-F62 -> 0
A63: ='BASE PAX'!A38 -> TREKKING 1/2 DAY | B63: ='BASE PAX'!B38 -> 0 | C63: ='BASE PAX'!C38 -> 60000 | D63: =C63*0.2+C63 -> 72000 | E63: =D63*B63 -> 0 | F63: =B63*C63 -> 0 | G63: =E63-F63 -> 0
A64: ='BASE PAX'!A39 -> TREKKING FUK DAY | B64: ='BASE PAX'!B39 -> 0 | C64: ='BASE PAX'!C39 -> 90000 | D64: =C64*0.2+C64 -> 108000 | E64: =D64*B64 -> 0 | F64: =B64*C64 -> 0 | G64: =E64-F64 -> 0
A65: ='BASE PAX'!A40 -> FLOTADA FAMILIAR | B65: ='BASE PAX'!B40 -> 0 | C65: ='BASE PAX'!C40 -> 60000 | D65: =C65*0.2+C65 -> 72000 | E65: =D65*B65 -> 0 | F65: =B65*C65 -> 0 | G65: =E65-F65 -> 0
A66: ='BASE PAX'!A41 -> RAFTING 1/2 DAY | B66: ='BASE PAX'!B41 -> 0 | C66: ='BASE PAX'!C41 -> 75000 | D66: =C66*0.2+C66 -> 90000 | E66: =D66*B66 -> 0 | F66: =B66*C66 -> 0 | G66: =E66-F66 -> 0
A67: ='BASE PAX'!A42 -> RAFTING FULL DAY | B67: ='BASE PAX'!B42 -> 0 | C67: ='BASE PAX'!C42 -> 110000 | D67: =C67*0.2+C67 -> 132000 | E67: =D67*B67 -> 0 | F67: =B67*C67 -> 0 | G67: =E67-F67 -> 0
A68: ='BASE PAX'!A43 -> CABALGADA 1/2 DAy | B68: ='BASE PAX'!B43 -> 0 | C68: ='BASE PAX'!C43 -> 90000 | D68: =C68*0.2+C68 -> 108000 | E68: =D68*B68 -> 0 | F68: =B68*C68 -> 0 | G68: =E68-F68 -> 0
A69: ='BASE PAX'!A44 -> CABALGADA FULL DAY | B69: ='BASE PAX'!B44 -> 0 | C69: ='BASE PAX'!C44 -> 140000 | D69: =C69*0.2+C69 -> 168000 | E69: =D69*B69 -> 0 | F69: =B69*C69 -> 0 | G69: =E69-F69 -> 0
A70: ='BASE PAX'!A45 -> LANCHA YELCHO | B70: ='BASE PAX'!B45 -> 0 | C70: ='BASE PAX'!C45 -> 120000 | D70: =C70*0.2+C70 -> 144000 | E70: =D70*B70 -> 0 | F70: =B70*C70 -> 0 | G70: =E70-F70 -> 0
A71: ='BASE PAX'!A46 -> RECREACAO INFANTIL 3HS | B71: ='BASE PAX'!B46 -> 0 | C71: ='BASE PAX'!C46 -> 30000 | D71: =C71*0.2+C71 -> 36000 | E71: =D71*B71 -> 0 | F71: =B71*C71 -> 0 | G71: =E71-F71 -> 0
A72: SUBTOTAL ACTIVITIES | E72: =SUM(E62:E71) -> 0 | F72: =B72*C72 -> 0 | G72: =E72-F72 -> 0
A74: 5. TRANSPORT | B74: QUANT. | C74: $ CUSTO | D74: $ VENDA | E74: SUBTOTAL | F74: SUBTOTAL CUSTO | G74: COMISSÕES
A75: ='BASE PAX'!A50 -> TRANSFER AEROPORTO CHEGADA | B75: ='BASE PAX'!B50 -> 0 | C75: ='BASE PAX'!C50 -> 80000 | D75: =C75*0.2+C75 -> 96000 | E75: =D75*B75 -> 0 | F75: =B75*C75 -> 0 | G75: =E75-F75 -> 0
A76: ='BASE PAX'!A51 -> TRANSFER AEROPORTO PARTIDA | B76: ='BASE PAX'!B51 -> 0 | C76: ='BASE PAX'!C51 -> 80000 | D76: =C76*0.2+C76 -> 96000 | E76: =D76*B76 -> 0 | F76: =B76*C76 -> 0 | G76: =E76-F76 -> 0
A77: ='BASE PAX'!A52 -> TRANSFERS INTERNO | B77: ='BASE PAX'!B52 -> 0 | C77: ='BASE PAX'!C52 -> 18000 | D77: =C77*0.2+C77 -> 21600 | E77: =D77*B77 -> 0 | F77: =B77*C77 -> 0 | G77: =E77-F77 -> 0
A78: ='BASE PAX'!A53 -> EXTRAS 1 | B78: ='BASE PAX'!B53 -> 0 | C78: ='BASE PAX'!C53 -> 150000 | D78: =C78*0.2+C78 -> 180000 | E78: =D78*B78 -> 0 | F78: =B78*C78 -> 0 | G78: =E78-F78 -> 0
A79: ='BASE PAX'!A54 -> EXTRAS 2 | B79: ='BASE PAX'!B54 -> 0 | C79: ='BASE PAX'!C54 -> 0 | D79: =C79*0.2+C79 -> 0 | E79: =D79*B79 -> 0 | F79: =B79*C79 -> 0 | G79: =E79-F79 -> 0
A80: SUBTOTAL TRANSPORT | E80: =SUM(E75:E79) -> 0 | F80: =SUM(F75:F79) -> 0 | G80: =E80-F80 -> 0
A82: 6. EXPERIENCES | B82: QUANT. | C82: $ CUSTO | D82: $ VENDA | E82: SUBTOTAL | F82: SUBTOTAL CUSTO | G82: COMISSÕES
A83: ='BASE PAX'!A58 -> WS INSTRUCTOR | B83: ='BASE PAX'!B58 -> 0 | C83: ='BASE PAX'!C58 -> 3415000 | D83: =(C83*0.15)+C83 -> 3927250 | E83: =D83*B83 -> 0 | F83: =B83*C83 -> 0 | G83: =E83-F83 -> 0
A84: ='BASE PAX'!A59 -> PRODUCER FEE | B84: ='BASE PAX'!B59 -> 0 | C84: ='BASE PAX'!C59 -> 180000 | D84: =(C84*0.15)+C84 -> 207000 | E84: =D84*B84 -> 0 | F84: =B84*C84 -> 0 | G84: =E84-F84 -> 0
A85: ='BASE PAX'!A60 -> 0 | B85: ='BASE PAX'!B60 -> 0 | C85: ='BASE PAX'!C60 -> 20000 | D85: =(C85*0.15)+C85 -> 23000 | E85: =D85*B85 -> 0 | F85: =B85*C85 -> 0 | G85: =E85-F85 -> 0
A86: SUBTOTAL EXPERIENCES | E86: =SUM(E83:E85) -> 0 | F86: =SUM(F81:F85) -> 0 | G86: =E86-F86 -> 0
A88: 7. EXTRAS ( por cabin ) | B88: USOS | C88: $ CUSTO | D88: $ VENDA | E88: SUBTOTAL | G88: COMISSÕES
A89: ='BASE PAX'!A64 -> COORDENAÇÃO PRODUÇÃO | B89: ='BASE PAX'!B64 -> 0 | C89: ='BASE PAX'!C64 -> 50000 | D89: ='BASE PAX'!D64 -> 0 | E89: =D89*B89 -> 0 | G89: =E89*0.2 -> 0
A90: ='BASE PAX'!A65 -> EXTRA MÃO DE OBRA | B90: ='BASE PAX'!B65 -> 0 | C90: ='BASE PAX'!C65 -> 50000 | D90: ='BASE PAX'!D65 -> 0 | E90: =D90*B90 -> 0 | G90: =E90*0.2 -> 0
A91: ='BASE PAX'!A66 -> TAXA LIMPEZA CHECK IN / CHECKOUT | B91: ='BASE PAX'!B66 -> 0 | C91: ='BASE PAX'!C66 -> 40000 | D91: ='BASE PAX'!D66 -> 0 | E91: =D91*B91 -> 0 | G91: =E91*0.2 -> 0
A92: ='BASE PAX'!A67 -> TAXA LIMPEZA DIARIA | B92: ='BASE PAX'!B67 -> 0 | C92: ='BASE PAX'!C67 -> 30000 | D92: ='BASE PAX'!D67 -> 0 | E92: =D92*B92 -> 0 | G92: =E92*0.2 -> 0
A93: ='BASE PAX'!A68 -> SOUVENIR | B93: ='BASE PAX'!B68 -> 0 | C93: ='BASE PAX'!C68 -> 15000 | D93: ='BASE PAX'!D68 -> 0 | E93: =D93*B93 -> 0 | G93: =E93*0.2 -> 0
A94: ='BASE PAX'!A69 -> ASSISTENTE COORDENAÇÃO | B94: ='BASE PAX'!B69 -> 0 | C94: ='BASE PAX'!C69 -> 30000 | D94: ='BASE PAX'!D69 -> 0 | E94: =D94*B94 -> 0 | G94: =E94*0.2 -> 0
A95: SUBTOTAL EXTRAS | E95: =SUM(E89:E94) -> 0 | G95: =SUM(G89:G94) -> 0
A97: 8. QUINCHO (por cabin) | B97: USOS | C97: $ CUSTO | D97: $ VENDA | E97: SUBTOTAL
A98: ='BASE PAX'!A73 -> QUINCHO DAY USE / CABIN | B98: ='BASE PAX'!B73 -> 0 | C98: ='BASE PAX'!C73 -> 15000 | D98: =C98+(C98*0.2) -> 18000 | E98: =D98*B98 -> 0
A99: SUBTOTAL QUINCHO | E99: =E98 -> 0

Sheet BUDGET CHAITEN 2
C3: COIGUE
A5: TOTAL PAX ADULT | B5: 2 | E5: CHAITEN
A6: TOTAL PAX INFANT | B6: 0 | D6: BUDGET TOTAL | F6: =D21 -> 0
A7: CHECK IN. | B7: =CALENDAR!C2 -> 0 | D7: SUBTOTAL PAGO | F7: =SUM(F12:F20) -> 0
A8: CHECK OUT. | B8: =CALENDAR!C3 -> 0 | D8: SUBTOTAL A RECEBER | F8: =F6-F7 -> 0
A9: TOTAL NIGHTS. | B9: =CALENDAR!J2 -> 0 | D9: TIP |
A11: RESUMO. | B11: PREÇO CLIENTE CASH CLP $ | C11: TAXA CC | D11: PREÇO CLIENTE PAGTO CC $ | F11: =E5 -> CHAITEN | I11: CONTROLE PAGAMENTOS
C12: 0.05 | I12: DATA | J12: VALOR PAGO CLP $ | K12: FORMA PAGTO
A13: 1.LODGING | B13: =G28 -> 0 | C13: =B13*$C$12 -> 0 | D13: =B13+(B13*$C$12) -> 0
A14: 2.FOOD | B14: =J49 -> 0 | C14: =B14*$C$12 -> 0 | D14: =B14+(B14*$C$12) -> 0 | F14: =A14 -> 2.FOOD | G14: =G49 -> 0
A15: 3.DRINKS | B15: =E59 -> 0 | C15: =B15*$C$12 -> 0 | D15: =B15+(B15*$C$12) -> 0 | F15: =A15 -> 3.DRINKS | G15: =G59 -> 0
A16: 4. ACTIVITIES | B16: =$E$72 -> 0 | C16: =B16*$C$12 -> 0 | D16: =B16+(B16*$C$12) -> 0 | F16: =A16 -> 4. ACTIVITIES | G16: =G72 -> 0
A17: 5.TRANSPORT | B17: =$E$80 -> 0 | C17: =B17*$C$12 -> 0 | D17: =B17+(B17*$C$12) -> 0 | F17: =A17 -> 5.TRANSPORT | G17: =G80 -> 0
A18: 6.EXPERIENCES | B18: =$E$86 -> 0 | C18: =B18*$C$12 -> 0 | D18: =B18+(B18*$C$12) -> 0 | F18: =A18 -> 6.EXPERIENCES | G18: =G86 -> 0
A19: 7.EXTRAS | B19: =$E$95 -> 0 | C19: =B19*$C$12 -> 0 | D19: =B19+(B19*$C$12) -> 0 | F19: =A19 -> 7.EXTRAS | G19: =G95 -> 0
A20: 8. QUINCHO | B20: =$E$99 -> 0 | C20: =B20*$C$12 -> 0 | D20: =B20+(B20*$C$12) -> 0 | F20: SUBTOTAL COMISSÕES | G20: =G14+G15+G16+G17+G18+G19 -> 0
A21: SUBTOTAL 1 | B21: =SUM(B13:B20) -> 0 | D21: =SUM(D13:D20) -> 0
A23: 1. LODGING | B23: QUANT. | C23: $ CABIN / DIA | D23: $ ADICIONAL / DIA | E23: BASE CÁLCULO | F23: DESCONTOS | G23: $ SUBTOTAL
A24: CHAITEN (até 2 pax) - até 06 noites | B24: 1 | C24: =288190.9 -> 288190.9 | E24: =(C24+D24)*$B$9*B24 -> 0 | F24: 0 | G24: =E24-(E24*F24) -> 0
A25: CHAITEN ( 2 + baby) - até 06 noites | B25: 0 | C25: =288190.9 -> 288190.9 | D25: 50000 | E25: =(C25+D25)*$B$9*B25 -> 0 | F25: 0 | G25: =E25-(E25*F25) -> 0
A26: CHAITEN (até 2 pax) - 7 noites ou + | B26: 0 | C26: =259371.81 -> 259371.81 | E26: =(C26+D26)*$B$9*B26 -> 0 | F26: 0 | G26: =E26-(E26*F26) -> 0
A27: CHAITEN ( 2 + baby) - 7 noites ou + | B27: 0 | C27: =259371.81 -> 259371.81 | D27: 50000 | E27: =(C27+D27)*$B$9*B27 -> 0 | F27: 0 | G27: =E27-(E27*F27) -> 0
A28: SUBTOTAL LODGING | G28: =SUM(G24:G27) -> 0
A30: 2. FOOD | B30: QUANT. | C30: $ CUSTO | D30: $ VENDA | E30: SUBTOTAL $ VENDA | F30: SUBTOTAL $ CUSTO | G30: COMISSÕES
A31: ='BASE PAX'!A6 -> BREAKFAST | B31: =(B5*B9*'BASE PAX'!G6)+('BASE PAX'!H6*B6*B9) -> 0 | E31: 0 | F31: =B31*C31 -> 0 | G31: =0.2*B31 -> 0 | H31: =A31 -> BREAKFAST | I31: =B31 -> 0
A32: ='BASE PAX'!A7 -> LUNCH 1 | B32: =($B$5+$B$6)*'BASE PAX'!B7 -> 0 | C32: ='BASE PAX'!C7 -> 40000 | D32: ='BASE PAX'!D7 -> 48000 | E32: =D32*B32 -> 0 | F32: =B32*C32 -> 0 | G32: =E32-F32 -> 0
A33: ='BASE PAX'!A8 -> LUNCH 2 | B33: =($B$5+$B$6)*'BASE PAX'!B8 -> 0 | C33: ='BASE PAX'!C8 -> 40000 | D33: ='BASE PAX'!D8 -> 48000 | E33: =D33*B33 -> 0 | F33: =B33*C33 -> 0 | G33: =E33-F33 -> 0
A34: ='BASE PAX'!A9 -> LUNCH 3 | B34: =($B$5+$B$6)*'BASE PAX'!B9 -> 0 | C34: ='BASE PAX'!C9 -> 40000 | D34: ='BASE PAX'!D9 -> 48000 | E34: =D34*B34 -> 0 | F34: =B34*C34 -> 0 | G34: =E34-F34 -> 0
A35: ='BASE PAX'!A10 -> LUNCH 4 | B35: =($B$5+$B$6)*'BASE PAX'!B10 -> 0 | C35: ='BASE PAX'!C10 -> 45000 | D35: ='BASE PAX'!D10 -> 54000 | E35: =D35*B35 -> 0 | F35: =B35*C35 -> 0 | G35: =E35-F35 -> 0
A36: ='BASE PAX'!A11 -> LUNCH 5 | B36: =($B$5+$B$6)*'BASE PAX'!B11 -> 0 | C36: ='BASE PAX'!C11 -> 50000 | D36: ='BASE PAX'!D11 -> 60000 | E36: =D36*B36 -> 0 | F36: =B36*C36 -> 0 | G36: =E36-F36 -> 0
A37: ='BASE PAX'!A12 -> LUNCH 6 | B37: =($B$5+$B$6)*'BASE PAX'!B12 -> 0 | C37: ='BASE PAX'!C12 -> 0 | D37: ='BASE PAX'!D12 -> 0 | E37: =D37*B37 -> 0 | F37: =B37*C37 -> 0 | G37: =E37-F37 -> 0
A38: ='BASE PAX'!A13 -> LUNCH 7 | B38: =($B$5+$B$6)*'BASE PAX'!B13 -> 0 | C38: ='BASE PAX'!C13 -> 5000 | D38: ='BASE PAX'!D13 -> 6000 | E38: =D38*B38 -> 0 | F38: =B38*C38 -> 0 | G38: =E38-F38 -> 0
A39: ='BASE PAX'!A14 -> SNACKS | B39: =($B$5+$B$6)*'BASE PAX'!B14 -> 0 | C39: ='BASE PAX'!C14 -> 8000 | D39: ='BASE PAX'!D14 -> 9600 | E39: =D39*B39 -> 0 | F39: =B39*C39 -> 0 | G39: =E39-F39 -> 0
A40: ='BASE PAX'!A15 -> DINNER 1 | B40: =($B$5+$B$6)*'BASE PAX'!B15 -> 0 | C40: ='BASE PAX'!C15 -> 70000 | D40: ='BASE PAX'!D15 -> 84000 | E40: =D40*B40 -> 0 | F40: =B40*C40 -> 0 | G40: =E40-F40 -> 0
A41: ='BASE PAX'!A16 -> DINNER 2 | B41: =($B$5+$B$6)*'BASE PAX'!B16 -> 0 | C41: ='BASE PAX'!C16 -> 25000 | D41: ='BASE PAX'!D16 -> 30000 | E41: =D41*B41 -> 0 | F41: =B41*C41 -> 0 | G41: =E41-F41 -> 0
A42: ='BASE PAX'!A17 -> DINNER 3 | B42: =($B$5+$B$6)*'BASE PAX'!B17 -> 0 | C42: ='BASE PAX'!C17 -> 50000 | D42: ='BASE PAX'!D17 -> 60000 | E42: =D42*B42 -> 0 | F42: =B42*C42 -> 0 | G42: =E42-F42 -> 0
A43: ='BASE PAX'!A18 -> DINNER 4 | B43: =($B$5+$B$6)*'BASE PAX'!B18 -> 0 | C43: ='BASE PAX'!C18 -> 65000 | D43: ='BASE PAX'!D18 -> 78000 | E43: =D43*B43 -> 0 | F43: =B43*C43 -> 0 | G43: =E43-F43 -> 0
... A46: ='BASE PAX'!A21 -> DINNER 7 | B46: =($B$5+$B$6)*'BASE PAX'!B21 -> 0 | C46: ='BASE PAX'!C21 -> 75000 | D46: ='BASE PAX'!D21 -> 90000 | E46: =D46*B46 -> 0 | F46: =B46*C46 -> 0 | G46: =E46-F46 -> 0
A47: ='BASE PAX'!A22 -> QUANT. TOTAL | PADRAO ALMOÇO | B47: ='BASE PAX'!B22 -> 0 | G47: =0.2*I47 -> 0 | H47: =A47 -> QUANT. TOTAL | PADRAO ALMOÇO | I47: =(B5*B47*'BASE PAX'!G22)+(B6*B47*'BASE PAX'!H22) -> 0
A48: ='BASE PAX'!A23 -> QUANT. TOTAL | PADRAO JANTAR | B48: ='BASE PAX'!B23 -> 0 | G48: =0.2*I48 -> 0 | H48: =A48 -> QUANT. TOTAL | PADRAO JANTAR | I48: =(B5*B48*'BASE PAX'!G23)+(B6*B48*'BASE PAX'!H23) -> 0
A49: SUBTOTAL FOOD | E49: =SUM(E31:E48) -> 0 | F49: =SUM(F31:F48) -> 0 | G49: =SUM(G31:G48) -> 0 | H49: SUBTOTAL | I49: =I31+I47+I48 -> 0 | J49: =I49+E49 -> 0 | K49: TOTAL FOOD
A51: 3. DRINKS (por cabin) | B51: QUANT. | C51: $ CUSTO | D51: $ VENDA | E51: SUBTOTAL | F51: SUBTOTAL $ CUSTO | G51: COMISSÕES
A52: ='BASE PAX'!A27 -> SUCOS | B52: ='BASE PAX'!B27 -> 0 | C52: ='BASE PAX'!C27 -> 0 | D52: =(C52*0.2)+C52 -> 0 | E52: =D52*B52 -> 0 | F52: =B52*C52 -> 0 | G52: =E52-F52 -> 0
A53: ='BASE PAX'!A28 -> SUCOS | B53: ='BASE PAX'!B28 -> 0 | C53: ='BASE PAX'!C28 -> 0 | D53: =(C53*0.2)+C53 -> 0 | E53: =D53*B53 -> 0 | F53: =B53*C53 -> 0 | G53: =E53-F53 -> 0
A54: ='BASE PAX'!A29 -> CERVEJAS | B54: ='BASE PAX'!B29 -> 0 | C54: ='BASE PAX'!C29 -> 2000 | D54: =(C54*0.2)+C54 -> 2400 | E54: =D54*B54 -> 0 | F54: =B54*C54 -> 0 | G54: =E54-F54 -> 0
A55: ='BASE PAX'!A30 -> VINHOS | B55: ='BASE PAX'!B30 -> 0 | C55: ='BASE PAX'!C30 -> 8000 | D55: =(C55*0.2)+C55 -> 9600 | E55: =D55*B55 -> 0 | F55: =B55*C55 -> 0 | G55: =E55-F55 -> 0
A56: ='BASE PAX'!A31 -> DRINKS | B56: ='BASE PAX'!B31 -> 0 | C56: ='BASE PAX'!C31 -> 15000 | D56: =(C56*0.2)+C56 -> 18000 | E56: =D56*B56 -> 0 | F56: =B56*C56 -> 0 | G56: =E56-F56 -> 0
A57: ='BASE PAX'!A32 -> COOLER | B57: ='BASE PAX'!B32 -> 0 | C57: ='BASE PAX'!C32 -> 5000 | D57: =(C57*0.2)+C57 -> 6000 | E57: =D57*B57 -> 0 | F57: =B57*C57 -> 0 | G57: =E57-F57 -> 0
A58: ='BASE PAX'!A33 -> 0 | B58: ='BASE PAX'!B33 -> 0 | C58: ='BASE PAX'!C33 -> 0 | D58: =(C58*0.2)+C58 -> 0 | E58: =D58*B58 -> 0 | F58: =B58*C58 -> 0 | G58: =E58-F58 -> 0
A59: SUBTOTAL DRINKS | E59: =SUM(E52:E58) -> 0 | F59: =SUM(F52:F58) -> 0 | G59: =E59-F59 -> 0
A61: 4. ACTIVITIES | B61: QUANT. | C61: $ CUSTO | D61: $ VENDA | E61: SUBTOTAL | F61: SUBTOTAL $ CUSTO | G61: COMISSÕES
A62: ='BASE PAX'!A37 -> HOTTUBE | B62: ='BASE PAX'!B37 -> 0 | C62: ='BASE PAX'!C37 -> 12000 | D62: =C62*0.2+C62 -> 14400 | E62: =D62*B62 -> 0 | F62: =B62*C62 -> 0 | G62: =E62-F62 -> 0
A63: ='BASE PAX'!A38 -> TREKKING 1/2 DAY | B63: ='BASE PAX'!B38 -> 0 | C63: ='BASE PAX'!C38 -> 60000 | D63: =C63*0.2+C63 -> 72000 | E63: =D63*B63 -> 0 | F63: =B63*C63 -> 0 | G63: =E63-F63 -> 0
A64: ='BASE PAX'!A39 -> TREKKING FUK DAY | B64: ='BASE PAX'!B39 -> 0 | C64: ='BASE PAX'!C39 -> 90000 | D64: =C64*0.2+C64 -> 108000 | E64: =D64*B64 -> 0 | F64: =B64*C64 -> 0 | G64: =E64-F64 -> 0
A65: ='BASE PAX'!A40 -> FLOTADA FAMILIAR | B65: ='BASE PAX'!B40 -> 0 | C65: ='BASE PAX'!C40 -> 60000 | D65: =C65*0.2+C65 -> 72000 | E65: =D65*B65 -> 0 | F65: =B65*C65 -> 0 | G65: =E65-F65 -> 0
A66: ='BASE PAX'!A41 -> RAFTING 1/2 DAY | B66: ='BASE PAX'!B41 -> 0 | C66: ='BASE PAX'!C41 -> 75000 | D66: =C66*0.2+C66 -> 90000 | E66: =D66*B66 -> 0 | F66: =B66*C66 -> 0 | G66: =E66-F66 -> 0
A67: ='BASE PAX'!A42 -> RAFTING FULL DAY | B67: ='BASE PAX'!B42 -> 0 | C67: ='BASE PAX'!C42 -> 110000 | D67: =C67*0.2+C67 -> 132000 | E67: =D67*B67 -> 0 | F67: =B67*C67 -> 0 | G67: =E67-F67 -> 0
A68: ='BASE PAX'!A43 -> CABALGADA 1/2 DAy | B68: ='BASE PAX'!B43 -> 0 | C68: ='BASE PAX'!C43 -> 90000 | D68: =C68*0.2+C68 -> 108000 | E68: =D68*B68 -> 0 | F68: =B68*C68 -> 0 | G68: =E68-F68 -> 0
A69: ='BASE PAX'!A44 -> CABALGADA FULL DAY | B69: ='BASE PAX'!B44 -> 0 | C69: ='BASE PAX'!C44 -> 140000 | D69: =C69*0.2+C69 -> 168000 | E69: =D69*B69 -> 0 | F69: =B69*C69 -> 0 | G69: =E69-F69 -> 0
A70: ='BASE PAX'!A45 -> LANCHA YELCHO | B70: ='BASE PAX'!B45 -> 0 | C70: ='BASE PAX'!C45 -> 120000 | D70: =C70*0.2+C70 -> 144000 | E70: =D70*B70 -> 0 | F70: =B70*C70 -> 0 | G70: =E70-F70 -> 0
A71: ='BASE PAX'!A46 -> RECREACAO INFANTIL 3HS | B71: ='BASE PAX'!B46 -> 0 | C71: ='BASE PAX'!C46 -> 30000 | D71: =C71*0.2+C71 -> 36000 | E71: =D71*B71 -> 0 | F71: =B71*C71 -> 0 | G71: =E71-F71 -> 0
A72: SUBTOTAL ACTIVITIES | E72: =SUM(E62:E71) -> 0 | F72: =B72*C72 -> 0 | G72: =E72-F72 -> 0
A74: 5. TRANSPORT | B74: QUANT. | C74: $ CUSTO | D74: $ VENDA | E74: SUBTOTAL | F74: SUBTOTAL CUSTO | G74: COMISSÕES
A75: ='BASE PAX'!A50 -> TRANSFER AEROPORTO CHEGADA | B75: ='BASE PAX'!B50 -> 0 | C75: ='BASE PAX'!C50 -> 80000 | D75: =C75*0.2+C75 -> 96000 | E75: =D75*B75 -> 0 | F75: =B75*C75 -> 0 | G75: =E75-F75 -> 0
A76: ='BASE PAX'!A51 -> TRANSFER AEROPORTO PARTIDA | B76: ='BASE PAX'!B51 -> 0 | C76: ='BASE PAX'!C51 -> 80000 | D76: =C76*0.2+C76 -> 96000 | E76: =D76*B76 -> 0 | F76: =B76*C76 -> 0 | G76: =E76-F76 -> 0
A77: ='BASE PAX'!A52 -> TRANSFERS INTERNO | B77: ='BASE PAX'!B52 -> 0 | C77: ='BASE PAX'!C52 -> 18000 | D77: =C77*0.2+C77 -> 21600 | E77: =D77*B77 -> 0 | F77: =B77*C77 -> 0 | G77: =E77-F77 -> 0
A78: ='BASE PAX'!A53 -> EXTRAS 1 | B78: ='BASE PAX'!B53 -> 0 | C78: ='BASE PAX'!C53 -> 150000 | D78: =C78*0.2+C78 -> 180000 | E78: =D78*B78 -> 0 | F78: =B78*C78 -> 0 | G78: =E78-F78 -> 0
A79: ='BASE PAX'!A54 -> EXTRAS 2 | B79: ='BASE PAX'!B54 -> 0 | C79: ='BASE PAX'!C54 -> 0 | D79: =C79*0.2+C79 -> 0 | E79: =D79*B79 -> 0 | F79: =B79*C79 -> 0 | G79: =E79-F79 -> 0
A80: SUBTOTAL TRANSPORT | E80: =SUM(E75:E79) -> 0 | F80: =SUM(F75:F79) -> 0 | G80: =E80-F80 -> 0
A82: 6. EXPERIENCES | B82: QUANT. | C82: $ CUSTO | D82: $ VENDA | E82: SUBTOTAL | F82: SUBTOTAL CUSTO | G82: COMISSÕES
A83: ='BASE PAX'!A58 -> WS INSTRUCTOR | B83: ='BASE PAX'!B58 -> 0 | C83: ='BASE PAX'!C58 -> 3415000 | D83: =(C83*0.15)+C83 -> 3927250 | E83: =D83*B83 -> 0 | F83: =B83*C83 -> 0 | G83: =E83-F83 -> 0
A84: ='BASE PAX'!A59 -> PRODUCER FEE | B84: ='BASE PAX'!B59 -> 0 | C84: ='BASE PAX'!C59 -> 180000 | D84: =(C84*0.15)+C84 -> 207000 | E84: =D84*B84 -> 0 | F84: =B84*C84 -> 0 | G84: =E84-F84 -> 0
A85: ='BASE PAX'!A60 -> 0 | B85: ='BASE PAX'!B60 -> 0 | C85: ='BASE PAX'!C60 -> 20000 | D85: =(C85*0.15)+C85 -> 23000 | E85: =D85*B85 -> 0 | F85: =B85*C85 -> 0 | G85: =E85-F85 -> 0
A86: SUBTOTAL EXPERIENCES | E86: =SUM(E83:E85) -> 0 | F86: =SUM(F81:F85) -> 0 | G86: =E86-F86 -> 0
A88: 7. EXTRAS ( por cabin ) | B88: USOS | C88: $ CUSTO | D88: $ VENDA | E88: SUBTOTAL | G88: COMISSÕES
A89: ='BASE PAX'!A64 -> COORDENAÇÃO PRODUÇÃO | B89: ='BASE PAX'!B64 -> 0 | C89: ='BASE PAX'!C64 -> 50000 | D89: ='BASE PAX'!D64 -> 0 | E89: =D89*B89 -> 0 | G89: =E89*0.2 -> 0
A90: ='BASE PAX'!A65 -> EXTRA MÃO DE OBRA | B90: ='BASE PAX'!B65 -> 0 | C90: ='BASE PAX'!C65 -> 50000 | D90: ='BASE PAX'!D65 -> 0 | E90: =D90*B90 -> 0 | G90: =E90*0.2 -> 0
A91: ='BASE PAX'!A66 -> TAXA LIMPEZA CHECK IN / CHECKOUT | B91: ='BASE PAX'!B66 -> 0 | C91: ='BASE PAX'!C66 -> 40000 | D91: ='BASE PAX'!D66 -> 0 | E91: =D91*B91 -> 0 | G91: =E91*0.2 -> 0
A92: ='BASE PAX'!A67 -> TAXA LIMPEZA DIARIA | B92: ='BASE PAX'!B67 -> 0 | C92: ='BASE PAX'!C67 -> 30000 | D92: ='BASE PAX'!D67 -> 0 | E92: =D92*B92 -> 0 | G92: =E92*0.2 -> 0
A93: ='BASE PAX'!A68 -> SOUVENIR | B93: ='BASE PAX'!B68 -> 0 | C93: ='BASE PAX'!C68 -> 15000 | D93: ='BASE PAX'!D68 -> 0 | E93: =D93*B93 -> 0 | G93: =E93*0.2 -> 0
A94: ='BASE PAX'!A69 -> ASSISTENTE COORDENAÇÃO | B94: ='BASE PAX'!B69 -> 0 | C94: ='BASE PAX'!C69 -> 30000 | D94: ='BASE PAX'!D69 -> 0 | E94: =D94*B94 -> 0 | G94: =E94*0.2 -> 0
A95: SUBTOTAL EXTRAS | E95: =SUM(E89:E94) -> 0 | G95: =SUM(G89:G94) -> 0
A97: 8. QUINCHO (por cabin) | B97: USOS | C97: $ CUSTO | D97: $ VENDA | E97: SUBTOTAL
A98: ='BASE PAX'!A73 -> QUINCHO DAY USE / CABIN | B98: ='BASE PAX'!B73 -> 0 | C98: ='BASE PAX'!C73 -> 15000 | D98: =C98+(C98*0.2) -> 18000 | E98: =D98*B98 -> 0
A99: SUBTOTAL QUINCHO | E99: =E98 -> 0

Sheet BUDGET CHAITEN 2+1
C3: COIGUE
A5: TOTAL PAX ADULT | B5: 2 | E5: CHAITEN
A6: TOTAL PAX INFANT | B6: 1 | D6: BUDGET TOTAL | F6: =D21 -> 0
A7: CHECK IN. | B7: =CALENDAR!C2 -> 0 | D7: SUBTOTAL PAGO | F7: =SUM(F12:F20) -> 0
A8: CHECK OUT. | B8: =CALENDAR!C3 -> 0 | D8: SUBTOTAL A RECEBER | F8: =F6-F7 -> 0
A9: TOTAL NIGHTS. | B9: =CALENDAR!J2 -> 0 | D9: TIP |
A11: RESUMO. | B11: PREÇO CLIENTE CASH CLP $ | C11: TAXA CC | D11: PREÇO CLIENTE PAGTO CC $ | F11: =E5 -> CHAITEN | I11: CONTROLE PAGAMENTOS
C12: 0.05 | I12: DATA | J12: VALOR PAGO CLP $ | K12: FORMA PAGTO
A13: 1.LODGING | B13: =G28 -> 0 | C13: =B13*$C$12 -> 0 | D13: =B13+(B13*$C$12) -> 0
A14: 2.FOOD | B14: =J49 -> 0 | C14: =B14*$C$12 -> 0 | D14: =B14+(B14*$C$12) -> 0 | F14: =A14 -> 2.FOOD | G14: =G49 -> 0
A15: 3.DRINKS | B15: =E59 -> 0 | C15: =B15*$C$12 -> 0 | D15: =B15+(B15*$C$12) -> 0 | F15: =A15 -> 3.DRINKS | G15: =G59 -> 0
A16: 4. ACTIVITIES | B16: =$E$72 -> 0 | C16: =B16*$C$12 -> 0 | D16: =B16+(B16*$C$12) -> 0 | F16: =A16 -> 4. ACTIVITIES | G16: =G72 -> 0
A17: 5.TRANSPORT | B17: =$E$80 -> 0 | C17: =B17*$C$12 -> 0 | D17: =B17+(B17*$C$12) -> 0 | F17: =A17 -> 5.TRANSPORT | G17: =G80 -> 0
A18: 6.EXPERIENCES | B18: =$E$86 -> 0 | C18: =B18*$C$12 -> 0 | D18: =B18+(B18*$C$12) -> 0 | F18: =A18 -> 6.EXPERIENCES | G18: =G86 -> 0
A19: 7.EXTRAS | B19: =$E$95 -> 0 | C19: =B19*$C$12 -> 0 | D19: =B19+(B19*$C$12) -> 0 | F19: =A19 -> 7.EXTRAS | G19: =G95 -> 0
A20: 8. QUINCHO | B20: =$E$99 -> 0 | C20: =B20*$C$12 -> 0 | D20: =B20+(B20*$C$12) -> 0 | F20: SUBTOTAL COMISSÕES | G20: =G14+G15+G16+G17+G18+G19 -> 0
A21: SUBTOTAL 1 | B21: =SUM(B13:B20) -> 0 | D21: =SUM(D13:D20) -> 0
A23: 1. LODGING | B23: QUANT. | C23: $ CABIN / DIA | D23: $ ADICIONAL / DIA | E23: BASE CÁLCULO | F23: DESCONTOS | G23: $ SUBTOTAL
A24: CHAITEN (até 2 pax) - até 06 noites | B24: 0 | C24: =288190.9 -> 288190.9 | E24: =(C24+D24)*$B$9*B24 -> 0 | F24: 0 | G24: =E24-(E24*F24) -> 0
A25: CHAITEN ( 2 + baby) - até 06 noites | B25: 1 | C25: =288190.9 -> 288190.9 | D25: 50000 | E25: =(C25+D25)*$B$9*B25 -> 0 | F25: 0 | G25: =E25-(E25*F25) -> 0
A26: CHAITEN (até 2 pax) - 7 noites ou + | B26: 0 | C26: =259371.81 -> 259371.81 | E26: =(C26+D26)*$B$9*B26 -> 0 | F26: 0 | G26: =E26-(E26*F26) -> 0
A27: CHAITEN ( 2 + baby) - 7 noites ou + | B27: 0 | C27: =259371.81 -> 259371.81 | D27: 50000 | E27: =(C27+D27)*$B$9*B27 -> 0 | F27: 0 | G27: =E27-(E27*F27) -> 0
A28: SUBTOTAL LODGING | G28: =SUM(G24:G27) -> 0
A30: 2. FOOD | B30: QUANT. | C30: $ CUSTO | D30: $ VENDA | E30: SUBTOTAL $ VENDA | F30: SUBTOTAL $ CUSTO | G30: COMISSÕES
A31: ='BASE PAX'!A6 -> BREAKFAST | B31: =(B5*B9*'BASE PAX'!G6)+('BASE PAX'!H6*B6*B9) -> 0 | F31: =B31*C31 -> 0 | G31: =0.2*B31 -> 0 | H31: ='BASE PAX'!A6 -> BREAKFAST | I31: =B31 -> 0
A32: ='BASE PAX'!A7 -> LUNCH 1 | B32: =($B$5+($B$6*0.5))*'BASE PAX'!B7 -> 0 | C32: ='BASE PAX'!C7 -> 40000 | D32: ='BASE PAX'!D7 -> 48000 | E32: =D32*B32 -> 0 | F32: =B32*C32 -> 0 | G32: =E32-F32 -> 0
A33: ='BASE PAX'!A8 -> LUNCH 2 | B33: =($B$5+($B$6*0.5))*'BASE PAX'!B8 -> 0 | C33: ='BASE PAX'!C8 -> 40000 | D33: ='BASE PAX'!D8 -> 48000 | E33: =D33*B33 -> 0 | F33: =B33*C33 -> 0 | G33: =E33-F33 -> 0
A34: ='BASE PAX'!A9 -> LUNCH 3 | B34: =($B$5+($B$6*0.5))*'BASE PAX'!B9 -> 0 | C34: ='BASE PAX'!C9 -> 40000 | D34: ='BASE PAX'!D9 -> 48000 | E34: =D34*B34 -> 0 | F34: =B34*C34 -> 0 | G34: =E34-F34 -> 0
A35: ='BASE PAX'!A10 -> LUNCH 4 | B35: =($B$5+($B$6*0.5))*'BASE PAX'!B10 -> 0 | C35: ='BASE PAX'!C10 -> 45000 | D35: ='BASE PAX'!D10 -> 54000 | E35: =D35*B35 -> 0 | F35: =B35*C35 -> 0 | G35: =E35-F35 -> 0
A36: ='BASE PAX'!A11 -> LUNCH 5 | B36: =($B$5+($B$6*0.6))*'BASE PAX'!B11 -> 0 | C36: ='BASE PAX'!C11 -> 50000 | D36: ='BASE PAX'!D11 -> 60000 | E36: =D36*B36 -> 0 | F36: =B36*C36 -> 0 | G36: =E36-F36 -> 0
A37: ='BASE PAX'!A12 -> LUNCH 6 | B37: =($B$5+($B$6*0.5))*'BASE PAX'!B12 -> 0 | C37: ='BASE PAX'!C12 -> 0 | D37: ='BASE PAX'!D12 -> 0 | E37: =D37*B37 -> 0 | F37: =B37*C37 -> 0 | G37: =E37-F37 -> 0
A38: ='BASE PAX'!A13 -> LUNCH 7 | B38: =($B$5+($B$6*0.5))*'BASE PAX'!B13 -> 0 | C38: ='BASE PAX'!C13 -> 5000 | D38: ='BASE PAX'!D13 -> 6000 | E38: =D38*B38 -> 0 | F38: =B38*C38 -> 0 | G38: =E38-F38 -> 0
A39: ='BASE PAX'!A14 -> SNACKS | B39: =($B$5+$B$6)*'BASE PAX'!B14 -> 0 | C39: ='BASE PAX'!C14 -> 8000 | D39: ='BASE PAX'!D14 -> 9600 | E39: =D39*B39 -> 0 | F39: =B39*C39 -> 0 | G39: =E39-F39 -> 0
A40: ='BASE PAX'!A15 -> DINNER 1 | B40: =($B$5+($B$6*0.6))*'BASE PAX'!B15 -> 0 | C40: ='BASE PAX'!C15 -> 70000 | D40: ='BASE PAX'!D15 -> 84000 | E40: =D40*B40 -> 0 | F40: =B40*C40 -> 0 | G40: =E40-F40 -> 0
A41: ='BASE PAX'!A16 -> DINNER 2 | B41: =($B$5+($B$6*0.6))*'BASE PAX'!B16 -> 0 | C41: ='BASE PAX'!C16 -> 25000 | D41: ='BASE PAX'!D16 -> 30000 | E41: =D41*B41 -> 0 | F41: =B41*C41 -> 0 | G41: =E41-F41 -> 0
A42: ='BASE PAX'!A17 -> DINNER 3 | B42: =($B$5+($B$6*0.6))*'BASE PAX'!B17 -> 0 | C42: ='BASE PAX'!C17 -> 50000 | D42: ='BASE PAX'!D17 -> 60000 | E42: =D42*B42 -> 0 | F42: =B42*C42 -> 0 | G42: =E42-F42 -> 0
A43: ='BASE PAX'!A18 -> DINNER 4 | B43: =($B$5+($B$6*0.5))*'BASE PAX'!B18 -> 0 | C43: ='BASE PAX'!C18 -> 65000 | D43: ='BASE PAX'!D18 -> 78000 | E43: =D43*B43 -> 0 | F43: =B43*C43 -> 0 | G43: =E43-F43 -> 0
A44: ='BASE PAX'!A19 -> DINNER 5 | B44: =($B$5+($B$6*0.6))*'BASE PAX'!B19 -> 0 | C44: ='BASE PAX'!C19 -> 75000 | D44: ='BASE PAX'!D19 -> 90000 | E44: =D44*B44 -> 0 | F44: =B44*C44 -> 0 | G44: =E44-F44 -> 0
A45: ='BASE PAX'!A20 -> DINNER 6 | B45: =($B$5+($B$6*0.5))*'BASE PAX'!B20 -> 0 | C45: ='BASE PAX'!C20 -> 0 | D45: ='BASE PAX'!D20 -> 0 | E45: =D45*B45 -> 0 | F45: =B45*C45 -> 0 | G45: =E45-F45 -> 0
A46: ='BASE PAX'!A21 -> DINNER 7 | B46: =($B$5+($B$6*0.6))*'BASE PAX'!B21 -> 0 | C46: ='BASE PAX'!C21 -> 75000 | D46: ='BASE PAX'!D21 -> 90000 | E46: =D46*B46 -> 0 | F46: =B46*C46 -> 0 | G46: =E46-F46 -> 0
A47: ='BASE PAX'!A22 -> QUANT. TOTAL | PADRAO ALMOÇO | B47: ='BASE PAX'!B22 -> 0 | G47: =0.2*I47 -> 0 | H47: ='BASE PAX'!A22 -> QUANT. TOTAL | PADRAO ALMOÇO | I47: =(B5*B47*'BASE PAX'!G22)+(B6*B47*'BASE PAX'!H22) -> 0
A48: ='BASE PAX'!A23 -> QUANT. TOTAL | PADRAO JANTAR | B48: ='BASE PAX'!B23 -> 0 | G48: =0.2*I48 -> 0 | H48: ='BASE PAX'!A23 -> QUANT. TOTAL | PADRAO JANTAR | I48: =(B5*B48*'BASE PAX'!G23)+(B6*B48*'BASE PAX'!H23) -> 0
A49: SUBTOTAL FOOD | E49: =SUM(E31:E48) -> 0 | F49: =SUM(F31:F48) -> 0 | G49: =SUM(G31:G48) -> 0 | H49: SUBTOTAL | I49: =I31+I47+I48 -> 0 | J49: =I49+E49 -> 0 | K49: TOTAL FOOD
A51: 3. DRINKS (por cabin) | B51: QUANT. | C51: $ CUSTO | D51: $ VENDA | E51: SUBTOTAL | F51: SUBTOTAL $ CUSTO | G51: COMISSÕES
A52: ='BASE PAX'!A27 -> SUCOS | B52: ='BASE PAX'!B27 -> 0 | C52: ='BASE PAX'!C27 -> 0 | D52: =(C52*0.2)+C52 -> 0 | E52: =D52*B52 -> 0 | F52: =B52*C52 -> 0 | G52: =E52-F52 -> 0
A53: ='BASE PAX'!A28 -> SUCOS | B53: ='BASE PAX'!B28 -> 0 | C53: ='BASE PAX'!C28 -> 0 | D53: =(C53*0.2)+C53 -> 0 | E53: =D53*B53 -> 0 | F53: =B53*C53 -> 0 | G53: =E53-F53 -> 0
A54: ='BASE PAX'!A29 -> CERVEJAS | B54: ='BASE PAX'!B29 -> 0 | C54: ='BASE PAX'!C29 -> 2000 | D54: =(C54*0.2)+C54 -> 2400 | E54: =D54*B54 -> 0 | F54: =B54*C54 -> 0 | G54: =E54-F54 -> 0
A55: ='BASE PAX'!A30 -> VINHOS | B55: ='BASE PAX'!B30 -> 0 | C55: ='BASE PAX'!C30 -> 8000 | D55: =(C55*0.2)+C55 -> 9600 | E55: =D55*B55 -> 0 | F55: =B55*C55 -> 0 | G55: =E55-F55 -> 0
A56: ='BASE PAX'!A31 -> DRINKS | B56: ='BASE PAX'!B31 -> 0 | C56: ='BASE PAX'!C31 -> 15000 | D56: =(C56*0.2)+C56 -> 18000 | E56: =D56*B56 -> 0 | F56: =B56*C56 -> 0 | G56: =E56-F56 -> 0
A57: ='BASE PAX'!A32 -> COOLER | B57: ='BASE PAX'!B32 -> 0 | C57: ='BASE PAX'!C32 -> 5000 | D57: =(C57*0.2)+C57 -> 6000 | E57: =D57*B57 -> 0 | F57: =B57*C57 -> 0 | G57: =E57-F57 -> 0
A58: ='BASE PAX'!A33 -> 0 | B58: ='BASE PAX'!B33 -> 0 | C58: ='BASE PAX'!C33 -> 0 | D58: =(C58*0.2)+C58 -> 0 | E58: =D58*B58 -> 0 | F58: =B58*C58 -> 0 | G58: =E58-F58 -> 0
A59: SUBTOTAL DRINKS | E59: =SUM(E52:E58) -> 0 | F59: =SUM(F52:F58) -> 0 | G59: =E59-F59 -> 0
A61: 4. ACTIVITIES | B61: QUANT. | C61: $ CUSTO | D61: $ VENDA | E61: SUBTOTAL | F61: SUBTOTAL $ CUSTO | G61: COMISSÕES
A62: ='BASE PAX'!A37 -> HOTTUBE | B62: ='BASE PAX'!B37 -> 0 | C62: ='BASE PAX'!C37 -> 12000 | D62: =C62*0.2+C62 -> 14400 | E62: =D62*B62 -> 0 | F62: =B62*C62 -> 0 | G62: =E62-F62 -> 0
A63: ='BASE PAX'!A38 -> TREKKING 1/2 DAY | B63: ='BASE PAX'!B38 -> 0 | C63: ='BASE PAX'!C38 -> 60000 | D63: =C63*0.2+C63 -> 72000 | E63: =D63*B63 -> 0 | F63: =B63*C63 -> 0 | G63: =E63-F63 -> 0
A64: ='BASE PAX'!A39 -> TREKKING FUK DAY | B64: ='BASE PAX'!B39 -> 0 | C64: ='BASE PAX'!C39 -> 90000 | D64: =C64*0.2+C64 -> 108000 | E64: =D64*B64 -> 0 | F64: =B64*C64 -> 0 | G64: =E64-F64 -> 0
A65: ='BASE PAX'!A40 -> FLOTADA FAMILIAR | B65: ='BASE PAX'!B40 -> 0 | C65: ='BASE PAX'!C40 -> 60000 | D65: =C65*0.2+C65 -> 72000 | E65: =D65*B65 -> 0 | F65: =B65*C65 -> 0 | G65: =E65-F65 -> 0
A66: ='BASE PAX'!A41 -> RAFTING 1/2 DAY | B66: ='BASE PAX'!B41 -> 0 | C66: ='BASE PAX'!C41 -> 75000 | D66: =C66*0.2+C66 -> 90000 | E66: =D66*B66 -> 0 | F66: =B66*C66 -> 0 | G66: =E66-F66 -> 0
A67: ='BASE PAX'!A42 -> RAFTING FULL DAY | B67: ='BASE PAX'!B42 -> 0 | C67: ='BASE PAX'!C42 -> 110000 | D67: =C67*0.2+C67 -> 132000 | E67: =D67*B67 -> 0 | F67: =B67*C67 -> 0 | G67: =E67-F67 -> 0
A68: ='BASE PAX'!A43 -> CABALGADA 1/2 DAy | B68: ='BASE PAX'!B43 -> 0 | C68: ='BASE PAX'!C43 -> 90000 | D68: =C68*0.2+C68 -> 108000 | E68: =D68*B68 -> 0 | F68: =B68*C68 -> 0 | G68: =E68-F68 -> 0
A69: ='BASE PAX'!A44 -> CABALGADA FULL DAY | B69: ='BASE PAX'!B44 -> 0 | C69: ='BASE PAX'!C44 -> 140000 | D69: =C69*0.2+C69 -> 168000 | E69: =D69*B69 -> 0 | F69: =B69*C69 -> 0 | G69: =E69-F69 -> 0
A70: ='BASE PAX'!A45 -> LANCHA YELCHO | B70: ='BASE PAX'!B45 -> 0 | C70: ='BASE PAX'!C45 -> 120000 | D70: =C70*0.2+C70 -> 144000 | E70: =D70*B70 -> 0 | F70: =B70*C70 -> 0 | G70: =E70-F70 -> 0
A71: ='BASE PAX'!A46 -> RECREACAO INFANTIL 3HS | B71: ='BASE PAX'!B46 -> 0 | C71: ='BASE PAX'!C46 -> 30000 | D71: =C71*0.2+C71 -> 36000 | E71: =D71*B71 -> 0 | F71: =B71*C71 -> 0 | G71: =E71-F71 -> 0
A72: SUBTOTAL ACTIVITIES | E72: =SUM(E62:E71) -> 0 | F72: =B72*C72 -> 0 | G72: =E72-F72 -> 0
A74: 5. TRANSPORT | B74: QUANT. | C74: $ CUSTO | D74: $ VENDA | E74: SUBTOTAL | F74: SUBTOTAL CUSTO | G74: COMISSÕES
A75: ='BASE PAX'!A50 -> TRANSFER AEROPORTO CHEGADA | B75: ='BASE PAX'!B50 -> 0 | C75: 50000 | D75: =C75*0.2+C75 -> 60000 | E75: =D75*B75 -> 0 | F75: =B75*C75 -> 0 | G75: =E75-F75 -> 0
A76: ='BASE PAX'!A51 -> TRANSFER AEROPORTO PARTIDA | B76: ='BASE PAX'!B51 -> 0 | C76: ='BASE PAX'!C51 -> 80000 | D76: =C76*0.2+C76 -> 96000 | E76: =D76*B76 -> 0 | F76: =B76*C76 -> 0 | G76: =E76-F76 -> 0
A77: ='BASE PAX'!A52 -> TRANSFERS INTERNO | B77: ='BASE PAX'!B52 -> 0 | C77: ='BASE PAX'!C52 -> 18000 | D77: =C77*0.2+C77 -> 21600 | E77: =D77*B77 -> 0 | F77: =B77*C77 -> 0 | G77: =E77-F77 -> 0
A78: ='BASE PAX'!A53 -> EXTRAS 1 | B78: ='BASE PAX'!B53 -> 0 | C78: ='BASE PAX'!C53 -> 150000 | D78: =C78*0.2+C78 -> 180000 | E78: =D78*B78 -> 0 | F78: =B78*C78 -> 0 | G78: =E78-F78 -> 0
A79: ='BASE PAX'!A54 -> EXTRAS 2 | B79: ='BASE PAX'!B54 -> 0 | C79: ='BASE PAX'!C54 -> 0 | D79: =C79*0.2+C79 -> 0 | E79: =D79*B79 -> 0 | F79: =B79*C79 -> 0 | G79: =E79-F79 -> 0
A80: SUBTOTAL TRANSPORT | E80: =SUM(E75:E79) -> 0 | F80: =SUM(F75:F79) -> 0 | G80: =E80-F80 -> 0
A82: 6. EXPERIENCES | B82: QUANT. | C82: $ CUSTO | D82: $ VENDA | E82: SUBTOTAL | F82: SUBTOTAL CUSTO | G82: COMISSÕES
A83: ='BASE PAX'!A58 -> WS INSTRUCTOR | B83: ='BASE PAX'!B58 -> 0 | C83: ='BASE PAX'!C58 -> 3415000 | D83: =(C83*0.15)+C83 -> 3927250 | E83: =D83*B83 -> 0 | F83: =B83*C83 -> 0 | G83: =E83-F83 -> 0
A84: ='BASE PAX'!A59 -> PRODUCER FEE | B84: ='BASE PAX'!B59 -> 0 | C84: ='BASE PAX'!C59 -> 180000 | D84: =(C84*0.15)+C84 -> 207000 | E84: =D84*B84 -> 0 | F84: =B84*C84 -> 0 | G84: =E84-F84 -> 0
A85: ='BASE PAX'!A60 -> 0 | B85: ='BASE PAX'!B60 -> 0 | C85: ='BASE PAX'!C60 -> 20000 | D85: =(C85*0.15)+C85 -> 23000 | E85: =D85*B85 -> 0 | F85: =B85*C85 -> 0 | G85: =E85-F85 -> 0
A86: SUBTOTAL EXPERIENCES | E86: =SUM(E83:E85) -> 0 | F86: =SUM(F81:F85) -> 0 | G86: =E86-F86 -> 0
A88: 7. EXTRAS ( por cabin ) | B88: USOS | C88: $ CUSTO | D88: $ VENDA | E88: SUBTOTAL | G88: COMISSÕES
A89: ='BASE PAX'!A64 -> COORDENAÇÃO PRODUÇÃO | B89: ='BASE PAX'!B64 -> 0 | C89: ='BASE PAX'!C64 -> 50000 | D89: ='BASE PAX'!D64 -> 0 | E89: =D89*B89 -> 0 | G89: =E89*0.2 -> 0
A90: ='BASE PAX'!A65 -> EXTRA MÃO DE OBRA | B90: ='BASE PAX'!B65 -> 0 | C90: ='BASE PAX'!C65 -> 50000 | D90: ='BASE PAX'!D65 -> 0 | E90: =D90*B90 -> 0 | G90: =E90*0.2 -> 0
A91: ='BASE PAX'!A66 -> TAXA LIMPEZA CHECK IN / CHECKOUT | B91: ='BASE PAX'!B66 -> 0 | C91: ='BASE PAX'!C66 -> 40000 | D91: ='BASE PAX'!D66 -> 0 | E91: =D91*B91 -> 0 | G91: =E91*0.2 -> 0
A92: ='BASE PAX'!A67 -> TAXA LIMPEZA DIARIA | B92: ='BASE PAX'!B67 -> 0 | C92: ='BASE PAX'!C67 -> 30000 | D92: ='BASE PAX'!D67 -> 0 | E92: =D92*B92 -> 0 | G92: =E92*0.2 -> 0
A93: ='BASE PAX'!A68 -> SOUVENIR | B93: ='BASE PAX'!B68 -> 0 | C93: ='BASE PAX'!C68 -> 15000 | D93: ='BASE PAX'!D68 -> 0 | E93: =D93*B93 -> 0 | G93: =E93*0.2 -> 0
A94: ='BASE PAX'!A69 -> ASSISTENTE COORDENAÇÃO | B94: ='BASE PAX'!B69 -> 0 | C94: ='BASE PAX'!C69 -> 30000 | D94: ='BASE PAX'!D69 -> 0 | E94: =D94*B94 -> 0 | G94: =E94*0.2 -> 0
A95: SUBTOTAL EXTRAS | E95: =SUM(E89:E94) -> 0 | G95: =SUM(G89:G94) -> 0
A97: 8. QUINCHO (por cabin) | B97: USOS | C97: $ CUSTO | D97: $ VENDA | E97: SUBTOTAL
A98: ='BASE PAX'!A73 -> QUINCHO DAY USE / CABIN | B98: ='BASE PAX'!B73 -> 0 | C98: ='BASE PAX'!C73 -> 15000 | D98: =C98+(C98*0.2) -> 18000 | E98: =D98*B98 -> 0
A99: SUBTOTAL QUINCHO | E99: =E98 -> 0

Sheet BUDGET CHAITEN 2+2
C3: COIGUE
A5: TOTAL PAX ADULT | B5: 2 | E5: CHAITEN
A6: TOTAL PAX INFANT | B6: 2 | D6: BUDGET TOTAL | F6: =D21 -> 0
A7: CHECK IN. | B7: =CALENDAR!C2 -> 0 | D7: SUBTOTAL PAGO | F7: =SUM(F12:F20) -> 0
A8: CHECK OUT. | B8: =CALENDAR!C3 -> 0 | D8: SUBTOTAL A RECEBER | F8: =F6-F7 -> 0
A9: TOTAL NIGHTS. | B9: =CALENDAR!J2 -> 0 | D9: TIP |
A11: RESUMO. | B11: PREÇO CLIENTE CASH CLP $ | C11: TAXA CC | D11: PREÇO CLIENTE PAGTO CC $ | F11: =E5 -> CHAITEN | I11: CONTROLE PAGAMENTOS
C12: 0.05 | I12: DATA | J12: VALOR PAGO CLP $ | K12: FORMA PAGTO
A13: 1.LODGING | B13: =G28 -> 0 | C13: =B13*$C$12 -> 0 | D13: =B13+(B13*$C$12) -> 0
A14: 2.FOOD | B14: =J49 -> 0 | C14: =B14*$C$12 -> 0 | D14: =B14+(B14*$C$12) -> 0 | F14: =A14 -> 2.FOOD | G14: =G49 -> 0
A15: 3.DRINKS | B15: =E59 -> 0 | C15: =B15*$C$12 -> 0 | D15: =B15+(B15*$C$12) -> 0 | F15: =A15 -> 3.DRINKS | G15: =G59 -> 0
A16: 4. ACTIVITIES | B16: =$E$72 -> 0 | C16: =B16*$C$12 -> 0 | D16: =B16+(B16*$C$12) -> 0 | F16: =A16 -> 4. ACTIVITIES | G16: =G72 -> 0
A17: 5.TRANSPORT | B17: =$E$80 -> 0 | C17: =B17*$C$12 -> 0 | D17: =B17+(B17*$C$12) -> 0 | F17: =A17 -> 5.TRANSPORT | G17: =G80 -> 0
A18: 6.EXPERIENCES | B18: =$E$86 -> 0 | C18: =B18*$C$12 -> 0 | D18: =B18+(B18*$C$12) -> 0 | F18: =A18 -> 6.EXPERIENCES | G18: =G86 -> 0
A19: 7.EXTRAS | B19: =$E$95 -> 0 | C19: =B19*$C$12 -> 0 | D19: =B19+(B19*$C$12) -> 0 | F19: =A19 -> 7.EXTRAS | G19: =G95 -> 0
A20: 8. QUINCHO | B20: =$E$99 -> 0 | C20: =B20*$C$12 -> 0 | D20: =B20+(B20*$C$12) -> 0 | F20: SUBTOTAL COMISSÕES | G20: =G14+G15+G16+G17+G18+G19 -> 0
A21: SUBTOTAL 1 | B21: =SUM(B13:B20) -> 0 | D21: =SUM(D13:D20) -> 0
A23: 1. LODGING | B23: QUANT. | C23: $ CABIN / DIA | D23: $ ADICIONAL / DIA | E23: BASE CÁLCULO | F23: DESCONTOS | G23: $ SUBTOTAL
A24: CHAITEN (até 2 pax) - até 06 noites | B24: 0 | C24: =288190.9 -> 288190.9 | E24: =(C24+D24)*$B$9*B24 -> 0 | F24: 0 | G24: =E24-(E24*F24) -> 0
A25: CHAITEN ( 2 + baby) - até 06 noites | B25: 1 | C25: =288190.9 -> 288190.9 | D25: =$B$6*50000 -> 100000 | E25: =(C25+D25)*$B$9*B25 -> 0 | F25: 0 | G25: =E25-(E25*F25) -> 0
A26: CHAITEN (até 2 pax) - 7 noites ou + | B26: 0 | C26: =259371.81 -> 259371.81 | E26: =(C26+D26)*$B$9*B26 -> 0 | F26: 0 | G26: =E26-(E26*F26) -> 0
A27: CHAITEN ( 2 + baby) - 7 noites ou + | B27: 0 | C27: =259371.81 -> 259371.81 | D27: 50000 | E27: =(C27+D27)*$B$9*B27 -> 0 | F27: 0 | G27: =E27-(E27*F27) -> 0
A28: SUBTOTAL LODGING | G28: =SUM(G24:G27) -> 0
A30: 2. FOOD | B30: QUANT. | C30: $ CUSTO | D30: $ VENDA | E30: SUBTOTAL $ VENDA | F30: SUBTOTAL $ CUSTO | G30: COMISSÕES
A31: ='BASE PAX'!A6 -> BREAKFAST | B31: =(B5*B9*'BASE PAX'!G6)+('BASE PAX'!H6*B6*B9) -> 0 | F31: =B31*C31 -> 0 | G31: =0.2*B31 -> 0 | H31: ='BASE PAX'!A6 -> BREAKFAST | I31: =B31 -> 0
A32: ='BASE PAX'!A7 -> LUNCH 1 | B32: =($B$5+($B$6*0.5))*'BASE PAX'!B7 -> 0 | C32: ='BASE PAX'!C7 -> 40000 | D32: ='BASE PAX'!D7 -> 48000 | E32: =D32*B32 -> 0 | F32: =B32*C32 -> 0 | G32: =E32-F32 -> 0
A33: ='BASE PAX'!A8 -> LUNCH 2 | B33: =($B$5+($B$6*0.5))*'BASE PAX'!B8 -> 0 | C33: ='BASE PAX'!C8 -> 40000 | D33: ='BASE PAX'!D8 -> 48000 | E33: =D33*B33 -> 0 | F33: =B33*C33 -> 0 | G33: =E33-F33 -> 0
A34: ='BASE PAX'!A9 -> LUNCH 3 | B34: =($B$5+($B$6*0.5))*'BASE PAX'!B9 -> 0 | C34: ='BASE PAX'!C9 -> 40000 | D34: ='BASE PAX'!D9 -> 48000 | E34: =D34*B34 -> 0 | F34: =B34*C34 -> 0 | G34: =E34-F34 -> 0
A35: ='BASE PAX'!A10 -> LUNCH 4 | B35: =($B$5+($B$6*0.5))*'BASE PAX'!B10 -> 0 | C35: ='BASE PAX'!C10 -> 45000 | D35: ='BASE PAX'!D10 -> 54000 | E35: =D35*B35 -> 0 | F35: =B35*C35 -> 0 | G35: =E35-F35 -> 0
A36: ='BASE PAX'!A11 -> LUNCH 5 | B36: =($B$5+($B$6*0.6))*'BASE PAX'!B11 -> 0 | C36: ='BASE PAX'!C11 -> 50000 | D36: ='BASE PAX'!D11 -> 60000 | E36: =D36*B36 -> 0 | F36: =B36*C36 -> 0 | G36: =E36-F36 -> 0
A37: ='BASE PAX'!A12 -> LUNCH 6 | B37: =($B$5+($B$6*0.5))*'BASE PAX'!B12 -> 0 | C37: ='BASE PAX'!C12 -> 0 | D37: ='BASE PAX'!D12 -> 0 | E37: =D37*B37 -> 0 | F37: =B37*C37 -> 0 | G37: =E37-F37 -> 0
A38: ='BASE PAX'!A13 -> LUNCH 7 | B38: =($B$5+($B$6*0.5))*'BASE PAX'!B13 -> 0 | C38: ='BASE PAX'!C13 -> 5000 | D38: ='BASE PAX'!D13 -> 6000 | E38: =D38*B38 -> 0 | F38: =B38*C38 -> 0 | G38: =E38-F38 -> 0
A39: ='BASE PAX'!A14 -> SNACKS | B39: =($B$5+$B$6)*'BASE PAX'!B14 -> 0 | C39: ='BASE PAX'!C14 -> 8000 | D39: ='BASE PAX'!D14 -> 9600 | E39: =D39*B39 -> 0 | F39: =B39*C39 -> 0 | G39: =E39-F39 -> 0
A40: ='BASE PAX'!A15 -> DINNER 1 | B40: =($B$5+($B$6*0.6))*'BASE PAX'!B15 -> 0 | C40: ='BASE PAX'!C15 -> 70000 | D40: ='BASE PAX'!D15 -> 84000 | E40: =D40*B40 -> 0 | F40: =B40*C40 -> 0 | G40: =E40-F40 -> 0
A41: ='BASE PAX'!A16 -> DINNER 2 | B41: =($B$5+($B$6*0.6))*'BASE PAX'!B16 -> 0 | C41: ='BASE PAX'!C16 -> 25000 | D41: ='BASE PAX'!D16 -> 30000 | E41: =D41*B41 -> 0 | F41: =B41*C41 -> 0 | G41: =E41-F41 -> 0
A42: ='BASE PAX'!A17 -> DINNER 3 | B42: =($B$5+($B$6*0.6))*'BASE PAX'!B17 -> 0 | C42: ='BASE PAX'!C17 -> 50000 | D42: ='BASE PAX'!D17 -> 60000 | E42: =D42*B42 -> 0 | F42: =B42*C42 -> 0 | G42: =E42-F42 -> 0
A43: ='BASE PAX'!A18 -> DINNER 4 | B43: =($B$5+($B$6*0.5))*'BASE PAX'!B18 -> 0 | C43: ='BASE PAX'!C18 -> 65000 | D43: ='BASE PAX'!D18 -> 78000 | E43: =D43*B43 -> 0 | F43: =B43*C43 -> 0 | G43: =E43-F43 -> 0
A44: ='BASE PAX'!A19 -> DINNER 5 | B44: =($B$5+($B$6*0.6))*'BASE PAX'!B19 -> 0 | C44: ='BASE PAX'!C19 -> 75000 | D44: ='BASE PAX'!D19 -> 90000 | E44: =D44*B44 -> 0 | F44: =B44*C44 -> 0 | G44: =E44-F44 -> 0
A45: ='BASE PAX'!A20 -> DINNER 6 | B45: =($B$5+($B$6*0.5))*'BASE PAX'!B20 -> 0 | C45: ='BASE PAX'!C20 -> 0 | D45: ='BASE PAX'!D20 -> 0 | E45: =D45*B45 -> 0 | F45: =B45*C45 -> 0 | G45: =E45-F45 -> 0
A46: ='BASE PAX'!A21 -> DINNER 7 | B46: =($B$5+($B$6*0.6))*'BASE PAX'!B21 -> 0 | C46: ='BASE PAX'!C21 -> 75000 | D46: ='BASE PAX'!D21 -> 90000 | E46: =D46*B46 -> 0 | F46: =B46*C46 -> 0 | G46: =E46-F46 -> 0
A47: ='BASE PAX'!A22 -> QUANT. TOTAL | PADRAO ALMOÇO | B47: ='BASE PAX'!B22 -> 0 | G47: =0.2*I47 -> 0 | H47: ='BASE PAX'!A22 -> QUANT. TOTAL | PADRAO ALMOÇO | I47: =(B5*B47*'BASE PAX'!G22)+(B6*B47*'BASE PAX'!H22) -> 0
A48: ='BASE PAX'!A23 -> QUANT. TOTAL | PADRAO JANTAR | B48: ='BASE PAX'!B23 -> 0 | G48: =0.2*I48 -> 0 | H48: ='BASE PAX'!A23 -> QUANT. TOTAL | PADRAO JANTAR | I48: =(B5*B48*'BASE PAX'!G23)+(B6*B48*'BASE PAX'!H23) -> 0
A49: SUBTOTAL FOOD | E49: =SUM(E31:E48) -> 0 | F49: =SUM(F31:F48) -> 0 | G49: =SUM(G31:G48) -> 0 | H49: SUBTOTAL | I49: =I31+I47+I48 -> 0 | J49: =I49+E49 -> 0 | K49: TOTAL FOOD
A51: 3. DRINKS (por cabin) | B51: QUANT. | C51: $ CUSTO | D51: $ VENDA | E51: SUBTOTAL | F51: SUBTOTAL $ CUSTO | G51: COMISSÕES
A52: ='BASE PAX'!A27 -> SUCOS | B52: ='BASE PAX'!B27 -> 0 | C52: ='BASE PAX'!C27 -> 0 | D52: =(C52*0.2)+C52 -> 0 | E52: =D52*B52 -> 0 | F52: =B52*C52 -> 0 | G52: =E52-F52 -> 0
A53: ='BASE PAX'!A28 -> SUCOS | B53: ='BASE PAX'!B28 -> 0 | C53: ='BASE PAX'!C28 -> 0 | D53: =(C53*0.2)+C53 -> 0 | E53: =D53*B53 -> 0 | F53: =B53*C53 -> 0 | G53: =E53-F53 -> 0
A54: ='BASE PAX'!A29 -> CERVEJAS | B54: ='BASE PAX'!B29 -> 0 | C54: ='BASE PAX'!C29 -> 2000 | D54: =(C54*0.2)+C54 -> 2400 | E54: =D54*B54 -> 0 | F54: =B54*C54 -> 0 | G54: =E54-F54 -> 0
A55: ='BASE PAX'!A30 -> VINHOS | B55: ='BASE PAX'!B30 -> 0 | C55: ='BASE PAX'!C30 -> 8000 | D55: =(C55*0.2)+C55 -> 9600 | E55: =D55*B55 -> 0 | F55: =B55*C55 -> 0 | G55: =E55-F55 -> 0
A56: ='BASE PAX'!A31 -> DRINKS | B56: ='BASE PAX'!B31 -> 0 | C56: ='BASE PAX'!C31 -> 15000 | D56: =(C56*0.2)+C56 -> 18000 | E56: =D56*B56 -> 0 | F56: =B56*C56 -> 0 | G56: =E56-F56 -> 0
A57: ='BASE PAX'!A32 -> COOLER | B57: ='BASE PAX'!B32 -> 0 | C57: ='BASE PAX'!C32 -> 5000 | D57: =(C57*0.2)+C57 -> 6000 | E57: =D57*B57 -> 0 | F57: =B57*C57 -> 0 | G57: =E57-F57 -> 0
A58: ='BASE PAX'!A33 -> 0 | B58: ='BASE PAX'!B33 -> 0 | C58: ='BASE PAX'!C33 -> 0 | D58: =(C58*0.2)+C58 -> 0 | E58: =D58*B58 -> 0 | F58: =B58*C58 -> 0 | G58: =E58-F58 -> 0
A59: SUBTOTAL DRINKS | E59: =SUM(E52:E58) -> 0 | F59: =SUM(F52:F58) -> 0 | G59: =E59-F59 -> 0
A61: 4. ACTIVITIES | B61: QUANT. | C61: $ CUSTO | D61: $ VENDA | E61: SUBTOTAL | F61: SUBTOTAL $ CUSTO | G61: COMISSÕES
A62: ='BASE PAX'!A37 -> HOTTUBE | B62: ='BASE PAX'!B37 -> 0 | C62: ='BASE PAX'!C37 -> 12000 | D62: =C62*0.2+C62 -> 14400 | E62: =D62*B62 -> 0 | F62: =B62*C62 -> 0 | G62: =E62-F62 -> 0
A63: ='BASE PAX'!A38 -> TREKKING 1/2 DAY | B63: ='BASE PAX'!B38 -> 0 | C63: ='BASE PAX'!C38 -> 60000 | D63: =C63*0.2+C63 -> 72000 | E63: =D63*B63 -> 0 | F63: =B63*C63 -> 0 | G63: =E63-F63 -> 0
A64: ='BASE PAX'!A39 -> TREKKING FUK DAY | B64: ='BASE PAX'!B39 -> 0 | C64: ='BASE PAX'!C39 -> 90000 | D64: =C64*0.2+C64 -> 108000 | E64: =D64*B64 -> 0 | F64: =B64*C64 -> 0 | G64: =E64-F64 -> 0
A65: ='BASE PAX'!A40 -> FLOTADA FAMILIAR | B65: ='BASE PAX'!B40 -> 0 | C65: ='BASE PAX'!C40 -> 60000 | D65: =C65*0.2+C65 -> 72000 | E65: =D65*B65 -> 0 | F65: =B65*C65 -> 0 | G65: =E65-F65 -> 0
A66: ='BASE PAX'!A41 -> RAFTING 1/2 DAY | B66: ='BASE PAX'!B41 -> 0 | C66: ='BASE PAX'!C41 -> 75000 | D66: =C66*0.2+C66 -> 90000 | E66: =D66*B66 -> 0 | F66: =B66*C66 -> 0 | G66: =E66-F66 -> 0
A67: ='BASE PAX'!A42 -> RAFTING FULL DAY | B67: ='BASE PAX'!B42 -> 0 | C67: ='BASE PAX'!C42 -> 110000 | D67: =C67*0.2+C67 -> 132000 | E67: =D67*B67 -> 0 | F67: =B67*C67 -> 0 | G67: =E67-F67 -> 0
A68: ='BASE PAX'!A43 -> CABALGADA 1/2 DAy | B68: ='BASE PAX'!B43 -> 0 | C68: ='BASE PAX'!C43 -> 90000 | D68: =C68*0.2+C68 -> 108000 | E68: =D68*B68 -> 0 | F68: =B68*C68 -> 0 | G68: =E68-F68 -> 0
A69: ='BASE PAX'!A44 -> CABALGADA FULL DAY | B69: ='BASE PAX'!B44 -> 0 | C69: ='BASE PAX'!C44 -> 140000 | D69: =C69*0.2+C69 -> 168000 | E69: =D69*B69 -> 0 | F69: =B69*C69 -> 0 | G69: =E69-F69 -> 0
A70: ='BASE PAX'!A45 -> LANCHA YELCHO | B70: ='BASE PAX'!B45 -> 0 | C70: ='BASE PAX'!C45 -> 120000 | D70: =C70*0.2+C70 -> 144000 | E70: =D70*B70 -> 0 | F70: =B70*C70 -> 0 | G70: =E70-F70 -> 0
A71: ='BASE PAX'!A46 -> RECREACAO INFANTIL 3HS | B71: ='BASE PAX'!B46 -> 0 | C71: ='BASE PAX'!C46 -> 30000 | D71: =C71*0.2+C71 -> 36000 | E71: =D71*B71 -> 0 | F71: =B71*C71 -> 0 | G71: =E71-F71 -> 0
A72: SUBTOTAL ACTIVITIES | E72: =SUM(E62:E71) -> 0 | F72: =B72*C72 -> 0 | G72: =E72-F72 -> 0
A74: 5. TRANSPORT | B74: QUANT. | C74: $ CUSTO | D74: $ VENDA | E74: SUBTOTAL | F74: SUBTOTAL CUSTO | G74: COMISSÕES
A75: ='BASE PAX'!A50 -> TRANSFER AEROPORTO CHEGADA | B75: ='BASE PAX'!B50 -> 0 | C75: 50000 | D75: =C75*0.2+C75 -> 60000 | E75: =D75*B75 -> 0 | F75: =B75*C75 -> 0 | G75: =E75-F75 -> 0
A76: ='BASE PAX'!A51 -> TRANSFER AEROPORTO PARTIDA | B76: ='BASE PAX'!B51 -> 0 | C76: ='BASE PAX'!C51 -> 80000 | D76: =C76*0.2+C76 -> 96000 | E76: =D76*B76 -> 0 | F76: =B76*C76 -> 0 | G76: =E76-F76 -> 0
A77: ='BASE PAX'!A52 -> TRANSFERS INTERNO | B77: ='BASE PAX'!B52 -> 0 | C77: ='BASE PAX'!C52 -> 18000 | D77: =C77*0.2+C77 -> 21600 | E77: =D77*B77 -> 0 | F77: =B77*C77 -> 0 | G77: =E77-F77 -> 0
A78: ='BASE PAX'!A53 -> EXTRAS 1 | B78: ='BASE PAX'!B53 -> 0 | C78: ='BASE PAX'!C53 -> 150000 | D78: =C78*0.2+C78 -> 180000 | E78: =D78*B78 -> 0 | F78: =B78*C78 -> 0 | G78: =E78-F78 -> 0
A79: ='BASE PAX'!A54 -> EXTRAS 2 | B79: ='BASE PAX'!B54 -> 0 | C79: ='BASE PAX'!C54 -> 0 | D79: =C79*0.2+C79 -> 0 | E79: =D79*B79 -> 0 | F79: =B79*C79 -> 0 | G79: =E79-F79 -> 0
A80: SUBTOTAL TRANSPORT | E80: =SUM(E75:E79) -> 0 | F80: =SUM(F75:F79) -> 0 | G80: =E80-F80 -> 0
A82: 6. EXPERIENCES | B82: QUANT. | C82: $ CUSTO | D82: $ VENDA | E82: SUBTOTAL | F82: SUBTOTAL CUSTO | G82: COMISSÕES
A83: ='BASE PAX'!A58 -> WS INSTRUCTOR | B83: ='BASE PAX'!B58 -> 0 | C83: ='BASE PAX'!C58 -> 3415000 | D83: =(C83*0.15)+C83 -> 3927250 | E83: =D83*B83 -> 0 | F83: =B83*C83 -> 0 | G83: =E83-F83 -> 0
A84: ='BASE PAX'!A59 -> PRODUCER FEE | B84: ='BASE PAX'!B59 -> 0 | C84: ='BASE PAX'!C59 -> 180000 | D84: =(C84*0.15)+C84 -> 207000 | E84: =D84*B84 -> 0 | F84: =B84*C84 -> 0 | G84: =E84-F84 -> 0
A85: ='BASE PAX'!A60 -> 0 | B85: ='BASE PAX'!B60 -> 0 | C85: ='BASE PAX'!C60 -> 20000 | D85: =(C85*0.15)+C85 -> 23000 | E85: =D85*B85 -> 0 | F85: =B85*C85 -> 0 | G85: =E85-F85 -> 0
A86: SUBTOTAL EXPERIENCES | E86: =SUM(E83:E85) -> 0 | F86: =SUM(F81:F85) -> 0 | G86: =E86-F86 -> 0
A88: 7. EXTRAS ( por cabin ) | B88: USOS | C88: $ CUSTO | D88: $ VENDA | E88: SUBTOTAL | G88: COMISSÕES
A89: ='BASE PAX'!A64 -> COORDENAÇÃO PRODUÇÃO | B89: ='BASE PAX'!B64 -> 0 | C89: ='BASE PAX'!C64 -> 50000 | D89: ='BASE PAX'!D64 -> 0 | E89: =D89*B89 -> 0 | G89: =E89*0.2 -> 0
A90: ='BASE PAX'!A65 -> EXTRA MÃO DE OBRA | B90: ='BASE PAX'!B65 -> 0 | C90: ='BASE PAX'!C65 -> 50000 | D90: ='BASE PAX'!D65 -> 0 | E90: =D90*B90 -> 0 | G90: =E90*0.2 -> 0
A91: ='BASE PAX'!A66 -> TAXA LIMPEZA CHECK IN / CHECKOUT | B91: ='BASE PAX'!B66 -> 0 | C91: ='BASE PAX'!C66 -> 40000 | D91: ='BASE PAX'!D66 -> 0 | E91: =D91*B91 -> 0 | G91: =E91*0.2 -> 0
A92: ='BASE PAX'!A67 -> TAXA LIMPEZA DIARIA | B92: ='BASE PAX'!B67 -> 0 | C92: ='BASE PAX'!C67 -> 30000 | D92: ='BASE PAX'!D67 -> 0 | E92: =D92*B92 -> 0 | G92: =E92*0.2 -> 0
A93: ='BASE PAX'!A68 -> SOUVENIR | B93: ='BASE PAX'!B68 -> 0 | C93: ='BASE PAX'!C68 -> 15000 | D93: ='BASE PAX'!D68 -> 0 | E93: =D93*B93 -> 0 | G93: =E93*0.2 -> 0
A94: ='BASE PAX'!A69 -> ASSISTENTE COORDENAÇÃO | B94: ='BASE PAX'!B69 -> 0 | C94: ='BASE PAX'!C69 -> 30000 | D94: ='BASE PAX'!D69 -> 0 | E94: =D94*B94 -> 0 | G94: =E94*0.2 -> 0
A95: SUBTOTAL EXTRAS | E95: =SUM(E89:E94) -> 0 | G95: =SUM(G89:G94) -> 0
A97: 8. QUINCHO (por cabin) | B97: USOS | C97: $ CUSTO | D97: $ VENDA | E97: SUBTOTAL
A98: ='BASE PAX'!A73 -> QUINCHO DAY USE / CABIN | B98: ='BASE PAX'!B73 -> 0 | C98: ='BASE PAX'!C73 -> 15000 | D98: =C98+(C98*0.2) -> 18000 | E98: =D98*B98 -> 0
A99: SUBTOTAL QUINCHO | E99: =E98 -> 0

Sheet BUDGET CHAITEN 3
C3: COIGUE
A5: TOTAL PAX ADULT | B5: 3 | E5: CHAITEN
A6: TOTAL PAX INFANT | B6: 0 | D6: BUDGET TOTAL | F6: =D21 -> 0
A7: CHECK IN. | B7: =CALENDAR!C2 -> 0 | D7: SUBTOTAL PAGO | F7: =SUM(F12:F20) -> 0
A8: CHECK OUT. | B8: =CALENDAR!C3 -> 0 | D8: SUBTOTAL A RECEBER | F8: =F6-F7 -> 0
A9: TOTAL NIGHTS. | B9: =CALENDAR!J2 -> 0 | D9: TIP |
A11: RESUMO. | B11: PREÇO CLIENTE CASH CLP $ | C11: TAXA CC | D11: PREÇO CLIENTE PAGTO CC $ | F11: =E5 -> CHAITEN | I11: CONTROLE PAGAMENTOS
C12: 0.05 | I12: DATA | J12: VALOR PAGO CLP $ | K12: FORMA PAGTO
A13: 1.LODGING | B13: =G28 -> 0 | C13: =B13*$C$12 -> 0 | D13: =B13+(B13*$C$12) -> 0
A14: 2.FOOD | B14: =J49 -> 0 | C14: =B14*$C$12 -> 0 | D14: =B14+(B14*$C$12) -> 0 | F14: =A14 -> 2.FOOD | G14: =G49 -> 0
A15: 3.DRINKS | B15: =E59 -> 0 | C15: =B15*$C$12 -> 0 | D15: =B15+(B15*$C$12) -> 0 | F15: =A15 -> 3.DRINKS | G15: =G59 -> 0
A16: 4. ACTIVITIES | B16: =$E$72 -> 0 | C16: =B16*$C$12 -> 0 | D16: =B16+(B16*$C$12) -> 0 | F16: =A16 -> 4. ACTIVITIES | G16: =G72 -> 0
A17: 5.TRANSPORT | B17: =$E$80 -> 0 | C17: =B17*$C$12 -> 0 | D17: =B17+(B17*$C$12) -> 0 | F17: =A17 -> 5.TRANSPORT | G17: =G80 -> 0
A18: 6.EXPERIENCES | B18: =$E$86 -> 0 | C18: =B18*$C$12 -> 0 | D18: =B18+(B18*$C$12) -> 0 | F18: =A18 -> 6.EXPERIENCES | G18: =G86 -> 0
A19: 7.EXTRAS | B19: =$E$95 -> 0 | C19: =B19*$C$12 -> 0 | D19: =B19+(B19*$C$12) -> 0 | F19: =A19 -> 7.EXTRAS | G19: =G95 -> 0
A20: 8. QUINCHO | B20: =$E$99 -> 0 | C20: =B20*$C$12 -> 0 | D20: =B20+(B20*$C$12) -> 0 | F20: SUBTOTAL COMISSÕES | G20: =G14+G15+G16+G17+G18+G19 -> 0
A21: SUBTOTAL 1 | B21: =SUM(B13:B20) -> 0 | D21: =SUM(D13:D20) -> 0
A23: 1. LODGING | B23: QUANT. | C23: $ CABIN / DIA | D23: $ ADICIONAL / DIA | E23: BASE CÁLCULO | F23: DESCONTOS | G23: $ SUBTOTAL
A24: CHAITEN (até 2 pax) - até 06 noites | B24: 0 | C24: =288190.9 -> 288190.9 | E24: =(C24+D24)*$B$9*B24 -> 0 | F24: 0 | G24: =E24-(E24*F24) -> 0
A25: CHAITEN ( 2 + baby) - até 06 noites | B25: 1 | C25: =288190.9 -> 288190.9 | D25: 50000 | E25: =(C25+D25)*$B$9*B25 -> 0 | F25: 0 | G25: =E25-(E25*F25) -> 0
A26: CHAITEN (até 2 pax) - 7 noites ou + | B26: 0 | C26: =259371.81 -> 259371.81 | E26: =(C26+D26)*$B$9*B26 -> 0 | F26: 0 | G26: =E26-(E26*F26) -> 0
A27: CHAITEN ( 2 + baby) - 7 noites ou + | B27: 0 | C27: =259371.81 -> 259371.81 | D27: 50000 | E27: =(C27+D27)*$B$9*B27 -> 0 | F27: 0 | G27: =E27-(E27*F27) -> 0
A28: SUBTOTAL LODGING | G28: =SUM(G24:G27) -> 0
A30: 2. FOOD | B30: QUANT. | C30: $ CUSTO | D30: $ VENDA | E30: SUBTOTAL $ VENDA | F30: SUBTOTAL $ CUSTO | G30: COMISSÕES
A31: ='BASE PAX'!A6 -> BREAKFAST | B31: =(B5*B9*'BASE PAX'!G6)+('BASE PAX'!H6*B6*B9) -> 0 | F31: =B31*C31 -> 0 | G31: =0.2*B31 -> 0 | H31: ='BASE PAX'!A6 -> BREAKFAST | I31: =B31 -> 0
A32: ='BASE PAX'!A7 -> LUNCH 1 | B32: =($B$5+($B$6*0.5))*'BASE PAX'!B7 -> 0 | C32: ='BASE PAX'!C7 -> 40000 | D32: ='BASE PAX'!D7 -> 48000 | E32: =D32*B32 -> 0 | F32: =B32*C32 -> 0 | G32: =E32-F32 -> 0
A33: ='BASE PAX'!A8 -> LUNCH 2 | B33: =($B$5+($B$6*0.5))*'BASE PAX'!B8 -> 0 | C33: ='BASE PAX'!C8 -> 40000 | D33: ='BASE PAX'!D8 -> 48000 | E33: =D33*B33 -> 0 | F33: =B33*C33 -> 0 | G33: =E33-F33 -> 0
A34: ='BASE PAX'!A9 -> LUNCH 3 | B34: =($B$5+($B$6*0.5))*'BASE PAX'!B9 -> 0 | C34: ='BASE PAX'!C9 -> 40000 | D34: ='BASE PAX'!D9 -> 48000 | E34: =D34*B34 -> 0 | F34: =B34*C34 -> 0 | G34: =E34-F34 -> 0
A35: ='BASE PAX'!A10 -> LUNCH 4 | B35: =($B$5+($B$6*0.5))*'BASE PAX'!B10 -> 0 | C35: ='BASE PAX'!C10 -> 45000 | D35: ='BASE PAX'!D10 -> 54000 | E35: =D35*B35 -> 0 | F35: =B35*C35 -> 0 | G35: =E35-F35 -> 0
A36: ='BASE PAX'!A11 -> LUNCH 5 | B36: =($B$5+($B$6*0.6))*'BASE PAX'!B11 -> 0 | C36: ='BASE PAX'!C11 -> 50000 | D36: ='BASE PAX'!D11 -> 60000 | E36: =D36*B36 -> 0 | F36: =B36*C36 -> 0 | G36: =E36-F36 -> 0
A37: ='BASE PAX'!A12 -> LUNCH 6 | B37: =($B$5+($B$6*0.5))*'BASE PAX'!B12 -> 0 | C37: ='BASE PAX'!C12 -> 0 | D37: ='BASE PAX'!D12 -> 0 | E37: =D37*B37 -> 0 | F37: =B37*C37 -> 0 | G37: =E37-F37 -> 0
A38: ='BASE PAX'!A13 -> LUNCH 7 | B38: =($B$5+($B$6*0.5))*'BASE PAX'!B13 -> 0 | C38: ='BASE PAX'!C13 -> 5000 | D38: ='BASE PAX'!D13 -> 6000 | E38: =D38*B38 -> 0 | F38: =B38*C38 -> 0 | G38: =E38-F38 -> 0
A39: ='BASE PAX'!A14 -> SNACKS | B39: =($B$5+$B$6)*'BASE PAX'!B14 -> 0 | C39: ='BASE PAX'!C14 -> 8000 | D39: ='BASE PAX'!D14 -> 9600 | E39: =D39*B39 -> 0 | F39: =B39*C39 -> 0 | G39: =E39-F39 -> 0
A40: ='BASE PAX'!A15 -> DINNER 1 | B40: =($B$5+($B$6*0.6))*'BASE PAX'!B15 -> 0 | C40: ='BASE PAX'!C15 -> 70000 | D40: ='BASE PAX'!D15 -> 84000 | E40: =D40*B40 -> 0 | F40: =B40*C40 -> 0 | G40: =E40-F40 -> 0
A41: ='BASE PAX'!A16 -> DINNER 2 | B41: =($B$5+($B$6*0.6))*'BASE PAX'!B16 -> 0 | C41: ='BASE PAX'!C16 -> 25000 | D41: ='BASE PAX'!D16 -> 30000 | E41: =D41*B41 -> 0 | F41: =B41*C41 -> 0 | G41: =E41-F41 -> 0
A42: ='BASE PAX'!A17 -> DINNER 3 | B42: =($B$5+($B$6*0.6))*'BASE PAX'!B17 -> 0 | C42: ='BASE PAX'!C17 -> 50000 | D42: ='BASE PAX'!D17 -> 60000 | E42: =D42*B42 -> 0 | F42: =B42*C42 -> 0 | G42: =E42-F42 -> 0
A43: ='BASE PAX'!A18 -> DINNER 4 | B43: =($B$5+($B$6*0.5))*'BASE PAX'!B18 -> 0 | C43: ='BASE PAX'!C18 -> 65000 | D43: ='BASE PAX'!D18 -> 78000 | E43: =D43*B43 -> 0 | F43: =B43*C43 -> 0 | G43: =E43-F43 -> 0
A44: ='BASE PAX'!A19 -> DINNER 5 | B44: =($B$5+($B$6*0.6))*'BASE PAX'!B19 -> 0 | C44: ='BASE PAX'!C19 -> 75000 | D44: ='BASE PAX'!D19 -> 90000 | E44: =D44*B44 -> 0 | F44: =B44*C44 -> 0 | G44: =E44-F44 -> 0
A45: ='BASE PAX'!A20 -> DINNER 6 | B45: =($B$5+($B$6*0.5))*'BASE PAX'!B20 -> 0 | C45: ='BASE PAX'!C20 -> 0 | D45: ='BASE PAX'!D20 -> 0 | E45: =D45*B45 -> 0 | F45: =B45*C45 -> 0 | G45: =E45-F45 -> 0
A46: ='BASE PAX'!A21 -> DINNER 7 | B46: =($B$5+($B$6*0.6))*'BASE PAX'!B21 -> 0 | C46: ='BASE PAX'!C21 -> 75000 | D46: ='BASE PAX'!D21 -> 90000 | E46: =D46*B46 -> 0 | F46: =B46*C46 -> 0 | G46: =E46-F46 -> 0
A47: ='BASE PAX'!A22 -> QUANT. TOTAL | PADRAO ALMOÇO | B47: ='BASE PAX'!B22 -> 0 | G47: =0.2*I47 -> 0 | H47: ='BASE PAX'!A22 -> QUANT. TOTAL | PADRAO ALMOÇO | I47: =(B5*B47*'BASE PAX'!G22)+(B6*B47*'BASE PAX'!H22) -> 0
A48: ='BASE PAX'!A23 -> QUANT. TOTAL | PADRAO JANTAR | B48: ='BASE PAX'!B23 -> 0 | G48: =0.2*I48 -> 0 | H48: ='BASE PAX'!A23 -> QUANT. TOTAL | PADRAO JANTAR | I48: =(B5*B48*'BASE PAX'!G23)+(B6*B48*'BASE PAX'!H23) -> 0
A49: SUBTOTAL FOOD | E49: =SUM(E31:E48) -> 0 | F49: =SUM(F31:F48) -> 0 | G49: =SUM(G31:G48) -> 0 | H49: SUBTOTAL | I49: =I31+I47+I48 -> 0 | J49: =I49+E49 -> 0 | K49: TOTAL FOOD
A51: 3. DRINKS (por cabin) | B51: QUANT. | C51: $ CUSTO | D51: $ VENDA | E51: SUBTOTAL | F51: SUBTOTAL $ CUSTO | G51: COMISSÕES
A52: ='BASE PAX'!A27 -> SUCOS | B52: ='BASE PAX'!B27 -> 0 | C52: ='BASE PAX'!C27 -> 0 | D52: =(C52*0.2)+C52 -> 0 | E52: =D52*B52 -> 0 | F52: =B52*C52 -> 0 | G52: =E52-F52 -> 0
A53: ='BASE PAX'!A28 -> SUCOS | B53: ='BASE PAX'!B28 -> 0 | C53: ='BASE PAX'!C28 -> 0 | D53: =(C53*0.2)+C53 -> 0 | E53: =D53*B53 -> 0 | F53: =B53*C53 -> 0 | G53: =E53-F53 -> 0
A54: ='BASE PAX'!A29 -> CERVEJAS | B54: ='BASE PAX'!B29 -> 0 | C54: ='BASE PAX'!C29 -> 2000 | D54: =(C54*0.2)+C54 -> 2400 | E54: =D54*B54 -> 0 | F54: =B54*C54 -> 0 | G54: =E54-F54 -> 0
A55: ='BASE PAX'!A30 -> VINHOS | B55: ='BASE PAX'!B30 -> 0 | C55: ='BASE PAX'!C30 -> 8000 | D55: =(C55*0.2)+C55 -> 9600 | E55: =D55*B55 -> 0 | F55: =B55*C55 -> 0 | G55: =E55-F55 -> 0
A56: ='BASE PAX'!A31 -> DRINKS | B56: ='BASE PAX'!B31 -> 0 | C56: ='BASE PAX'!C31 -> 15000 | D56: =(C56*0.2)+C56 -> 18000 | E56: =D56*B56 -> 0 | F56: =B56*C56 -> 0 | G56: =E56-F56 -> 0
A57: ='BASE PAX'!A32 -> COOLER | B57: ='BASE PAX'!B32 -> 0 | C57: ='BASE PAX'!C32 -> 5000 | D57: =(C57*0.2)+C57 -> 6000 | E57: =D57*B57 -> 0 | F57: =B57*C57 -> 0 | G57: =E57-F57 -> 0
A58: ='BASE PAX'!A33 -> 0 | B58: ='BASE PAX'!B33 -> 0 | C58: ='BASE PAX'!C33 -> 0 | D58: =(C58*0.2)+C58 -> 0 | E58: =D58*B58 -> 0 | F58: =B58*C58 -> 0 | G58: =E58-F58 -> 0
A59: SUBTOTAL DRINKS | E59: =SUM(E52:E58) -> 0 | F59: =SUM(F52:F58) -> 0 | G59: =E59-F59 -> 0
A61: 4. ACTIVITIES | B61: QUANT. | C61: $ CUSTO | D61: $ VENDA | E61: SUBTOTAL | F61: SUBTOTAL $ CUSTO | G61: COMISSÕES
A62: ='BASE PAX'!A37 -> HOTTUBE | B62: ='BASE PAX'!B37 -> 0 | C62: ='BASE PAX'!C37 -> 12000 | D62: =C62*0.2+C62 -> 14400 | E62: =D62*B62 -> 0 | F62: =B62*C62 -> 0 | G62: =E62-F62 -> 0
A63: ='BASE PAX'!A38 -> TREKKING 1/2 DAY | B63: ='BASE PAX'!B38 -> 0 | C63: ='BASE PAX'!C38 -> 60000 | D63: =C63*0.2+C63 -> 72000 | E63: =D63*B63 -> 0 | F63: =B63*C63 -> 0 | G63: =E63-F63 -> 0
A64: ='BASE PAX'!A39 -> TREKKING FUK DAY | B64: ='BASE PAX'!B39 -> 0 | C64: ='BASE PAX'!C39 -> 90000 | D64: =C64*0.2+C64 -> 108000 | E64: =D64*B64 -> 0 | F64: =B64*C64 -> 0 | G64: =E64-F64 -> 0
A65: ='BASE PAX'!A40 -> FLOTADA FAMILIAR | B65: ='BASE PAX'!B40 -> 0 | C65: ='BASE PAX'!C40 -> 60000 | D65: =C65*0.2+C65 -> 72000 | E65: =D65*B65 -> 0 | F65: =B65*C65 -> 0 | G65: =E65-F65 -> 0
A66: ='BASE PAX'!A41 -> RAFTING 1/2 DAY | B66: ='BASE PAX'!B41 -> 0 | C66: ='BASE PAX'!C41 -> 75000 | D66: =C66*0.2+C66 -> 90000 | E66: =D66*B66 -> 0 | F66: =B66*C66 -> 0 | G66: =E66-F66 -> 0
A67: ='BASE PAX'!A42 -> RAFTING FULL DAY | B67: ='BASE PAX'!B42 -> 0 | C67: ='BASE PAX'!C42 -> 110000 | D67: =C67*0.2+C67 -> 132000 | E67: =D67*B67 -> 0 | F67: =B67*C67 -> 0 | G67: =E67-F67 -> 0
A68: ='BASE PAX'!A43 -> CABALGADA 1/2 DAy | B68: ='BASE PAX'!B43 -> 0 | C68: ='BASE PAX'!C43 -> 90000 | D68: =C68*0.2+C68 -> 108000 | E68: =D68*B68 -> 0 | F68: =B68*C68 -> 0 | G68: =E68-F68 -> 0
A69: ='BASE PAX'!A44 -> CABALGADA FULL DAY | B69: ='BASE PAX'!B44 -> 0 | C69: ='BASE PAX'!C44 -> 140000 | D69: =C69*0.2+C69 -> 168000 | E69: =D69*B69 -> 0 | F69: =B69*C69 -> 0 | G69: =E69-F69 -> 0
A70: ='BASE PAX'!A45 -> LANCHA YELCHO | B70: ='BASE PAX'!B45 -> 0 | C70: ='BASE PAX'!C45 -> 120000 | D70: =C70*0.2+C70 -> 144000 | E70: =D70*B70 -> 0 | F70: =B70*C70 -> 0 | G70: =E70-F70 -> 0
A71: ='BASE PAX'!A46 -> RECREACAO INFANTIL 3HS | B71: ='BASE PAX'!B46 -> 0 | C71: ='BASE PAX'!C46 -> 30000 | D71: =C71*0.2+C71 -> 36000 | E71: =D71*B71 -> 0 | F71: =B71*C71 -> 0 | G71: =E71-F71 -> 0
A72: SUBTOTAL ACTIVITIES | E72: =SUM(E62:E71) -> 0 | F72: =B72*C72 -> 0 | G72: =E72-F72 -> 0
A74: 5. TRANSPORT | B74: QUANT. | C74: $ CUSTO | D74: $ VENDA | E74: SUBTOTAL | F74: SUBTOTAL CUSTO | G74: COMISSÕES
A75: ='BASE PAX'!A50 -> TRANSFER AEROPORTO CHEGADA | B75: ='BASE PAX'!B50 -> 0 | C75: 50000 | D75: =C75*0.2+C75 -> 60000 | E75: =D75*B75 -> 0 | F75: =B75*C75 -> 0 | G75: =E75-F75 -> 0
A76: ='BASE PAX'!A51 -> TRANSFER AEROPORTO PARTIDA | B76: ='BASE PAX'!B51 -> 0 | C76: ='BASE PAX'!C51 -> 80000 | D76: =C76*0.2+C76 -> 96000 | E76: =D76*B76 -> 0 | F76: =B76*C76 -> 0 | G76: =E76-F76 -> 0
A77: ='BASE PAX'!A52 -> TRANSFERS INTERNO | B77: ='BASE PAX'!B52 -> 0 | C77: ='BASE PAX'!C52 -> 18000 | D77: =C77*0.2+C77 -> 21600 | E77: =D77*B77 -> 0 | F77: =B77*C77 -> 0 | G77: =E77-F77 -> 0
A78: ='BASE PAX'!A53 -> EXTRAS 1 | B78: ='BASE PAX'!B53 -> 0 | C78: ='BASE PAX'!C53 -> 150000 | D78: =C78*0.2+C78 -> 180000 | E78: =D78*B78 -> 0 | F78: =B78*C78 -> 0 | G78: =E78-F78 -> 0
A79: ='BASE PAX'!A54 -> EXTRAS 2 | B79: ='BASE PAX'!B54 -> 0 | C79: ='BASE PAX'!C54 -> 0 | D79: =C79*0.2+C79 -> 0 | E79: =D79*B79 -> 0 | F79: =B79*C79 -> 0 | G79: =E79-F79 -> 0
A80: SUBTOTAL TRANSPORT | E80: =SUM(E75:E79) -> 0 | F80: =SUM(F75:F79) -> 0 | G80: =E80-F80 -> 0
A82: 6. EXPERIENCES | B82: QUANT. | C82: $ CUSTO | D82: $ VENDA | E82: SUBTOTAL | F82: SUBTOTAL CUSTO | G82: COMISSÕES
A83: ='BASE PAX'!A58 -> WS INSTRUCTOR | B83: ='BASE PAX'!B58 -> 0 | C83: ='BASE PAX'!C58 -> 3415000 | D83: =(C83*0.15)+C83 -> 3927250 | E83: =D83*B83 -> 0 | F83: =B83*C83 -> 0 | G83: =E83-F83 -> 0
A84: ='BASE PAX'!A59 -> PRODUCER FEE | B84: ='BASE PAX'!B59 -> 0 | C84: ='BASE PAX'!C59 -> 180000 | D84: =(C84*0.15)+C84 -> 207000 | E84: =D84*B84 -> 0 | F84: =B84*C84 -> 0 | G84: =E84-F84 -> 0
A85: ='BASE PAX'!A60 -> 0 | B85: ='BASE PAX'!B60 -> 0 | C85: ='BASE PAX'!C60 -> 20000 | D85: =(C85*0.15)+C85 -> 23000 | E85: =D85*B85 -> 0 | F85: =B85*C85 -> 0 | G85: =E85-F85 -> 0
A86: SUBTOTAL EXPERIENCES | E86: =SUM(E83:E85) -> 0 | F86: =SUM(F81:F85) -> 0 | G86: =E86-F86 -> 0
A88: 7. EXTRAS ( por cabin ) | B88: USOS | C88: $ CUSTO | D88: $ VENDA | E88: SUBTOTAL | G88: COMISSÕES
A89: ='BASE PAX'!A64 -> COORDENAÇÃO PRODUÇÃO | B89: ='BASE PAX'!B64 -> 0 | C89: ='BASE PAX'!C64 -> 50000 | D89: ='BASE PAX'!D64 -> 0 | E89: =D89*B89 -> 0 | G89: =E89*0.2 -> 0
A90: ='BASE PAX'!A65 -> EXTRA MÃO DE OBRA | B90: ='BASE PAX'!B65 -> 0 | C90: ='BASE PAX'!C65 -> 50000 | D90: ='BASE PAX'!D65 -> 0 | E90: =D90*B90 -> 0 | G90: =E90*0.2 -> 0
A91: ='BASE PAX'!A66 -> TAXA LIMPEZA CHECK IN / CHECKOUT | B91: ='BASE PAX'!B66 -> 0 | C91: ='BASE PAX'!C66 -> 40000 | D91: ='BASE PAX'!D66 -> 0 | E91: =D91*B91 -> 0 | G91: =E91*0.2 -> 0
A92: ='BASE PAX'!A67 -> TAXA LIMPEZA DIARIA | B92: ='BASE PAX'!B67 -> 0 | C92: ='BASE PAX'!C67 -> 30000 | D92: ='BASE PAX'!D67 -> 0 | E92: =D92*B92 -> 0 | G92: =E92*0.2 -> 0
A93: ='BASE PAX'!A68 -> SOUVENIR | B93: ='BASE PAX'!B68 -> 0 | C93: ='BASE PAX'!C68 -> 15000 | D93: ='BASE PAX'!D68 -> 0 | E93: =D93*B93 -> 0 | G93: =E93*0.2 -> 0
A94: ='BASE PAX'!A69 -> ASSISTENTE COORDENAÇÃO | B94: ='BASE PAX'!B69 -> 0 | C94: ='BASE PAX'!C69 -> 30000 | D94: ='BASE PAX'!D69 -> 0 | E94: =D94*B94 -> 0 | G94: =E94*0.2 -> 0
A95: SUBTOTAL EXTRAS | E95: =SUM(E89:E94) -> 0 | G95: =SUM(G89:G94) -> 0
A97: 8. QUINCHO (por cabin) | B97: USOS | C97: $ CUSTO | D97: $ VENDA | E97: SUBTOTAL
A98: ='BASE PAX'!A73 -> QUINCHO DAY USE / CABIN | B98: ='BASE PAX'!B73 -> 0 | C98: ='BASE PAX'!C73 -> 15000 | D98: =C98+(C98*0.2) -> 18000 | E98: =D98*B98 -> 0
A99: SUBTOTAL QUINCHO | E99: =E98 -> 0

Sheet BUDGET CORCOVADO 1
C3: COIGUE
A5: TOTAL PAX ADULT | B5: 1 | D5: CORCOVADO
A6: TOTAL PAX INFANT | B6: 0 | D6: BUDGET TOTAL | F6: =D21 -> 0
A7: CHECK IN. | B7: =CALENDAR!C2 -> 0 | D7: SUBTOTAL PAGO | F7: =SUM(F12:F20) -> 0
A8: CHECK OUT. | B8: =CALENDAR!C3 -> 0 | D8: SUBTOTAL A RECEBER | F8: =F6-F7 -> 0
A9: TOTAL NIGHTS. | B9: =CALENDAR!J2 -> 0 | D9: TIP |
A11: RESUMO. | B11: PREÇO CLIENTE CASH CLP $ | C11: TAXA CC | D11: PREÇO CLIENTE PAGTO CC $ | F11: =D5 -> CORCOVADO | I11: CONTROLE PAGAMENTOS
C12: 0.05 | I12: DATA | J12: VALOR PAGO CLP $ | K12: FORMA PAGTO
A13: 1.LODGING | B13: =G28 -> 0 | C13: =B13*$C$12 -> 0 | D13: =B13+(B13*$C$12) -> 0
A14: 2.FOOD | B14: =J49 -> 0 | C14: =B14*$C$12 -> 0 | D14: =B14+(B14*$C$12) -> 0 | F14: =A14 -> 2.FOOD | G14: =G49 -> 0
A15: 3.DRINKS | B15: =E59 -> 0 | C15: =B15*$C$12 -> 0 | D15: =B15+(B15*$C$12) -> 0 | F15: =A15 -> 3.DRINKS | G15: =G59 -> 0
A16: 4. ACTIVITIES | B16: =$E$72 -> 0 | C16: =B16*$C$12 -> 0 | D16: =B16+(B16*$C$12) -> 0 | F16: =A16 -> 4. ACTIVITIES | G16: =G72 -> 0
A17: 5.TRANSPORT | B17: =$E$80 -> 0 | C17: =B17*$C$12 -> 0 | D17: =B17+(B17*$C$12) -> 0 | F17: =A17 -> 5.TRANSPORT | G17: =G80 -> 0
A18: 6.EXPERIENCES | B18: =$E$86 -> 0 | C18: =B18*$C$12 -> 0 | D18: =B18+(B18*$C$12) -> 0 | F18: =A18 -> 6.EXPERIENCES | G18: =G86 -> 0
A19: 7.EXTRAS | B19: =$E$95 -> 0 | C19: =B19*$C$12 -> 0 | D19: =B19+(B19*$C$12) -> 0 | F19: =A19 -> 7.EXTRAS | G19: =G95 -> 0
A20: 8. QUINCHO | B20: =$E$99 -> 0 | C20: =B20*$C$12 -> 0 | D20: =B20+(B20*$C$12) -> 0 | F20: SUBTOTAL COMISSÕES | G20: =G14+G15+G16+G17+G18+G19 -> 0
A21: SUBTOTAL 1 | B21: =SUM(B13:B20) -> 0 | D21: =SUM(D13:D20) -> 0
A23: 1. LODGING | B23: QUANT. | C23: $ CABIN / DIA | D23: $ ADICIONAL / DIA | E23: BASE CÁLCULO | F23: DESCONTOS | G23: $ SUBTOTAL
A24: CORCOVADO (até 4 pax) - até 06 noites | B24: 1 | C24: =398381.8 -> 398381.8 | E24: =(C24+D24)*$B$9*B24 -> 0 | F24: 0 | G24: =E24-(E24*F24) -> 0
A25: CORCOVADO ( até 4 + baby) - até 06 noites | B25: 0 | C25: =398381.8 -> 398381.8 | D25: 50000 | E25: =(C25+D25)*$B$9*B25 -> 0 | F25: 0 | G25: =E25-(E25*F25) -> 0
A26: CORCOVADO (até 4 pax) - 7 noites ou + | B26: 0 | C26: =358543.62 -> 358543.62 | E26: =(C26+D26)*$B$9*B26 -> 0 | F26: 0 | G26: =E26-(E26*F26) -> 0
A27: CORCOVADO ( até 4 + baby) - 7 noites ou + | B27: 0 | C27: =358543.62 -> 358543.62 | D27: 50000 | E27: =(C27+D27)*$B$9*B27 -> 0 | F27: 0 | G27: =E27-(E27*F27) -> 0
A28: SUBTOTAL LODGING | G28: =SUM(G24:G27) -> 0
A30: 2. FOOD | B30: QUANT. | C30: $ CUSTO | D30: $ VENDA | E30: SUBTOTAL $ VENDA | F30: SUBTOTAL $ CUSTO | G30: COMISSÕES
A31: ='BASE PAX'!A6 -> BREAKFAST | B31: =(B5*B9*'BASE PAX'!G6)+('BASE PAX'!H6*B6*B9) -> 0 | E31: 0 | F31: =B31*C31 -> 0 | G31: =0.2*B31 -> 0 | H31: =A31 -> BREAKFAST | I31: =B31 -> 0
A32: ='BASE PAX'!A7 -> LUNCH 1 | B32: =($B$5+$B$6)*'BASE PAX'!B7 -> 0 | C32: ='BASE PAX'!C7 -> 40000 | D32: ='BASE PAX'!D7 -> 48000 | E32: =D32*B32 -> 0 | F32: =B32*C32 -> 0 | G32: =E32-F32 -> 0
A33: ='BASE PAX'!A8 -> LUNCH 2 | B33: =($B$5+$B$6)*'BASE PAX'!B8 -> 0 | C33: ='BASE PAX'!C8 -> 40000 | D33: ='BASE PAX'!D8 -> 48000 | E33: =D33*B33 -> 0 | F33: =B33*C33 -> 0 | G33: =E33-F33 -> 0
A34: ='BASE PAX'!A9 -> LUNCH 3 | B34: =($B$5+$B$6)*'BASE PAX'!B9 -> 0 | C34: ='BASE PAX'!C9 -> 40000 | D34: ='BASE PAX'!D9 -> 48000 | E34: =D34*B34 -> 0 | F34: =B34*C34 -> 0 | G34: =E34-F34 -> 0
A35: ='BASE PAX'!A10 -> LUNCH 4 | B35: =($B$5+$B$6)*'BASE PAX'!B10 -> 0 | C35: ='BASE PAX'!C10 -> 45000 | D35: ='BASE PAX'!D10 -> 54000 | E35: =D35*B35 -> 0 | F35: =B35*C35 -> 0 | G35: =E35-F35 -> 0
A36: ='BASE PAX'!A11 -> LUNCH 5 | B36: =($B$5+$B$6)*'BASE PAX'!B11 -> 0 | C36: ='BASE PAX'!C11 -> 50000 | D36: ='BASE PAX'!D11 -> 60000 | E36: =D36*B36 -> 0 | F36: =B36*C36 -> 0 | G36: =E36-F36 -> 0
A37: ='BASE PAX'!A12 -> LUNCH 6 | B37: =($B$5+$B$6)*'BASE PAX'!B12 -> 0 | C37: ='BASE PAX'!C12 -> 0 | D37: ='BASE PAX'!D12 -> 0 | E37: =D37*B37 -> 0 | F37: =B37*C37 -> 0 | G37: =E37-F37 -> 0
